Workbook

Sheet Financials
A1: The Home Depot, Inc. | B1: ACTUAL | H1: FORECAST
A2: Balance Sheet (in millions) | B2: 43863 | C2: 44227 | D2: 44591 | E2: 44955 | F2: 45319 | G2: 45690 | H2: 46053 | I2: 46418 | J2: 46783 | K2: 47149 | L2: 47514
A4: ASSETS
A5: Cash and cash equivalents | B5: =B134 -> 2133 | C5: =C134 -> 7895 | D5: =D134 -> 2343 | E5: =E134 -> 2757 | F5: =F134 -> 3760 | G5: =G134 -> 1659 | H5: =H134 -> 2600 | I5: =I134 -> 2600 | ... L5: =L134 -> 2600
A6: Short-term investments | B6: 0 | C6: 0 | D6: 0 | E6: 0 | F6: 0 | G6: 0 | H6: =G6+Financing!H139 -> 965.07883 | I6: =H6+Financing!I139 -> 1431.5134 | J6: =I6+Financing!J139 -> 4733.0502 | K6: =J6+Financing!K139 -> 10762.567 | L6: =K6+Financing!L139 -> 17202.781
A7: Receivables, net | B7: 2106 | C7: 2992 | D7: 3426 | E7: 3317 | F7: 3328 | G7: 4903 | H7: ='Working Capital'!H4 -> 3756.5375 | I7: ='Working Capital'!I4 -> 4041.4541 | J7: ='Working Capital'!J4 -> 4348.1289 | K7: ='Working Capital'!K4 -> 4678.2338 | L7: ='Working Capital'!L4 -> 5033.57
A8: Merchandise inventories | B8: 14531 | C8: 16627 | D8: 22068 | E8: 24886 | F8: 20976 | G8: 23451 | H8: ='Working Capital'!H8 -> 23277.426 | I8: ='Working Capital'!I8 -> 25042.915 | J8: ='Working Capital'!J8 -> 26943.229 | K8: ='Working Capital'!K8 -> 28988.727 | L8: ='Working Capital'!L8 -> 31190.572
A9: Other current assets | B9: 1040 | C9: 963 | D9: 1218 | E9: 1511 | F9: 1711 | G9: 1670 | H9: ='Working Capital'!H12 -> 1595.9408 | I9: ='Working Capital'!I12 -> 1716.9857 | J9: ='Working Capital'!J12 -> 1847.2745 | K9: ='Working Capital'!K12 -> 1987.5175 | L9: ='Working Capital'!L12 -> 2138.4798
A10: Total current assets | B10: =SUM(B5:B9) -> 19810 | C10: =SUM(C5:C9) -> 28477 | D10: =SUM(D5:D9) -> 29055 | E10: =SUM(E5:E9) -> 32471 | F10: =SUM(F5:F9) -> 29775 | G10: =SUM(G5:G9) -> 31683 | H10: =SUM(H5:H9) -> 32194.983 | I10: =SUM(I5:I9) -> 34832.868 | ... L10: =SUM(L5:L9) -> 58165.403
A12: Net property and equipment | B12: 22770 | C12: 24705 | D12: 25199 | E12: 25631 | F12: 26154 | G12: 26702 | H12: ='Long Term Asset & Liab'!H15 -> 27196.248 | I12: ='Long Term Asset & Liab'!I15 -> 27763.533 | J12: ='Long Term Asset & Liab'!J15 -> 28410.019 | K12: ='Long Term Asset & Liab'!K15 -> 29142.409 | L12: ='Long Term Asset & Liab'!L15 -> 29967.996
A13: Operating lease right-of-use assets | B13: 5595 | C13: 5962 | D13: 5968 | E13: 6941 | F13: 7884 | G13: 8592 | H13: 8592 | I13: 8592 | J13: 8592 | K13: 8592 | L13: 8592
A14: Goodwill | B14: 2254 | C14: 7126 | D14: 7449 | E14: 7444 | F14: 8455 | G14: 19475 | H14: ='Long Term Asset & Liab'!H113 -> 19475 | I14: ='Long Term Asset & Liab'!I113 -> 19475 | J14: ='Long Term Asset & Liab'!J113 -> 19475 | K14: ='Long Term Asset & Liab'!K113 -> 19475 | L14: ='Long Term Asset & Liab'!L113 -> 19475
A15: Intangible assets | B15: 0 | C15: 3612 | D15: 3503 | E15: 3323 | F15: 3606 | G15: 8983 | H15: ='Long Term Asset & Liab'!H106 -> 8430 | I15: ='Long Term Asset & Liab'!I106 -> 7877 | J15: ='Long Term Asset & Liab'!J106 -> 7332 | K15: ='Long Term Asset & Liab'!K106 -> 6804 | L15: ='Long Term Asset & Liab'!L106 -> 6318
A16: Other assets | B16: 807 | C16: 699 | D16: 702 | E16: =3958-3323 -> 635 | F16: =4262-3606 -> 656 | G16: 684 | H16: ='Long Term Asset & Liab'!H121 -> 772.2294 | I16: ='Long Term Asset & Liab'!I121 -> 830.79955 | J16: ='Long Term Asset & Liab'!J121 -> 893.84252 | K16: ='Long Term Asset & Liab'!K121 -> 961.70201 | L16: ='Long Term Asset & Liab'!L121 -> 1034.7483
A17: Total assets | B17: =SUM(B10:B16) -> 51236 | C17: =SUM(C10:C16) -> 70581 | D17: =SUM(D10:D16) -> 71876 | E17: =SUM(E10:E16) -> 76445 | F17: =SUM(F10:F16) -> 76530 | G17: =SUM(G10:G16) -> 96119 | H17: =SUM(H10:H16) -> 96660.46 | I17: =SUM(I10:I16) -> 99371.2 | ... L17: =SUM(L10:L16) -> 123553.15
A19: LIABILITIES
A21: Short-term debt | B21: 974 | C21: 0 | D21: 1035 | E21: 0 | F21: 0 | G21: 316 | H21: 316 | I21: 316 | J21: 316 | K21: 316 | L21: 316
A22: Accounts payable | B22: 7787 | C22: 11606 | D22: 13462 | E22: 11443 | F22: 10037 | G22: 11938 | H22: ='Working Capital'!H16 -> 12861.806 | I22: ='Working Capital'!I16 -> 13837.316 | J22: ='Working Capital'!J16 -> 14887.324 | K22: ='Working Capital'!K16 -> 16017.552 | L22: ='Working Capital'!L16 -> 17234.168
A23: Accrued salaries and related expenses | B23: 1494 | C23: 2463 | D23: 2426 | E23: 1991 | F23: 2096 | G23: 2315 | H23: ='Working Capital'!H20 -> 2591.293 | I23: ='Working Capital'!I20 -> 2787.831 | J23: ='Working Capital'!J20 -> 2999.378 | K23: ='Working Capital'!K20 -> 3227.0873 | L23: ='Working Capital'!L20 -> 3472.2013
A24: Sales taxes payable | B24: 605 | C24: 774 | D24: 848 | E24: 528 | F24: 449 | G24: 628 | H24: ='Working Capital'!H24 -> 737.90809 | I24: ='Working Capital'!I24 -> 793.87513 | J24: ='Working Capital'!J24 -> 854.11619 | K24: ='Working Capital'!K24 -> 918.9597 | L24: ='Working Capital'!L24 -> 988.75947
A25: Deferred revenue | B25: 2116 | C25: 2823 | D25: 3596 | E25: 3064 | F25: 2762 | G25: 2610 | H25: ='Working Capital'!H28 -> 3397.8094 | I25: ='Working Capital'!I28 -> 3655.518 | J25: ='Working Capital'!J28 -> 3932.9071 | K25: ='Working Capital'!K28 -> 4231.4889 | L25: ='Working Capital'!L28 -> 4552.8924
A26: Income taxes payable | B26: 55 | C26: 193 | D26: 158 | E26: 50 | F26: 28 | G26: 832 | H26: ='Working Capital'!H32 -> 289.79899 | I26: ='Working Capital'!I32 -> 316.50851 | J26: ='Working Capital'!J32 -> 345.84095 | K26: ='Working Capital'!K32 -> 374.17873 | L26: ='Working Capital'!L32 -> 402.00635
A27: Current installments of long-term debt | B27: 1839 | C27: 1416 | D27: 2447 | E27: 1231 | F27: 1368 | G27: 4582 | H27: =Financing!H9 -> 4845 | I27: =Financing!I9 -> 3769 | J27: =Financing!J9 -> 2727 | K27: =Financing!K9 -> 3946 | L27: =Financing!L9 -> 3946
A28: Current operating lease liabilities | B28: 828 | C28: 828 | D28: 830 | E28: 945 | F28: 1050 | G28: 1274 | H28: 1274 | I28: 1274 | J28: 1274 | K28: 1274 | L28: 1274
A29: Other accrued expenses | B29: 2677 | C29: 3063 | D29: 3891 | E29: 3858 | F29: 4225 | G29: 4166 | H29: ='Working Capital'!H36 -> 4358.8059 | I29: ='Working Capital'!I36 -> 4689.4019 | J29: ='Working Capital'!J36 -> 5045.2445 | K29: ='Working Capital'!K36 -> 5428.2736 | L29: ='Working Capital'!L36 -> 5840.5792
A30: Total current liabilities | B30: =SUM(B21:B29) -> 18375 | C30: =SUM(C21:C29) -> 23166 | D30: =SUM(D21:D29) -> 28693 | E30: =SUM(E21:E29) -> 23110 | F30: =SUM(F21:F29) -> 22015 | G30: =SUM(G21:G29) -> 28661 | H30: =SUM(H21:H29) -> 30672.421 | I30: =SUM(I21:I29) -> 31439.451 | ... L30: =SUM(L21:L29) -> 38026.607
A32: Long-term debt | B32: 28670 | C32: 35822 | D32: 36604 | E32: 41962 | F32: 42743 | G32: 48485 | H32: =Financing!H21 -> 43640 | I32: =Financing!I21 -> 39871 | J32: =Financing!J21 -> 37144 | K32: =Financing!K21 -> 33198 | L32: =Financing!L21 -> 29252
A33: Long-term operating lease liabilities | B33: 5066 | C33: 5356 | D33: 5353 | E33: 6226 | F33: 7082 | G33: 7633 | H33: 7633 | I33: 7633 | J33: 7633 | K33: 7633 | L33: 7633
A34: Deferred income taxes | B34: 706 | C34: 1131 | D34: 909 | E34: 1019 | F34: 863 | G34: 1962 | H34: ='Long Term Asset & Liab'!H131 -> 1575.8957 | I34: ='Long Term Asset & Liab'!I131 -> 1576.3042 | J34: ='Long Term Asset & Liab'!J131 -> 1579.2067 | K34: ='Long Term Asset & Liab'!K131 -> 1585.0523 | L34: ='Long Term Asset & Liab'!L131 -> 1594.7645
A35: Other long-term liabilities | B35: 1535 | C35: 1807 | D35: 2013 | E35: 2566 | F35: 2783 | G35: 2738 | H35: ='Long Term Asset & Liab'!H126 -> 2694.2226 | I35: ='Long Term Asset & Liab'!I126 -> 2898.5673 | J35: ='Long Term Asset & Liab'!J126 -> 3118.5173 | K35: ='Long Term Asset & Liab'!K126 -> 3355.2715 | L35: ='Long Term Asset & Liab'!L126 -> 3610.1218
A36: Total liabilities | B36: =SUM(B30:B35) -> 54352 | C36: =SUM(C30:C35) -> 67282 | D36: =SUM(D30:D35) -> 73572 | E36: =SUM(E30:E35) -> 74883 | F36: =SUM(F30:F35) -> 75486 | G36: =SUM(G30:G35) -> 89479 | H36: =SUM(H30:H35) -> 86215.539 | I36: =SUM(I30:I35) -> 83418.323 | ... L36: =SUM(L30:L35) -> 80116.493
A38: SHAREHOLDERS' EQUITY
A39: Common stock | B39: 89 | C39: 89 | D39: 90 | E39: 90 | F39: 90 | G39: 90 | H39: =Financing!H49 -> 90 | I39: =Financing!I49 -> 90 | J39: =Financing!J49 -> 90 | K39: =Financing!K49 -> 90 | L39: =Financing!L49 -> 90
A40: Paid-in capital | B40: 11001 | C40: 11540 | D40: 12132 | E40: 12592 | F40: 13147 | G40: 14117 | H40: =Financing!H50 -> 14811.189 | I40: =Financing!I50 -> 15560.124 | J40: =Financing!J50 -> 16368.218 | K40: =Financing!K50 -> 17240.231 | L40: =Financing!L50 -> 18181.727
A41: Retained earnings | B41: 51729 | C41: 58134 | D41: 67580 | E41: 76896 | F41: 83656 | G41: 89533 | H41: =G41+H79+Financing!H103 -> 98843.732 | I41: =H41+I79+Financing!I103 -> 109802.75 | J41: =I41+J79+Financing!J103 -> 122559.79 | K41: =J41+K79+Financing!K103 -> 137057.06 | L41: =K41+L79+Financing!L103 -> 153264.93
A42: Accumulated other comp. income (loss) | B42: -739 | C42: -671 | D42: -704 | E42: -718 | F42: -477 | G42: -1129 | H42: -1129 | I42: -1129 | J42: -1129 | K42: -1129 | L42: -1129
A43: Treasury stock | B43: -65196 | C43: -65793 | D43: -80794 | E43: -87298 | F43: -95372 | G43: -95971 | H43: =Financing!H82 -> -102171 | I43: =Financing!I82 -> -108371 | J43: =Financing!J82 -> -114571 | K43: =Financing!K82 -> -120771 | L43: =Financing!L82 -> -126971
A44: Total shareholders equity | B44: =SUM(B39:B43) -> -3116 | C44: =SUM(C39:C43) -> 3299 | D44: =SUM(D39:D43) -> -1696 | E44: =SUM(E39:E43) -> 1562 | F44: =SUM(F39:F43) -> 1044 | G44: =SUM(G39:G43) -> 6640 | H44: =SUM(H39:H43) -> 10444.921 | I44: =SUM(I39:I43) -> 15952.878 | ... L44: =SUM(L39:L43) -> 43436.654
A46: Total liabilities & equity | B46: =B36+B44 -> 51236 | C46: =C36+C44 -> 70581 | D46: =D36+D44 -> 71876 | E46: =E36+E44 -> 76445 | F46: =F36+F44 -> 76530 | G46: =G36+G44 -> 96119 | H46: =H36+H44 -> 96660.46 | I46: =I36+I44 -> 99371.2 | ... L46: =L36+L44 -> 123553.15
B48: =IF(B46=B17,"BALANCE","ERROR") -> BALANCE | C48: =IF(C46=C17,"BALANCE","ERROR") -> BALANCE | D48: =IF(D46=D17,"BALANCE","ERROR") -> BALANCE | E48: =IF(E46=E17,"BALANCE","ERROR") -> BALANCE | F48: =IF(F46=F17,"BALANCE","ERROR") -> BALANCE | G48: =IF(G46=G17,"BALANCE","ERROR") -> BALANCE | H48: =IF(H46=H17,"BALANCE","ERROR") -> BALANCE | I48: =IF(I46=I17,"BALANCE","ERROR") -> BALANCE | ... L48: =IF(L46=L17,"BALANCE","ERROR") -> BALANCE
B49: =B17-B46 -> 0 | C49: =C17-C46 -> 0 | D49: =D17-D46 -> 0 | E49: =E17-E46 -> 0 | F49: =F17-F46 -> 0 | G49: =G17-G46 -> 0 | H49: =H17-H46 -> 0 | I49: =I17-I46 -> 0 | ... L49: =L17-L46 -> 0
I50: =I49-H49 -> 0 | J50: =J49-I49 -> 0 | K50: =K49-J49 -> 0 | L50: =L49-K49 -> 0
A52: The Home Depot, Inc. | B52: ACTUAL | H52: FORECAST
A53: Statement of Earnings (in millions) | B53: 43863 | C53: 44227 | D53: 44591 | E53: 44955 | F53: 45319 | G53: 45690 | H53: 46053 | I53: 46418 | J53: 46783 | K53: 47149 | L53: 47514
A55: Net sales | B55: 110225 | C55: 132110 | D55: 151157 | E55: 157403 | F55: 152669 | G55: 159514 | H55: =Revenue!H6 -> 171606.53 | I55: =Revenue!I6 -> 184622.12 | J55: =Revenue!J6 -> 198631.67 | K55: =Revenue!K6 -> 213711.56 | L55: =Revenue!L6 -> 229944.06
A57: Cost of sales | B57: 72653 | C57: 87257 | D57: 100325 | E57: 104625 | F57: 101709 | G57: 106206 | H57: =Expenses!H7 -> 113826.61 | I57: =Expenses!I7 -> 122459.85 | J57: =Expenses!J7 -> 131752.39 | K57: =Expenses!K7 -> 141754.88 | L57: =Expenses!L7 -> 152521.9
A59: Gross profit | B59: =B55-B57 -> 37572 | C59: =C55-C57 -> 44853 | D59: =D55-D57 -> 50832 | E59: =E55-E57 -> 52778 | F59: =F55-F57 -> 50960 | G59: =G55-G57 -> 53308 | H59: =H55-H57 -> 57779.92 | I59: =I55-I57 -> 62162.269 | ... L59: =L55-L57 -> 77422.166
A61: Operating expenses:
A62: Selling, general and administrative | B62: 19740 | C62: 24447 | D62: 25406 | E62: 26284 | F62: 26598 | G62: 28748 | H62: =Expenses!H13 -> 30134.107 | I62: =Expenses!I13 -> 32419.645 | J62: =Expenses!J13 -> 34879.722 | K62: =Expenses!K13 -> 37527.75 | L62: =Expenses!L13 -> 40378.177
A63: Depreciation and amortization | B63: 1989 | C63: 2128 | D63: 2386 | E63: 2455 | F63: 2673 | G63: 3034 | H63: =-(0.89*'Long Term Asset & Liab'!H24)-'Long Term Asset & Liab'!H104 -> 3311.1594 | I63: =-(0.89*'Long Term Asset & Liab'!I24)-'Long Term Asset & Liab'!I104 -> 3488.8283 | J63: =-(0.89*'Long Term Asset & Liab'!J24)-'Long Term Asset & Liab'!J104 -> 3671.979 | K63: =-(0.89*'Long Term Asset & Liab'!K24)-'Long Term Asset & Liab'!K104 -> 3860.6652 | L63: =-(0.89*'Long Term Asset & Liab'!L24)-'Long Term Asset & Liab'!L104 -> 4040.0259
A65: Total operating expenses | B65: =SUM(B62:B64) -> 21729 | C65: =SUM(C62:C64) -> 26575 | D65: =SUM(D62:D64) -> 27792 | E65: =SUM(E62:E64) -> 28739 | F65: =SUM(F62:F64) -> 29271 | G65: =SUM(G62:G64) -> 31782 | H65: =SUM(H62:H64) -> 33445.267 | I65: =SUM(I62:I64) -> 35908.473 | ... L65: =SUM(L62:L64) -> 44418.203
A67: Operating income (loss) | B67: =B59-B65 -> 15843 | C67: =C59-C65 -> 18278 | D67: =D59-D65 -> 23040 | E67: =E59-E65 -> 24039 | F67: =F59-F65 -> 21689 | G67: =G59-G65 -> 21526 | H67: =H59-H65 -> 24334.653 | I67: =I59-I65 -> 26253.796 | ... L67: =L59-L65 -> 33003.963
A69: Interest and other (income) expense:
A70: Interest and investment income | B70: -73 | C70: -47 | D70: -44 | E70: -55 | F70: -178 | G70: -201 | H70: =Financing!H143 -> 0 | I70: =Financing!I143 -> 67.555518 | J70: =Financing!J143 -> 100.20594 | K70: =Financing!K143 -> 331.31351 | L70: =Financing!L143 -> 753.37966
A71: Interest expense | B71: 1201 | C71: 1347 | D71: 1347 | E71: 1617 | F71: 1943 | G71: 2321 | H71: =Financing!H29 -> 2191.6671 | I71: =Financing!I29 -> 2002.4305 | J71: =Financing!J29 -> 1802.332 | K71: =Financing!K29 -> 1646.6723 | L71: =Financing!L29 -> 1534.0472
A73: Interest and other,net | B73: =SUM(B70:B72) -> 1128 | C73: =SUM(C70:C72) -> 1300 | D73: =SUM(D70:D72) -> 1303 | E73: =SUM(E70:E72) -> 1562 | F73: =SUM(F70:F72) -> 1765 | G73: =SUM(G70:G72) -> 2120 | H73: =SUM(H70:H72) -> 2191.6671 | I73: =SUM(I70:I72) -> 2069.986 | ... L73: =SUM(L70:L72) -> 2287.4269
A75: Earnings before income taxes | B75: =B67-B73 -> 14715 | C75: =C67-C73 -> 16978 | D75: =D67-D73 -> 21737 | E75: =E67-E73 -> 22477 | F75: =F67-F73 -> 19924 | G75: =G67-G73 -> 19406 | H75: =H67-H73 -> 22142.986 | I75: =I67-I73 -> 24183.81 | ... L75: =L67-L73 -> 30716.536
A77: Provision for income taxes | B77: 3473 | C77: 4112 | D77: 5304 | E77: 5372 | F77: 4781 | G77: 4600 | H77: =Expenses!H20 -> 5307.6737 | I77: =Expenses!I20 -> 5796.8592 | J77: =Expenses!J20 -> 6334.0834 | K77: =Expenses!K20 -> 6853.0904 | L77: =Expenses!L20 -> 7362.7536
A79: Net earnings | B79: =B75-B77 -> 11242 | C79: =C75-C77 -> 12866 | D79: =D75-D77 -> 16433 | E79: =E75-E77 -> 17105 | F79: =F75-F77 -> 15143 | G79: =G75-G77 -> 14806 | H79: =H75-H77 -> 16835.312 | I79: =I75-I77 -> 18386.951 | ... L79: =L75-L77 -> 23353.782
A83: The Home Depot, Inc. | B83: ACTUAL | H83: FORECAST
A84: Statement of Cash Flows (in millions) | B84: 43863 | C84: 44227 | D84: 44591 | E84: 44955 | F84: 45319 | G84: 45690 | H84: 46053 | I84: 46418 | J84: 46783 | K84: 47149 | L84: 47514
A86: CASH FLOW FROM OPERATING ACTIVITIES
A87: Net income | B87: =B79 -> 11242 | C87: =C79 -> 12866 | D87: =D79 -> 16433 | E87: =E79 -> 17105 | F87: =F79 -> 15143 | G87: =G79 -> 14806 | H87: =H79 -> 16835.312 | I87: =I79 -> 18386.951 | ... L87: =L79 -> 23353.782
A88: Adj. to reconcile net income to net cash provided by operating activities:
A89: Depreciation and amortization | B89: 2296 | C89: 2519 | D89: 2862 | E89: 2796 | F89: 3061 | G89: 3336 | H89: =-'Long Term Asset & Liab'!H24 -> 3099.0556 | I89: =-'Long Term Asset & Liab'!I24 -> 3298.6835 | J89: =-'Long Term Asset & Liab'!J24 -> 3513.4595 | K89: =-'Long Term Asset & Liab'!K24 -> 3744.5676 | L89: =-'Long Term Asset & Liab'!L24 -> 3993.2875
A90: Amortization | E90: 179 | F90: 186 | G90: 425 | H90: =-'Long Term Asset & Liab'!H104 -> 553 | I90: =-'Long Term Asset & Liab'!I104 -> 553 | J90: =-'Long Term Asset & Liab'!J104 -> 545 | K90: =-'Long Term Asset & Liab'!K104 -> 528 | L90: =-'Long Term Asset & Liab'!L104 -> 486
A91: Stock based compensation | B91: 251 | C91: 310 | D91: 399 | E91: 366 | F91: 380 | G91: 442 | H91: =Financing!H56 -> 425.85643 | I91: =Financing!I56 -> 459.44143 | J91: =Financing!J56 -> 495.73271 | K91: =Financing!K56 -> 534.94467 | L91: =Financing!L56 -> 577.56935
A92: Other | B92: 184 | C92: 121 | D92: 196 | E92: 271 | F92: 314 | G92: 107
A93: Changes in operating assets and liabilities
A94: Receivables, net | B94: -170 | C94: -465 | D94: -435 | E94: 111 | F94: 134 | G94: 174 | H94: =-H7+G7 -> 1146.4625 | I94: =-I7+H7 -> -284.91661 | J94: =-J7+I7 -> -306.67478 | K94: =-K7+J7 -> -330.10491 | L94: =-L7+K7 -> -355.33619
A95: Merchandise inventories | B95: -593 | C95: -1657 | D95: -5403 | E95: -2830 | F95: 4137 | G95: -743 | H95: =-H8+G8 -> 173.57394 | I95: =-I8+H8 -> -1765.4889 | J95: =-J8+I8 -> -1900.3136 | K95: =-K8+J8 -> -2045.4987 | L95: =-L8+K8 -> -2201.8446
A96: Other current assets | B96: -135 | C96: 43 | D96: -330 | E96: -311 | F96: -184 | G96: 86 | H96: =G9-H9 -> 74.059241 | I96: =H9-I9 -> -121.04499 | J96: =I9-J9 -> -130.2888 | K96: =J9-K9 -> -140.24294 | L96: =K9-L9 -> -150.96229
A97: Other long-term assets | H97: =G16-H16 -> -88.229399 | I97: =H16-I16 -> -58.570155 | J97: =I16-J16 -> -63.042969 | K97: =J16-K16 -> -67.859488 | L97: =K16-L16 -> -73.04627
A98: Accounts payable | B98: 68 | C98: 5118 | D98: 2401 | E98: -2577 | F98: -1411 | G98: 518 | H98: =H22-G22 -> 923.80576 | I98: =I22-H22 -> 975.51059 | J98: =J22-I22 -> 1050.0072 | K98: =K22-J22 -> 1130.2283 | L98: =L22-K22 -> 1216.6164
A99: Accrued salaries | H99: =H23-G23 -> 276.29297 | I99: =I23-H23 -> 196.53801 | J99: =J23-I23 -> 211.54699 | K99: =K23-J23 -> 227.7093 | L99: =L23-K23 -> 245.11406
A100: Sales taxes payable | H100: =H24-G24 -> 109.90809 | I100: =I24-H24 -> 55.967037 | J100: =J24-I24 -> 60.24106 | K100: =K24-J24 -> 64.843511 | L100: =L24-K24 -> 69.799769
A101: Deferred revenue | B101: 334 | C101: 702 | D101: 775 | E101: -526 | F101: -318 | G101: -165 | H101: =H25-G25 -> 787.80936 | I101: =I25-H25 -> 257.70868 | J101: =J25-I25 -> 277.38907 | K101: =K25-J25 -> 298.58175 | L101: =L25-K25 -> 321.40359
A102: Income taxes payable | B102: 44 | C102: -149 | D102: -51 | E102: -107 | F102: -25 | G102: 809 | H102: =-G26+H26 -> -542.20101 | I102: =-H26+I26 -> 26.709526 | J102: =-I26+J26 -> 29.332441 | K102: =-J26+K26 -> 28.337781 | L102: =-K26+L26 -> 27.827613
A103: Other accrued expenses | H103: =-G29+H29 -> 192.80594 | I103: =-H29+I29 -> 330.59599 | J103: =-I29+J29 -> 355.84254 | K103: =-J29+K29 -> 383.02911 | L103: =-K29+L29 -> 412.30561
A104: Deferred income taxes | B104: 202 | C104: -569 | D104: -276 | E104: 138 | F104: -245 | G104: 15 | H104: =-G34+H34 -> -386.10432 | I104: =-H34+I34 -> 0.40855212 | J104: =-I34+J34 -> 2.9024998 | K104: =-J34+K34 -> 5.8455727 | L104: =-K34+L34 -> 9.7121923
A105: Other long-term liabilities | H105: =-G35+H35 -> -43.777429 | I105: =-H35+I35 -> 204.34476 | J105: =-I35+J35 -> 219.94992 | K105: =-J35+K35 -> 236.75421 | L105: =-K35+L35 -> 254.85032
A107: Net cash provided by operating activities | B107: =SUM(B87:B106) -> 13723 | C107: =SUM(C87:C106) -> 18839 | D107: =SUM(D87:D106) -> 16571 | E107: =SUM(E87:E106) -> 14615 | F107: =SUM(F87:F106) -> 21172 | G107: =SUM(G87:G106) -> 19810 | H107: =SUM(H87:H106) -> 23537.63 | I107: =SUM(I87:I106) -> 22515.838 | ... L107: =SUM(L87:L106) -> 28187.079
A109: CASH FLOW FROM INVESTING ACTIVITIES
A110: Capital expenditures | B110: -2678 | C110: -2463 | D110: -2566 | E110: -3119 | F110: -3226 | G110: -3485 | H110: =-'Long Term Asset & Liab'!H19 -> -3599.3031 | I110: =-'Long Term Asset & Liab'!I19 -> -3871.9685 | J110: =-'Long Term Asset & Liab'!J19 -> -4165.9455 | K110: =-'Long Term Asset & Liab'!K19 -> -4482.9583 | L110: =-'Long Term Asset & Liab'!L19 -> -4824.8747
A111: Payments for businesses acquired, net | B111: 0 | C111: -7780 | D111: -421 | E111: 0 | F111: -1514 | G111: -17644
A112: Proceeds from sales of property and equipment | B112: 37 | C112: 0 | D112: 0 | E112: 0 | F112: 0 | G112: 0 | H112: ='Long Term Asset & Liab'!H30 -> 6 | I112: ='Long Term Asset & Liab'!I30 -> 6 | J112: ='Long Term Asset & Liab'!J30 -> 6 | K112: ='Long Term Asset & Liab'!K30 -> 6 | L112: ='Long Term Asset & Liab'!L30 -> 6
A113: Purchase of investments | H113: =-Financing!H135 -> -965.07883 | I113: =-Financing!I135 -> -466.43461 | J113: =-Financing!J135 -> -3301.5368 | K113: =-Financing!K135 -> -6029.5164 | L113: =-Financing!L135 -> -6440.2145
A114: Other | B114: -12 | C114: 73 | D114: 18 | E114: -21 | F114: 11 | G114: 98
A116: Net cash used In investing activities | B116: =SUM(B110:B115) -> -2653 | C116: =SUM(C110:C115) -> -10170 | D116: =SUM(D110:D115) -> -2969 | E116: =SUM(E110:E115) -> -3140 | F116: =SUM(F110:F115) -> -4729 | G116: =SUM(G110:G115) -> -21031 | H116: =SUM(H110:H115) -> -4558.3819 | I116: =SUM(I110:I115) -> -4332.4032 | ... L116: =SUM(L110:L115) -> -11259.089
A118: CASH FLOW FROM FINANCING ACTIVITIES
A119: Repayments (proceeds) of short-term debt, net | B119: -365 | C119: -974 | D119: 1035 | E119: -1035 | F119: 0 | G119: 316
A120: Proceeds from long-term debt, net | B120: 3420 | C120: 7933 | D120: 2979 | E120: 6942 | F120: 1995 | G120: 10010 | H120: =Financing!H17 -> 0 | I120: =Financing!I17 -> 0 | J120: =Financing!J17 -> 0 | K120: =Financing!K17 -> 0 | L120: =Financing!L17 -> 0
A121: Repayments of long-term debt | B121: -1070 | C121: -2872 | D121: -1532 | E121: -2491 | F121: -1271 | G121: -1536 | H121: =Financing!H26 -> -4582 | I121: =Financing!I26 -> -4845 | J121: =Financing!J26 -> -3769 | K121: =Financing!K26 -> -2727 | L121: =Financing!L26 -> -3946
A122: Repurchases of common stock | B122: -6965 | C122: -791 | D122: -14809 | E122: -6696 | F122: -7951 | G122: -649 | H122: =Financing!H81 -> -6200 | I122: =Financing!I81 -> -6200 | J122: =Financing!J81 -> -6200 | K122: =Financing!K81 -> -6200 | L122: =Financing!L81 -> -6200
A123: Proceeds from sales of common stock | B123: 280 | C123: 326 | D123: 337 | E123: 264 | F123: 323 | G123: 395 | H123: =Financing!H55 -> 268.33214 | I123: =Financing!I55 -> 289.49404 | J123: =Financing!J55 -> 312.36118 | K123: =Financing!K55 -> 337.06864 | L123: =Financing!L55 -> 363.92644
A124: Cash dividends | B124: -5958 | C124: -6451 | D124: -6985 | E124: -7789 | F124: -8383 | G124: -8929 | H124: =Financing!H103 -> -7524.58 | I124: =Financing!I103 -> -7427.9288 | J124: =Financing!J103 -> -7333.9247 | K124: =Financing!K103 -> -7239.9205 | L124: =Financing!L103 -> -7145.9164
A125: Other | B125: -176 | C125: -154 | D125: -145 | E125: -188 | F125: -156 | G125: -301
A127: Net cash used In financing activities | B127: =SUM(B119:B126) -> -10834 | C127: =SUM(C119:C126) -> -2983 | D127: =SUM(D119:D126) -> -19120 | E127: =SUM(E119:E126) -> -10993 | F127: =SUM(F119:F126) -> -15443 | G127: =SUM(G119:G126) -> -694 | H127: =SUM(H119:H126) -> -18038.248 | I127: =SUM(I119:I126) -> -18183.435 | ... L127: =SUM(L119:L126) -> -16927.99
A129: Change in cash and cash equivalents | B129: =B107+B116+B127 -> 236 | C129: =C107+C116+C127 -> 5686 | D129: =D107+D116+D127 -> -5518 | E129: =E107+E116+E127 -> 482 | F129: =F107+F116+F127 -> 1000 | G129: =G107+G116+G127 -> -1915 | H129: =H107+H116+H127 -> 941 | I129: =I107+I116+I127 -> 0 | ... L129: =L107+L116+L127 -> 0
A131: Effect of exchange rate changes on cash | B131: 119 | C131: 76 | D131: -34 | E131: -68 | F131: 3 | G131: -186
...

Sheet Revenue
A1: The Home Depot, Inc. | B1: ACTUAL | H1: FORECAST
A2: (in millions) | B2: 43863 | C2: 44227 | D2: 44591 | E2: 44955 | F2: 45319 | G2: 45690 | H2: 46053 | I2: 46418 | J2: 46783 | K2: 47149 | L2: 47514
A4: FINAL REVENUE FORECAST (average of 4 methods)
A6: Net sales | B6: =Financials!B55 -> 110225 | C6: =Financials!C55 -> 132110 | D6: =Financials!D55 -> 151157 | E6: =Financials!E55 -> 157403 | F6: =Financials!F55 -> 152669 | G6: =Financials!G55 -> 159514 | H6: =AVERAGE(H13,H26,H44,H77) -> 171606.53 | I6: =AVERAGE(I13,I26,I44,I77) -> 184622.12 | J6: =AVERAGE(J13,J26,J44,J77) -> 198631.67 | K6: =AVERAGE(K13,K26,K44,K77) -> 213711.56 | L6: =AVERAGE(L13,L26,L44,L77) -> 229944.06
A11: FORECAST METHOD 1--BASED ON REVENUE GROWTH
A13: Net sales from income statement: | B13: =Financials!B55 -> 110225 | C13: =Financials!C55 -> 132110 | D13: =Financials!D55 -> 151157 | E13: =Financials!E55 -> 157403 | F13: =Financials!F55 -> 152669 | G13: =Financials!G55 -> 159514 | H13: =G13*(1+H15) -> 172275.12 | I13: =H13*(1+I15) -> 186057.13 | J13: =I13*(1+J15) -> 200941.7 | K13: =J13*(1+K15) -> 217017.04 | L13: =K13*(1+L15) -> 234378.4
A15: Sales Growth: | C15: =(C13-B13)/B13 -> 0.19854842 | D15: =(D13-C13)/C13 -> 0.14417531 | E15: =(E13-D13)/D13 -> 0.041321275 | F15: =(F13-E13)/E13 -> -0.030075666 | G15: =(G13-F13)/F13 -> 0.044835559 | H15: 0.08 | I15: 0.08 | J15: 0.08 | K15: 0.08 | L15: 0.08
A19: FORECAST METHOD 2--BASED ON REVENUE GROWTH BY PRODUCT TYPE
A21: Sales by product type:
A22: Building materials | B22: 39337 | C22: 46521 | D22: 54990 | E22: 54572 | F22: 52661 | G22: 52756 | H22: =G22*(1+H29) -> 56174.589 | I22: =H22*(1+I29) -> 59814.702 | J22: =I22*(1+J29) -> 63690.695 | K22: =J22*(1+K29) -> 67817.852 | L22: =K22*(1+L29) -> 72212.449
A23: Décor | B23: 37386 | C23: 43415 | D23: 50437 | E23: 54442 | F23: 51945 | G23: 51790 | H23: =G23*(1+H30) -> 55451.553 | I23: =H23*(1+I30) -> 59371.978 | J23: =I23*(1+J30) -> 63569.577 | K23: =J23*(1+K30) -> 68063.946 | L23: =K23*(1+L30) -> 72876.067
A24: Hardlines | B24: 33502 | C24: 42174 | D24: 45730 | E24: 48389 | F24: 48063 | G24: 48562 | H24: =G24*(1+H31) -> 52495.522 | I24: =H24*(1+I31) -> 56747.659 | J24: =I24*(1+J31) -> 61344.22 | K24: =J24*(1+K31) -> 66313.101 | L24: =K24*(1+L31) -> 71684.463
A25: Other | G25: 6406 | H25: =G25*(1+H32) -> 6918.48 | I25: =H25*(1+I32) -> 7471.9584 | J25: =I25*(1+J32) -> 8069.7151 | K25: =J25*(1+K32) -> 8715.2923 | L25: =K25*(1+L32) -> 9412.5157
B26: =SUM(B22:B25) -> 110225 | C26: =SUM(C22:C25) -> 132110 | D26: =SUM(D22:D25) -> 151157 | E26: =SUM(E22:E25) -> 157403 | F26: =SUM(F22:F25) -> 152669 | G26: =SUM(G22:G25) -> 159514 | H26: =SUM(H22:H25) -> 171040.14 | I26: =SUM(I22:I25) -> 183406.3 | ... L26: =SUM(L22:L25) -> 226185.49
A28: Sales Growth:
A29: Building materials | C29: =(C22-B22)/B22 -> 0.18262704 | D29: =(D22-C22)/C22 -> 0.18204682 | E29: =(E22-D22)/D22 -> -0.0076013821 | F29: =(F22-E22)/E22 -> -0.035017958 | G29: =(G22-F22)/F22 -> 0.0018039916 | H29: 0.0648 | I29: 0.0648 | J29: 0.0648 | K29: 0.0648 | L29: 0.0648
A30: Décor | C30: =(C23-B23)/B23 -> 0.16126357 | D30: =(D23-C23)/C23 -> 0.16174133 | E30: =(E23-D23)/D23 -> 0.079405992 | F30: =(F23-E23)/E23 -> -0.045865325 | G30: =(G23-F23)/F23 -> -0.0029839253 | H30: 0.0707 | I30: 0.0707 | J30: 0.0707 | K30: 0.0707 | L30: 0.0707
A31: Hardlines | C31: =(C24-B24)/B24 -> 0.25885022 | D31: =(D24-C24)/C24 -> 0.084317352 | E31: =(E24-D24)/D24 -> 0.058145637 | F31: =(F24-E24)/E24 -> -0.0067370683 | G31: =(G24-F24)/F24 -> 0.010382207 | H31: 0.081 | I31: 0.081 | J31: 0.081 | K31: 0.081 | L31: 0.081
A32: Other | G32: 0 | H32: 0.08 | I32: 0.08 | J32: 0.08 | K32: 0.08 | L32: 0.08
A39: FORECAST METHOD 3--INCORPORATING STORE DATA AND GEOGRAPHIC SEGMENTS
A41: Sales by geographic segment:
A42: US | B42: 101333 | C42: 122158 | D42: 138920 | E42: 144840 | F42: 140083 | G42: 147007 | H42: =H47*H56 -> 158828.07 | I42: =I47*I56 -> 171599.69 | J42: =J47*J56 -> 185398.29 | K42: =K47*K56 -> 200306.47 | L42: =L47*L56 -> 216413.43
A43: Outside the US | B43: 8892 | C43: 9952 | D43: 12237 | E43: 12563 | F43: 12586 | G43: 12507 | H43: =H51*H57 -> 13437.725 | I43: =I51*I57 -> 14437.711 | J43: =J51*J57 -> 15512.112 | K43: =K51*K57 -> 16666.467 | L43: =L51*L57 -> 17906.724
A44: Total | B44: =B42+B43 -> 110225 | C44: =C42+C43 -> 132110 | D44: =D42+D43 -> 151157 | E44: =E42+E43 -> 157403 | F44: =F42+F43 -> 152669 | G44: =G42+G43 -> 159514 | H44: =SUM(H42:H43) -> 172265.79 | I44: =SUM(I42:I43) -> 186037.4 | J44: =SUM(J42:J43) -> 200910.4 | K44: =SUM(K42:K43) -> 216972.93 | L44: =SUM(L42:L43) -> 234320.15
A46: Number of stores:
A47: US | B47: 1984 | C47: 1987 | D47: 2006 | E47: 2007 | F47: 2015 | G47: 2025 | H47: =G47*(1+H61) -> 2033.3025 | I47: =H47*(1+I61) -> 2041.639 | J47: =I47*(1+J61) -> 2050.0098 | K47: =J47*(1+K61) -> 2058.4148 | L47: =K47*(1+L61) -> 2066.8543
A49: Canada | B49: 182 | C49: 182 | D49: 182 | E49: 182 | F49: 182 | G49: 182 | H49: 182 | I49: 182 | J49: 182 | K49: 182 | L49: 182
A50: Mexico | B50: 125 | C50: 127 | D50: 129 | E50: 133 | F50: 138 | G50: 140 | H50: =H51-H49 -> 143.0912 | I50: =I51-I49 -> 146.21208 | J50: =J51-J49 -> 149.36291 | K50: =K51-K49 -> 152.544 | L50: =L51-L49 -> 155.75562
A51: Total outside US | B51: =B49+B50 -> 307 | C51: =C49+C50 -> 309 | D51: =D49+D50 -> 311 | E51: =E49+E50 -> 315 | F51: =F49+F50 -> 320 | G51: =G49+G50 -> 322 | H51: =G51*(1+H62) -> 325.0912 | I51: =H51*(1+I62) -> 328.21208 | J51: =I51*(1+J62) -> 331.36291 | K51: =J51*(1+K62) -> 334.544 | L51: =K51*(1+L62) -> 337.75562
A53: Total stores | B53: =B47+B51 -> 2291 | C53: =C47+C51 -> 2296 | D53: =D47+D51 -> 2317 | E53: =E47+E51 -> 2322 | F53: =F47+F51 -> 2335 | G53: =G47+G51 -> 2347 | H53: =H47+H51 -> 2358.3937 | I53: =I47+I51 -> 2369.8511 | ... L53: =L47+L51 -> 2404.6099
A55: Sales per store
A56: US | B56: =B42/B47 -> 51.075101 | C56: =C42/C47 -> 61.478611 | D56: =D42/D47 -> 69.252243 | E56: =E42/E47 -> 72.167414 | F56: =F42/F47 -> 69.520099 | G56: =G42/G47 -> 72.596049 | H56: =G56*(1+H65) -> 78.113349 | I56: =H56*(1+I65) -> 84.049964 | J56: =I56*(1+J65) -> 90.437761 | K56: =J56*(1+K65) -> 97.311031 | L56: =K56*(1+L65) -> 104.70667
A57: Outside the US | B57: =B43/B51 -> 28.964169 | C57: =C43/C51 -> 32.20712 | D57: =D43/D51 -> 39.347267 | E57: =E43/E51 -> 39.88254 | F57: =F43/F51 -> 39.33125 | G57: =G43/G51 -> 38.841615 | H57: =G57*(1+H66) -> 41.335247 | I57: =H57*(1+I66) -> 43.988969 | J57: =I57*(1+J66) -> 46.813061 | K57: =J57*(1+K66) -> 49.81846 | L57: =K57*(1+L66) -> 53.016805
A59: Growth:
A60: Number of stores:
A61: US | C61: =(C47-B47)/B47 -> 0.0015120968 | D61: =(D47-C47)/C47 -> 0.009562154 | E61: =(E47-D47)/D47 -> 0.00049850449 | F61: =(F47-E47)/E47 -> 0.0039860488 | G61: =(G47-F47)/F47 -> 0.0049627792 | H61: 0.0041 | I61: 0.0041 | J61: 0.0041 | K61: 0.0041 | L61: 0.0041
A62: Outside the US | C62: =(C51-B51)/B51 -> 0.006514658 | D62: =(D51-C51)/C51 -> 0.0064724919 | E62: =(E51-D51)/D51 -> 0.012861736 | F62: =(F51-E51)/E51 -> 0.015873016 | G62: =(G51-F51)/F51 -> 0.00625 | H62: 0.0096 | I62: 0.0096 | J62: 0.0096 | K62: 0.0096 | L62: 0.0096
A64: Sales per store
A65: US | C65: =(C56-B56)/B56 -> 0.20369045 | D65: =(D56-C56)/C56 -> 0.1264445 | E65: =(E56-D56)/D56 -> 0.042094965 | F65: =(F56-E56)/E56 -> -0.036682966 | G65: =(G56-F56)/F56 -> 0.04424548 | H65: 0.076 | I65: 0.076 | J65: 0.076 | K65: 0.076 | L65: 0.076
A66: Outside the US | C66: =(C57-B57)/B57 -> 0.11196421 | D66: =(D57-C57)/C57 -> 0.22169468 | E66: =(E57-D57)/D57 -> 0.013603811 | F66: =(F57-E57)/E57 -> -0.013822833 | G66: =(G57-F57)/F57 -> -0.012449009 | H66: 0.0642 | I66: 0.0642 | J66: 0.0642 | K66: 0.0642 | L66: 0.0642
A70: FORECAST METHOD 4--INCORPORATING SQUARE FOOTAGE DATA
A72: Sales by product line:
A73: Building materials | B73: =B22 -> 39337 | C73: =C22 -> 46521 | D73: =D22 -> 54990 | E73: =E22 -> 54572 | F73: =F22 -> 52661 | G73: =G22 -> 52756 | H73: =H85*H82 -> 56131.742 | I73: =I85*I82 -> 59723.491 | J73: =J85*J82 -> 63545.069 | K73: =K85*K82 -> 67611.18 | L73: =L85*L82 -> 71937.474
A74: Décor | B74: =B23 -> 37386 | C74: =C23 -> 43415 | D74: =D23 -> 50437 | E74: =E23 -> 54442 | F74: =F23 -> 51945 | G74: =G23 -> 51790 | H74: =H86*H82 -> 55403.699 | I74: =I86*I82 -> 59269.548 | J74: =J86*J82 -> 63405.139 | K74: =K86*K82 -> 67829.297 | L74: =L86*L82 -> 72562.154
A75: Hardlines | B75: =B24 -> 33502 | C75: =C24 -> 42174 | D75: =D24 -> 45730 | E75: =E24 -> 48389 | F75: =F24 -> 48063 | G75: =G24 -> 48562 | H75: =H87*H82 -> 52447.38 | I75: =I87*I82 -> 56643.623 | J75: =J87*J82 -> 61175.602 | K75: =K87*K82 -> 66070.179 | L75: =L87*L82 -> 71356.364
A76: Other | B76: =B25 -> 0 | C76: =C25 -> 0 | D76: =D25 -> 0 | E76: =E25 -> 0 | F76: =F25 -> 0 | G76: =G25 -> 6406 | H76: =H88*H82 -> 6862.2548 | I76: =I88*I82 -> 7351.0054 | J76: =J88*J82 -> 7874.5664 | K76: =K88*K82 -> 8435.417 | L76: =L88*L82 -> 9036.213
A77: Total | B77: =SUM(B73:B76) -> 110225 | C77: =SUM(C73:C76) -> 132110 | D77: =SUM(D73:D76) -> 151157 | E77: =SUM(E73:E76) -> 157403 | F77: =SUM(F73:F76) -> 152669 | G77: =SUM(G73:G76) -> 159514 | H77: =SUM(H73:H76) -> 170845.08 | I77: =SUM(I73:I76) -> 182987.67 | ... L77: =SUM(L73:L76) -> 224892.2
A79: Square feet (millions):
A80: Stores | B80: 238.1 | C80: 238.6 | D80: 240.5 | E80: 240.9 | F80: 242.3 | G80: 243.5 | H80: =G80+0.7 -> 244.2 | I80: =H80+0.7 -> 244.9 | J80: =I80+0.7 -> 245.6 | K80: =J80+0.7 -> 246.3 | L80: =K80+0.7 -> 247
A81: Warehouses, distribution and offices | B81: =60+4.4 -> 64.4 | C81: =75.9+5.1 -> 81 | D81: =88.5+5.3 -> 93.8 | E81: =103.1+5.2 -> 108.3 | F81: =111.5+4.8 -> 116.3 | G81: =108.3+4.7 -> 113 | H81: =H82-H80 -> 124.2784 | I81: =I82-I80 -> 135.95927 | J81: =J82-J80 -> 148.05615 | K81: =K82-K80 -> 160.58299 | L81: =L82-L80 -> 173.55426
B82: =B80+B81 -> 302.5 | C82: =C80+C81 -> 319.6 | D82: =D80+D81 -> 334.3 | E82: =E80+E81 -> 349.2 | F82: =F80+F81 -> 358.6 | G82: =G80+G81 -> 356.5 | H82: =G82*(1+H92) -> 368.4784 | I82: =H82*(1+I92) -> 380.85927 | J82: =I82*(1+J92) -> 393.65615 | K82: =J82*(1+K92) -> 406.88299 | L82: =K82*(1+L92) -> 420.55426
A84: Sales per square foot
A85: Building materials | B85: =B73/B82 -> 130.03967 | C85: =C73/C82 -> 145.56008 | D85: =D73/D82 -> 164.49297 | E85: =E73/E82 -> 156.27721 | F85: =F73/F82 -> 146.85165 | G85: =G73/G82 -> 147.98317 | H85: =G85*(1+H95) -> 152.33387 | I85: =H85*(1+I95) -> 156.81249 | J85: =I85*(1+J95) -> 161.42278 | K85: =J85*(1+K95) -> 166.16861 | L85: =K85*(1+L95) -> 171.05396
A86: Décor | B86: =B74/B82 -> 123.59008 | C86: =C74/C82 -> 135.84168 | D86: =D74/D82 -> 150.87347 | E86: =E74/E82 -> 155.90493 | F86: =F74/F82 -> 144.85499 | G86: =G74/G82 -> 145.27349 | H86: =G86*(1+H96) -> 150.35806 | I86: =H86*(1+I96) -> 155.6206 | J86: =I86*(1+J96) -> 161.06732 | K86: =J86*(1+K96) -> 166.70467 | L86: =K86*(1+L96) -> 172.53934
A87: Hardlines | B87: =B75/B82 -> 110.75041 | C87: =C75/C82 -> 131.9587 | D87: =D75/D82 -> 136.7933 | E87: =E75/E82 -> 138.57102 | F87: =F75/F82 -> 134.02956 | G87: =G75/G82 -> 136.21879 | H87: =G87*(1+H97) -> 142.33502 | I87: =H87*(1+I97) -> 148.72586 | J87: =I87*(1+J97) -> 155.40365 | K87: =J87*(1+K97) -> 162.38128 | L87: =K87*(1+L97) -> 169.67219
A88: Other | B88: =B76/B82 -> 0 | C88: =C76/C82 -> 0 | D88: =D76/D82 -> 0 | E88: =E76/E82 -> 0 | F88: =F76/F82 -> 0 | G88: =G76/G82 -> 17.969144 | H88: =G88*(1+H98) -> 18.623221 | I88: =H88*(1+I98) -> 19.301107 | J88: =I88*(1+J98) -> 20.003667 | K88: =J88*(1+K98) -> 20.7318 | L88: =K88*(1+L98) -> 21.486438
A89: Total | B89: =SUM(B85:B88) -> 364.38017 | C89: =SUM(C85:C88) -> 413.36045 | D89: =SUM(D85:D88) -> 452.15974 | E89: =SUM(E85:E88) -> 450.75315 | F89: =SUM(F85:F88) -> 425.7362 | G89: =SUM(G85:G88) -> 447.4446 | H89: =SUM(H85:H88) -> 463.65018 | I89: =SUM(I85:I88) -> 480.46005 | ... L89: =SUM(L85:L88) -> 534.75193
A91: Growth:
A92: Square footage | C92: =(C82-B82)/B82 -> 0.056528926 | D92: =(D82-C82)/C82 -> 0.045994994 | E92: =(E82-D82)/D82 -> 0.044570745 | F92: =(F82-E82)/E82 -> 0.026918671 | G92: =(G82-F82)/F82 -> -0.0058561071 | H92: 0.0336 | I92: 0.0336 | J92: 0.0336 | K92: 0.0336 | L92: 0.0336
A94: Sales per square foot
A95: Building materials | C95: =(C85-B85)/B85 -> 0.11935132 | D95: =(D85-C85)/C85 -> 0.13006929 | E95: =(E85-D85)/D85 -> -0.049945997 | F95: =(F85-E85)/E85 -> -0.060313081 | G95: =(G85-F85)/F85 -> 0.0077052213 | H95: 0.0294 | I95: 0.0294 | J95: 0.0294 | K95: 0.0294 | L95: 0.0294
A96: Décor | C96: =(C86-B86)/B86 -> 0.099130886 | D96: =(D86-C86)/C86 -> 0.11065669 | E96: =(E86-D86)/D86 -> 0.033348863 | F96: =(F86-E86)/E86 -> -0.070876105 | G96: =(G86-F86)/F86 -> 0.0028891007 | H96: 0.035 | I96: 0.035 | J96: 0.035 | K96: 0.035 | L96: 0.035
A97: Hardlines | C97: =(C87-B87)/B87 -> 0.19149622 | D97: =(D87-C87)/C87 -> 0.036637229 | E97: =(E87-D87)/D87 -> 0.012995666 | F97: =(F87-E87)/E87 -> -0.03277352 | G97: =(G87-F87)/F87 -> 0.016333967 | H97: 0.0449 | I97: 0.0449 | J97: 0.0449 | K97: 0.0449 | L97: 0.0449
A98: Other | C98: 0 | D98: 0 | E98: 0 | F98: 0 | G98: 0 | H98: 0.0364 | I98: 0.0364 | J98: 0.0364 | K98: 0.0364 | L98: 0.0364
A99: Total | C99: =SUM(C95:C98) -> 0.40997842 | D99: =SUM(D95:D98) -> 0.2773632 | E99: =SUM(E95:E98) -> -0.0036014674 | F99: =SUM(F95:F98) -> -0.16396271 | G99: =SUM(G95:G98) -> 0.026928289 | H99: =SUM(H95:H98) -> 0.1457 | I99: =SUM(I95:I98) -> 0.1457 | J99: =SUM(J95:J98) -> 0.1457 | ... L99: =SUM(L95:L98) -> 0.1457

Sheet Expenses
A1: The Home Depot, Inc. | B1: ACTUAL | H1: FORECAST
A2: (in millions) | B2: 43863 | C2: 44227 | D2: 44591 | E2: 44955 | F2: 45319 | G2: 45690 | H2: 46053 | I2: 46418 | J2: 46783 | K2: 47149 | L2: 47514
A4: Revenue forecast: | B4: =Financials!B55 -> 110225 | C4: =Financials!C55 -> 132110 | D4: =Financials!D55 -> 151157 | E4: =Financials!E55 -> 157403 | F4: =Financials!F55 -> 152669 | G4: =Financials!G55 -> 159514 | H4: =Financials!H55 -> 171606.53 | I4: =Financials!I55 -> 184622.12 | ... L4: =Financials!L55 -> 229944.06
A7: COGS from income statement: | B7: =Financials!B57 -> 72653 | C7: =Financials!C57 -> 87257 | D7: =Financials!D57 -> 100325 | E7: =Financials!E57 -> 104625 | F7: =Financials!F57 -> 101709 | G7: =Financials!G57 -> 106206 | H7: =H4*H9 -> 113826.61 | I7: =I4*I9 -> 122459.85 | J7: =J4*J9 -> 131752.39 | K7: =K4*K9 -> 141754.88 | L7: =L4*L9 -> 152521.9
A9: As a % of revenue | B9: =B7/B4 -> 0.65913359 | C9: =C7/C4 -> 0.66048747 | D9: =D7/D4 -> 0.66371389 | E9: =E7/E4 -> 0.66469508 | F9: =F7/F4 -> 0.66620598 | G9: =G7/G4 -> 0.6658099 | H9: 0.6633 | I9: 0.6633 | J9: 0.6633 | K9: 0.6633 | L9: 0.6633
A13: SG&A from income statement: | B13: =Financials!B62 -> 19740 | C13: =Financials!C62 -> 24447 | D13: =Financials!D62 -> 25406 | E13: =Financials!E62 -> 26284 | F13: =Financials!F62 -> 26598 | G13: =Financials!G62 -> 28748 | H13: =H4*H15 -> 30134.107 | I13: =I4*I15 -> 32419.645 | J13: =J4*J15 -> 34879.722 | K13: =K4*K15 -> 37527.75 | L13: =L4*L15 -> 40378.177
A15: As a % of revenue | B15: =B13/B4 -> 0.17908823 | C15: =C13/C4 -> 0.18505034 | D15: =D13/D4 -> 0.1680769 | E15: =E13/E4 -> 0.16698538 | F15: =F13/F4 -> 0.17422004 | G15: =G13/G4 -> 0.18022243 | H15: 0.1756 | I15: 0.1756 | J15: 0.1756 | K15: 0.1756 | L15: 0.1756
A19: Tax expense forecast
A20: Tax Expense | B20: =Financials!B77 -> 3473 | C20: =Financials!C77 -> 4112 | D20: =Financials!D77 -> 5304 | E20: =Financials!E77 -> 5372 | F20: =Financials!F77 -> 4781 | G20: =Financials!G77 -> 4600 | H20: =H21*H22 -> 5307.6737 | I20: =I21*I22 -> 5796.8592 | J20: =J21*J22 -> 6334.0834 | K20: =K21*K22 -> 6853.0904 | L20: =L21*L22 -> 7362.7536
A21: Pretax income | B21: =Financials!B75 -> 14715 | C21: =Financials!C75 -> 16978 | D21: =Financials!D75 -> 21737 | E21: =Financials!E75 -> 22477 | F21: =Financials!F75 -> 19924 | G21: =Financials!G75 -> 19406 | H21: =Financials!H75 -> 22142.986 | I21: =Financials!I75 -> 24183.81 | ... L21: =Financials!L75 -> 30716.536
A22: Effective tax rate (ETR) | B22: =B20/B21 -> 0.23601767 | C22: =C20/C21 -> 0.24219578 | D22: =D20/D21 -> 0.24400791 | E22: =E20/E21 -> 0.23899987 | F22: =F20/F21 -> 0.23996186 | G22: =G20/G21 -> 0.23704009 | H22: 0.2397 | I22: 0.2397 | J22: 0.2397 | K22: 0.2397 | L22: 0.2397

Sheet Working Capital
A1: The Home Depot, Inc. | B1: ACTUAL | H1: FORECAST
A2: (in millions) | B2: 43863 | C2: 44227 | D2: 44591 | E2: 44955 | F2: 45319 | G2: 45690 | H2: 46053 | I2: 46418 | J2: 46783 | K2: 47149 | L2: 47514
A4: Accounts receivable | B4: =Financials!B7 -> 2106 | C4: =Financials!C7 -> 2992 | D4: =Financials!D7 -> 3426 | E4: =Financials!E7 -> 3317 | F4: =Financials!F7 -> 3328 | G4: =Financials!G7 -> 4903 | H4: =(Financials!H55/365)*'Working Capital'!H5 -> 3756.5375 | I4: =(Financials!I55/365)*'Working Capital'!I5 -> 4041.4541 | J4: =(Financials!J55/365)*'Working Capital'!J5 -> 4348.1289 | K4: =(Financials!K55/365)*'Working Capital'!K5 -> 4678.2338 | L4: =(Financials!L55/365)*'Working Capital'!L5 -> 5033.57
A5: Days sales in A/R | C5: =Ratios!C59 -> 7.0425025 | D5: =Ratios!D59 -> 7.7487976 | E5: =Ratios!E59 -> 7.8181324 | F5: =Ratios!F59 -> 7.9434103 | G5: =Ratios!G59 -> 9.4170888 | H5: 7.99 | I5: 7.99 | J5: 7.99 | K5: 7.99 | L5: 7.99
A6: 5 year average | G6: =AVERAGE(C5:G5) -> 7.9939863
A8: Merchandise inventories | B8: =Financials!B8 -> 14531 | C8: =Financials!C8 -> 16627 | D8: =Financials!D8 -> 22068 | E8: =Financials!E8 -> 24886 | F8: =Financials!F8 -> 20976 | G8: =Financials!G8 -> 23451 | H8: =Financials!H57/'Working Capital'!H9 -> 23277.426 | I8: =Financials!I57/'Working Capital'!I9 -> 25042.915 | J8: =Financials!J57/'Working Capital'!J9 -> 26943.229 | K8: =Financials!K57/'Working Capital'!K9 -> 28988.727 | L8: =Financials!L57/'Working Capital'!L9 -> 31190.572
A9: Inventory turnover | C9: =Ratios!C66 -> 5.6009372 | D9: =Ratios!D66 -> 5.1854245 | E9: =Ratios!E66 -> 4.4564893 | F9: =Ratios!F66 -> 4.4354367 | G9: =Ratios!G66 -> 4.7811466 | H9: 4.89 | I9: 4.89 | J9: 4.89 | K9: 4.89 | L9: 4.89
A10: 5 year average | G10: =AVERAGE(C9:G9) -> 4.8918869
A12: Other current assets | B12: =Financials!B9 -> 1040 | C12: =Financials!C9 -> 963 | D12: =Financials!D9 -> 1218 | E12: =Financials!E9 -> 1511 | F12: =Financials!F9 -> 1711 | G12: =Financials!G9 -> 1670 | H12: =Financials!H55*'Working Capital'!H13 -> 1595.9408 | I12: =Financials!I55*'Working Capital'!I13 -> 1716.9857 | J12: =Financials!J55*'Working Capital'!J13 -> 1847.2745 | K12: =Financials!K55*'Working Capital'!K13 -> 1987.5175 | L12: =Financials!L55*'Working Capital'!L13 -> 2138.4798
A13: Percentage of revenue | B13: =B12/Financials!B55 -> 0.0094352461 | C13: =C12/Financials!C55 -> 0.0072893801 | D13: =D12/Financials!D55 -> 0.0080578471 | E13: =E12/Financials!E55 -> 0.0095995629 | F13: =F12/Financials!F55 -> 0.011207252 | G13: =G12/Financials!G55 -> 0.010469301 | H13: 0.0093 | I13: 0.0093 | J13: 0.0093 | K13: 0.0093 | L13: 0.0093
A14: 5 year average | G14: =AVERAGE(C13:G13) -> 0.0093246686
A16: Accounts payable | B16: =Financials!B22 -> 7787 | C16: =Financials!C22 -> 11606 | D16: =Financials!D22 -> 13462 | E16: =Financials!E22 -> 11443 | F16: =Financials!F22 -> 10037 | G16: =Financials!G22 -> 11938 | H16: =((Financials!H57+Financials!H62)/365)*H17 -> 12861.806 | I16: =((Financials!I57+Financials!I62)/365)*I17 -> 13837.316 | J16: =((Financials!J57+Financials!J62)/365)*J17 -> 14887.324 | K16: =((Financials!K57+Financials!K62)/365)*K17 -> 16017.552 | L16: =((Financials!L57+Financials!L62)/365)*L17 -> 17234.168
A17: Days costs in A/P | C17: =Ratios!C81 -> 31.683937 | D17: =Ratios!D81 -> 36.386492 | E17: =Ratios!E81 -> 34.720015 | F17: =Ratios!F81 -> 30.552503 | G17: =Ratios!G81 -> 29.71707 | H17: 32.61 | I17: 32.61 | J17: 32.61 | K17: 32.61 | L17: 32.61
A18: 5 year average | G18: =AVERAGE(C17:G17) -> 32.612003
A20: Accrued salaries and related expenses | B20: =Financials!B23 -> 1494 | C20: =Financials!C23 -> 2463 | D20: =Financials!D23 -> 2426 | E20: =Financials!E23 -> 1991 | F20: =Financials!F23 -> 2096 | G20: =Financials!G23 -> 2315 | H20: =(Financials!H57+Financials!H62)*H21 -> 2591.293 | I20: =(Financials!I57+Financials!I62)*I21 -> 2787.831 | J20: =(Financials!J57+Financials!J62)*J21 -> 2999.378 | K20: =(Financials!K57+Financials!K62)*K21 -> 3227.0873 | L20: =(Financials!L57+Financials!L62)*L21 -> 3472.2013
A21: Percentage of COGS and SG&A | B21: =B20/(Financials!B57+Financials!B62) -> 0.016170056 | C21: =C20/(Financials!C57+Financials!C62) -> 0.022049345 | D21: =D20/(Financials!D57+Financials!D62) -> 0.019295162 | E21: =E20/(Financials!E57+Financials!E62) -> 0.015209038 | F21: =F20/(Financials!F57+Financials!F62) -> 0.01633582 | G21: =G20/(Financials!G57+Financials!G62) -> 0.017153993 | H21: 0.018 | I21: 0.018 | J21: 0.018 | K21: 0.018 | L21: 0.018
A22: 5 year average | G22: =AVERAGE(C21:G21) -> 0.018008672
A24: Sales taxes payable | B24: =Financials!B24 -> 605 | C24: =Financials!C24 -> 774 | D24: =Financials!D24 -> 848 | E24: =Financials!E24 -> 528 | F24: =Financials!F24 -> 449 | G24: =Financials!G24 -> 628 | H24: =Financials!H55*'Working Capital'!H25 -> 737.90809 | I24: =Financials!I55*'Working Capital'!I25 -> 793.87513 | J24: =Financials!J55*'Working Capital'!J25 -> 854.11619 | K24: =Financials!K55*'Working Capital'!K25 -> 918.9597 | L24: =Financials!L55*'Working Capital'!L25 -> 988.75947
A25: Percentage of revenue | B25: =B24/Financials!B55 -> 0.005488773 | C25: =C24/Financials!C55 -> 0.0058587541 | D25: =D24/Financials!D55 -> 0.0056100611 | E25: =E24/Financials!E55 -> 0.0033544469 | F25: =F24/Financials!F55 -> 0.0029410031 | G25: =G24/Financials!G55 -> 0.0039369585 | H25: 0.0043 | I25: 0.0043 | J25: 0.0043 | K25: 0.0043 | L25: 0.0043
A26: 5 year average | G26: =AVERAGE(C25:G25) -> 0.0043402447
A28: Deferred revenue | B28: =Financials!B25 -> 2116 | C28: =Financials!C25 -> 2823 | D28: =Financials!D25 -> 3596 | E28: =Financials!E25 -> 3064 | F28: =Financials!F25 -> 2762 | G28: =Financials!G25 -> 2610 | H28: =Financials!H55*'Working Capital'!H29 -> 3397.8094 | I28: =Financials!I55*'Working Capital'!I29 -> 3655.518 | J28: =Financials!J55*'Working Capital'!J29 -> 3932.9071 | K28: =Financials!K55*'Working Capital'!K29 -> 4231.4889 | L28: =Financials!L55*'Working Capital'!L29 -> 4552.8924
A29: Percentage of revenue | B29: =B28/Financials!B55 -> 0.019197097 | C29: =C28/Financials!C55 -> 0.021368557 | D29: =D28/Financials!D55 -> 0.023789834 | E29: =E28/Financials!E55 -> 0.019465957 | F29: =F28/Financials!F55 -> 0.018091427 | G29: =G28/Financials!G55 -> 0.0163622 | H29: 0.0198 | I29: 0.0198 | J29: 0.0198 | K29: 0.0198 | L29: 0.0198
A30: 5 year average | G30: =AVERAGE(C29:G29) -> 0.019815595
A32: Income taxes payable | B32: =Financials!B26 -> 55 | C32: =Financials!C26 -> 193 | D32: =Financials!D26 -> 158 | E32: =Financials!E26 -> 50 | F32: =Financials!F26 -> 28 | G32: =Financials!G26 -> 832 | H32: =Financials!H77*'Working Capital'!H33 -> 289.79899 | I32: =Financials!I77*'Working Capital'!I33 -> 316.50851 | J32: =Financials!J77*'Working Capital'!J33 -> 345.84095 | K32: =Financials!K77*'Working Capital'!K33 -> 374.17873 | L32: =Financials!L77*'Working Capital'!L33 -> 402.00635
A33: Percentage of tax expense | B33: =B32/Financials!B77 -> 0.015836453 | C33: =C32/Financials!C77 -> 0.046935798 | D33: =D32/Financials!D77 -> 0.029788839 | E33: =E32/Financials!E77 -> 0.0093075205 | F33: =F32/Financials!F77 -> 0.0058565154 | G33: =G32/Financials!G77 -> 0.18086957 | H33: 0.0546 | I33: 0.0546 | J33: 0.0546 | K33: 0.0546 | L33: 0.0546
A34: 5 year average | G34: =AVERAGE(C33:G33) -> 0.054551647
A36: Other accrued expenses | B36: =Financials!B29 -> 2677 | C36: =Financials!C29 -> 3063 | D36: =Financials!D29 -> 3891 | E36: =Financials!E29 -> 3858 | F36: =Financials!F29 -> 4225 | G36: =Financials!G29 -> 4166 | H36: =Financials!H55*'Working Capital'!H37 -> 4358.8059 | I36: =Financials!I55*'Working Capital'!I37 -> 4689.4019 | J36: =Financials!J55*'Working Capital'!J37 -> 5045.2445 | K36: =Financials!K55*'Working Capital'!K37 -> 5428.2736 | L36: =Financials!L55*'Working Capital'!L37 -> 5840.5792
A37: Percentage of revenue | B37: =B36/Financials!B55 -> 0.024286686 | C37: =C36/Financials!C55 -> 0.023185224 | D37: =D36/Financials!D55 -> 0.025741448 | E37: =E36/Financials!E55 -> 0.024510333 | F37: =F36/Financials!F55 -> 0.02767425 | G37: =G36/Financials!G55 -> 0.02611683 | H37: 0.0254 | I37: 0.0254 | J37: 0.0254 | K37: 0.0254 | L37: 0.0254
A38: 5 year average | G38: =AVERAGE(C37:G37) -> 0.025445617

Sheet Long Term Asset & Liab
A1: The Home Depot, Inc. | B1: ACTUAL | H1: FORECAST
A2: (in millions) | B2: 43863 | C2: 44227 | D2: 44591 | E2: 44955 | F2: 45319 | G2: 45690 | H2: 46053 | I2: 46418 | J2: 46783 | K2: 47149 | L2: 47514
A4: Property, plant and equipment (PP&E), net
A5: Land | B5: 8390 | C5: 8543 | D5: 8617 | E5: 8719 | F5: 9027 | G5: 9060
A6: Buildings | B6: 18432 | C6: 18838 | D6: 19173 | E6: 19430 | F6: 20030 | G6: 20260
A7: Furniture, fixtures, and equipment | B7: 13666 | C7: 15119 | D7: 16441 | E7: 16564 | F7: 16667 | G7: 18474
A8: Leasehold improvements | B8: 1789 | C8: 1925 | D8: 2016 | E8: 2130 | F8: 2254 | G8: 2423
A9: Construction in progress | B9: 1005 | C9: 1068 | D9: 1139 | E9: 1297 | F9: 1192 | G9: 1521
A10: Finance leases | B10: 1578 | C10: 3308 | D10: 3943 | E10: 4135 | F10: 4087 | G10: 4045
A11: Gross PP&E | B11: =SUM(B5:B10) -> 44860 | C11: =SUM(C5:C10) -> 48801 | D11: =SUM(D5:D10) -> 51329 | E11: =SUM(E5:E10) -> 52275 | F11: =SUM(F5:F10) -> 53257 | G11: =SUM(G5:G10) -> 55783 | H11: =G11+H19+H20+H21+H22+H23 -> 59376.303 | I11: =H11+I19+I20+I21+I22+I23 -> 63242.272 | J11: =I11+J19+J20+J21+J22+J23 -> 67402.217 | K11: =J11+K19+K20+K21+K22+K23 -> 71879.175 | L11: =K11+L19+L20+L21+L22+L23 -> 76698.05
A13: Accumulated depreciation | B13: 22090 | C13: 24096 | D13: 26130 | E13: 26644 | F13: 27103 | G13: 29081 | H13: =G13-H24 -> 32180.056 | I13: =H13-I24 -> 35478.739 | J13: =I13-J24 -> 38992.199 | K13: =J13-K24 -> 42736.766 | L13: =K13-L24 -> 46730.054
A15: Net PP&E | B15: =B11-B13 -> 22770 | C15: =C11-C13 -> 24705 | D15: =D11-D13 -> 25199 | E15: =E11-E13 -> 25631 | F15: =F11-F13 -> 26154 | G15: =G11-G13 -> 26702 | H15: =H11-H13 -> 27196.248 | I15: =I11-I13 -> 27763.533 | ... L15: =L11-L13 -> 29967.996
A18: Beginning Balance | C18: 22770 | D18: =C26 -> 24705 | E18: =D26 -> 25199 | F18: =E26 -> 25631 | G18: =F26 -> 26154 | H18: =G26 -> 26702 | I18: =H26 -> 27196.248 | J18: =I26 -> 27763.533 | K18: =J26 -> 28410.019 | L18: =K26 -> 29142.409
A19: Additions--capital expenditures | C19: =-Financials!C110 -> 2463 | D19: =-Financials!D110 -> 2566 | E19: =-Financials!E110 -> 3119 | F19: =-Financials!F110 -> 3226 | G19: =-Financials!G110 -> 3485 | H19: =AVERAGE(H52,H64,H87) -> 3599.3031 | I19: =AVERAGE(I52,I64,I87) -> 3871.9685 | J19: =AVERAGE(J52,J64,J87) -> 4165.9455 | K19: =AVERAGE(K52,K64,K87) -> 4482.9583 | L19: =AVERAGE(L52,L64,L87) -> 4824.8747
A20: Additions--mergers & acquisitions
A21: Additions--new finance leases | C21: =C10-B10 -> 1730 | D21: 672 | E21: 322 | F21: 336 | G21: 153 | H21: 0 | I21: 0 | J21: 0 | K21: 0 | L21: 0
A22: Impairments | C22: 0 | D22: 0 | E22: 0 | F22: 0 | G22: 0 | H22: 0 | I22: 0 | J22: 0 | K22: 0 | L22: 0
A23: Disposals | C23: =IF(C31>0,-C31,0) -> 0 | D23: =IF(D31>0,-D31,0) -> 0 | E23: =IF(E31>0,-E31,0) -> 0 | F23: =IF(F31>0,-F31,0) -> 0 | G23: =IF(G31>0,-G31,0) -> 0 | H23: =IF(H31>0,-H31,0) -> -6 | I23: =IF(I31>0,-I31,0) -> -6 | J23: =IF(J31>0,-J31,0) -> -6 | ... L23: =IF(L31>0,-L31,0) -> -6
A24: Depreciation | C24: -2425 | D24: =-2650 -> -2650 | E24: =-Financials!E89 -> -2796 | F24: =-Financials!F89 -> -3061 | G24: =-Financials!G89 -> -3336 | H24: =-G11/H40 -> -3099.0556 | I24: =-H11/I40 -> -3298.6835 | J24: =-I11/J40 -> -3513.4595 | K24: =-J11/K40 -> -3744.5676 | L24: =-K11/L40 -> -3993.2875
A25: Unknown | C25: 167 | D25: -94 | E25: -213 | F25: 22 | G25: 246
A26: Ending Balance | C26: =SUM(C18:C25) -> 24705 | D26: =SUM(D18:D25) -> 25199 | E26: =SUM(E18:E25) -> 25631 | F26: =SUM(F18:F25) -> 26154 | G26: =SUM(G18:G25) -> 26702 | H26: =SUM(H18:H25) -> 27196.248 | I26: =SUM(I18:I25) -> 27763.533 | J26: =SUM(J18:J25) -> 28410.019 | ... L26: =SUM(L18:L25) -> 29967.996
A29: SALE/DISPOSAL OF PP&E
A30: Cash received | B30: =Financials!B112 -> 37 | C30: =Financials!C112 -> 0 | D30: =Financials!D112 -> 0 | E30: =Financials!E112 -> 0 | F30: =Financials!F112 -> 0 | G30: =Financials!G112 -> 0 | H30: 6 | I30: 6 | J30: 6 | K30: 6 | L30: 6
A31: Net PP&E | B31: =B30-B32 -> 37 | C31: =C30-C32 -> 0 | D31: =D30-D32 -> 0 | E31: =E30-E32 -> 0 | F31: =F30-F32 -> 0 | G31: =G30-G32 -> 0 | H31: =H30-H32 -> 6 | I31: =I30-I32 -> 6 | ... L31: =L30-L32 -> 6
A32: Gain (loss) | B32: 0 | C32: 0 | D32: 0 | E32: 0 | F32: 0 | G32: 0 | H32: 0 | I32: 0 | J32: 0 | K32: 0 | L32: 0
A34: Average Cash | G34: =AVERAGE(B30:G30) -> 6.1666667
A35: Average Gain | G35: =AVERAGE(B32:F32) -> 0
A38: FORECAST DEPRECIATION EXPENSE
A40: Average Useful Life | C40: =AVERAGE(B11:C11)/-C24 -> 19.311546 | D40: =AVERAGE(C11:D11)/-D24 -> 18.892453 | E40: =AVERAGE(D11:E11)/-E24 -> 18.527182 | F40: =AVERAGE(E11:F11)/-F24 -> 17.238157 | G40: =AVERAGE(F11:G11)/-G24 -> 16.342926 | H40: 18 | I40: 18 | J40: 18 | K40: 18 | L40: 18
A41: 5 year average | G41: =AVERAGE(C40:G40) -> 18.062453
A44: Depreciation on income statement | C44: =Financials!C63 -> 2128 | D44: =Financials!D63 -> 2386 | E44: =Financials!E63 -> 2455 | F44: =Financials!F63 -> 2673 | G44: =Financials!G63 -> 3034 | H44: =H45*H46 -> 2758.1594 | I44: =I45*I46 -> 2935.8283 | J44: =J45*J46 -> 3126.979 | K44: =K45*K46 -> 3332.6652 | L44: =L45*L46 -> 3554.0259
A45: Total depreciation expense | C45: =-C24 -> 2425 | D45: =-D24 -> 2650 | E45: =-E24 -> 2796 | F45: =-F24 -> 3061 | G45: =-G24 -> 3336 | H45: =-H24 -> 3099.0556 | I45: =-I24 -> 3298.6835 | J45: =-J24 -> 3513.4595 | ... L45: =-L24 -> 3993.2875
A46: Ratio | C46: =C44/C45 -> 0.87752577 | D46: =D44/D45 -> 0.90037736 | E46: =E44/E45 -> 0.87804006 | F46: =F44/F45 -> 0.87324404 | G46: =G44/G45 -> 0.90947242 | H46: 0.89 | I46: 0.89 | J46: 0.89 | K46: 0.89 | L46: 0.89
A50: FORECAST CAPITAL EXPENDITURES METHOD 1--LINK TO COMPANY OWNED STORES
A52: Capital expenditures | C52: =C19 -> 2463 | D52: =D19 -> 2566 | E52: =E19 -> 3119 | F52: =F19 -> 3226 | G52: =G19 -> 3485 | H52: =H54*H57 -> 3806.9353 | I52: =I54*I57 -> 4158.6249 | J52: =J54*J57 -> 4542.8202 | K52: =K54*K57 -> 4962.5272 | L52: =L54*L57 -> 5421.0299
A54: Number of company operated stores: | C54: =Revenue!C53 -> 2296 | D54: =Revenue!D53 -> 2317 | E54: =Revenue!E53 -> 2322 | F54: =Revenue!F53 -> 2335 | G54: =Revenue!G53 -> 2347 | H54: =Revenue!H53 -> 2358.3937 | I54: =Revenue!I53 -> 2369.8511 | J54: =Revenue!J53 -> 2381.3727 | ... L54: =Revenue!L53 -> 2404.6099
A56: Capital expenditures per company store
A57: Average | C57: =C52/C54 -> 1.0727352 | D57: =D52/D54 -> 1.1074666 | E57: =E52/E54 -> 1.3432386 | F57: =F52/F54 -> 1.3815846 | G57: =G52/G54 -> 1.4848743 | H57: =G57*(1+H58) -> 1.6142069 | I57: =H57*(1+I58) -> 1.7548043 | J57: =I57*(1+J58) -> 1.9076477 | K57: =J57*(1+K58) -> 2.0738038 | L57: =K57*(1+L58) -> 2.2544322
A58: % change | D58: =(D57-C57)/C57 -> 0.032376452 | E58: =(E57-D57)/D57 -> 0.21289314 | F58: =(F57-E57)/E57 -> 0.028547419 | G58: =(G57-F57)/F57 -> 0.074761782 | H58: 0.0871 | I58: 0.0871 | J58: 0.0871 | K58: 0.0871 | L58: 0.0871
A62: FORECAST CAPITAL EXPENDITURES METHOD 2--AS A % REVENUE
A64: Capital expenditures | C64: =C19 -> 2463 | D64: =D19 -> 2566 | E64: =E19 -> 3119 | F64: =F19 -> 3226 | G64: =G19 -> 3485 | H64: =H66*H68 -> 3380.6487 | I64: =I66*I68 -> 3637.0558 | J64: =J66*J68 -> 3913.0439 | K64: =K66*K68 -> 4210.1177 | L64: =L66*L68 -> 4529.898
A66: Revenue | C66: =Financials!C55 -> 132110 | D66: =Financials!D55 -> 151157 | E66: =Financials!E55 -> 157403 | F66: =Financials!F55 -> 152669 | G66: =Financials!G55 -> 159514 | H66: =Financials!H55 -> 171606.53 | I66: =Financials!I55 -> 184622.12 | J66: =Financials!J55 -> 198631.67 | ... L66: =Financials!L55 -> 229944.06
A68: Capital expenditures divided by revenue | C68: =C64/C66 -> 0.018643555 | D68: =D64/D66 -> 0.016975727 | E68: =E64/E66 -> 0.019815378 | F68: =F64/F66 -> 0.021130681 | G68: =G64/G66 -> 0.021847612 | H68: 0.0197 | I68: 0.0197 | J68: 0.0197 | K68: 0.0197 | L68: 0.0197
A69: Average | G69: =AVERAGE(C68:G68) -> 0.019682591
A73: FORECAST CAPITAL EXPENDITURES METHOD 3--FORECAST THE NET PP&E REQUIRED FOR EACH STORE
A75: Gross PP&E | B75: =B11 -> 44860 | C75: =C11 -> 48801 | D75: =D11 -> 51329 | E75: =E11 -> 52275 | F75: =F11 -> 53257 | G75: =G11 -> 55783 | H75: =G75+H80+H81+H82+H83+H87 -> 59387.325 | I75: =H75+I80+I82+I83+I87 -> 63201.55 | J75: =I75+J80+J82+J83+J87 -> 67237.523 | K75: =J75+K80+K82+K83+K87 -> 71507.753 | L75: =K75+L80+L82+L83+L87 -> 76025.449
A76: Accumulated depreciation | B76: =B13 -> 22090 | C76: =C13 -> 24096 | D76: =D13 -> 26130 | E76: =E13 -> 26644 | F76: =F13 -> 27103 | G76: =G13 -> 29081 | H76: =G76-H84 -> 32180.056 | I76: =H76-I84 -> 35479.351 | J76: =I76-J84 -> 38990.549 | K76: =J76-K84 -> 42725.967 | L76: =K76-L84 -> 46698.62
A77: Net PP&E | B77: =B75-B76 -> 22770 | C77: =C75-C76 -> 24705 | D77: =D75-D76 -> 25199 | E77: =E75-E76 -> 25631 | F77: =F75-F76 -> 26154 | G77: =G75-G76 -> 26702 | H77: =H75-H76 -> 27207.27 | I77: =I75-I76 -> 27722.199 | ... L77: =L75-L76 -> 29326.829
A79: Beginning Balance | C79: =C18 -> 22770 | D79: =C88 -> 24705 | E79: =D88 -> 25199 | F79: =E88 -> 25631 | G79: =F88 -> 26154 | H79: =G88 -> 26702 | I79: =H88 -> 27207.27 | J79: =I88 -> 27722.199 | K79: =J88 -> 28246.974 | L79: =K88 -> 28781.786
A80: PP&E acquired through acquisitions | C80: =C20 -> 0 | D80: =D20 -> 0 | E80: =E20 -> 0 | F80: =F20 -> 0 | G80: =G20 -> 0
A81: New finance leases | C81: =C21 -> 1730 | D81: =D21 -> 672 | E81: =E21 -> 322 | F81: =F21 -> 336 | G81: =G21 -> 153 | H81: 0 | I81: 0 | J81: 0 | K81: 0 | L81: 0
A82: Impairments | C82: =C22 -> 0 | D82: =D22 -> 0 | E82: =E22 -> 0 | F82: =F22 -> 0 | G82: =G22 -> 0 | H82: 0 | I82: 0 | J82: 0 | K82: 0 | L82: 0
A83: Disposals | C83: =C23 -> 0 | D83: =D23 -> 0 | E83: =E23 -> 0 | F83: =F23 -> 0 | G83: =G23 -> 0 | H83: =IF(H31>0,-H31,0) -> -6 | I83: =IF(I31>0,-I31,0) -> -6 | J83: =IF(J31>0,-J31,0) -> -6 | K83: =IF(K31>0,-K31,0) -> -6 | L83: =IF(L31>0,-L31,0) -> -6
A84: Depreciation | C84: =C24 -> -2425 | D84: =D24 -> -2650 | E84: =E24 -> -2796 | F84: =F24 -> -3061 | G84: =G24 -> -3336 | H84: =-G75/H40 -> -3099.0556 | I84: =-H75/I40 -> -3299.2959 | J84: =-I75/J40 -> -3511.1972 | K84: =-J75/K40 -> -3735.4179 | L84: =-K75/L40 -> -3972.6529
A85: Unknown | C85: =C25 -> 167 | D85: =D25 -> -94 | E85: =E25 -> -213 | F85: =F25 -> 22 | G85: =G25 -> 246
A86: PP&E before capital expenditures | C86: =SUM(C79:C85) -> 22242 | D86: =SUM(D79:D85) -> 22633 | E86: =SUM(E79:E85) -> 22512 | F86: =SUM(F79:F85) -> 22928 | G86: =SUM(G79:G85) -> 23217 | H86: =SUM(H79:H85) -> 23596.944 | I86: =SUM(I79:I85) -> 23901.974 | J86: =SUM(J79:J85) -> 24205.002 | ... L86: =SUM(L79:L85) -> 24803.133
A87: Capital Expenditures | C87: =C19 -> 2463 | D87: =D19 -> 2566 | E87: =E19 -> 3119 | F87: =F19 -> 3226 | G87: =G19 -> 3485 | H87: =H88-H86 -> 3610.3253 | I87: =I88-I86 -> 3820.2249 | J87: =J88-J86 -> 4041.9725 | K87: =K88-K86 -> 4276.23 | L87: =L88-L86 -> 4523.696
A88: Ending Balance | C88: =C86+C87 -> 24705 | D88: =D86+D87 -> 25199 | E88: =E86+E87 -> 25631 | F88: =F86+F87 -> 26154 | G88: =G86+G87 -> 26702 | H88: =H91*H93 -> 27207.27 | I88: =I91*I93 -> 27722.199 | J88: =J91*J93 -> 28246.974 | K88: =K91*K93 -> 28781.786 | L88: =L91*L93 -> 29326.829
A91: Company owned stores | C91: =C54 -> 2296 | D91: =D54 -> 2317 | E91: =E54 -> 2322 | F91: =F54 -> 2335 | G91: =G54 -> 2347 | H91: =H54 -> 2358.3937 | I91: =I54 -> 2369.8511 | J91: =J54 -> 2381.3727 | ... L91: =L54 -> 2404.6099
A93: Net PP&E per store | C93: =C88/C91 -> 10.760017 | D93: =D88/D91 -> 10.875701 | E93: =E88/E91 -> 11.038329 | F93: =F88/F91 -> 11.200857 | G93: =G88/G91 -> 11.377077 | H93: =G93*(1+H94) -> 11.536356 | I93: =H93*(1+I94) -> 11.697865 | J93: =I93*(1+J94) -> 11.861635 | K93: =J93*(1+K94) -> 12.027698 | L93: =K93*(1+L94) -> 12.196086
A94: % growth | D94: =(D93-C93)/C93 -> 0.010751276 | E94: =(E93-D93)/D93 -> 0.014953306 | F94: =(F93-E93)/E93 -> 0.014723923 | G94: =(G93-F93)/F93 -> 0.015732778 | H94: 0.014 | I94: 0.014 | J94: 0.014 | K94: 0.014 | L94: 0.014
A100: Intangible Assets
A101: Beginning balance | C101: 337 | D101: =C106 -> 3612 | E101: =D106 -> 3503 | F101: =E106 -> 3323 | G101: =F106 -> 3606 | H101: =G106 -> 8983 | I101: =H106 -> 8430 | J101: =I106 -> 7877 | K101: =J106 -> 7332 | L101: =K106 -> 6804
A102: Additions | C102: 3300 | D102: 65 | F102: 469 | G102: 5780 | H102: 0 | I102: 0 | J102: 0 | K102: 0 | L102: 0
A103: Divestitures
A104: Amortization--definite lived only | C104: -25 | D104: -174 | E104: -179 | F104: -186 | G104: -425 | H104: -553 | I104: -553 | J104: -545 | K104: -528 | L104: -486
A105: Impairment and other | E105: -1 | G105: 22
A106: Ending balance | C106: =SUM(C101:C105) -> 3612 | D106: =SUM(D101:D105) -> 3503 | E106: =SUM(E101:E105) -> 3323 | F106: =SUM(F101:F105) -> 3606 | G106: =SUM(G101:G105) -> 8983 | H106: =SUM(H101:H105) -> 8430 | I106: =SUM(I101:I105) -> 7877 | J106: =SUM(J101:J105) -> 7332 | ... L106: =SUM(L101:L105) -> 6318
A108: Goodwill
A109: Beginning balance | B109: 2252 | C109: =B113 -> 2254 | D109: =C113 -> 7126 | E109: =D113 -> 7449 | F109: =E113 -> 7444 | G109: =F113 -> 8455 | H109: =G113 -> 19475 | I109: =H113 -> 19475 | J109: =I113 -> 19475 | ... L109: =K113 -> 19475
A110: Acquisitions | B110: 0 | C110: 4870 | D110: 323 | F110: 998 | G110: =23+11025 -> 11048
A111: Dispositions | B111: 0
A112: Other | B112: 2 | C112: 2 | E112: -5 | F112: 13 | G112: -28
A113: Ending balance | B113: =SUM(B109:B112) -> 2254 | C113: =SUM(C109:C112) -> 7126 | D113: =SUM(D109:D112) -> 7449 | E113: =SUM(E109:E112) -> 7444 | F113: =SUM(F109:F112) -> 8455 | G113: =SUM(G109:G112) -> 19475 | H113: =SUM(H109:H112) -> 19475 | I113: =SUM(I109:I112) -> 19475 | ... L113: =SUM(L109:L112) -> 19475
A115: Disclosed Amortization Expense
A121: Other Assets | B121: =Financials!B16 -> 807 | C121: =Financials!C16 -> 699 | D121: =Financials!D16 -> 702 | E121: =Financials!E16 -> 635 | F121: =Financials!F16 -> 656 | G121: =Financials!G16 -> 684 | H121: =Financials!H55*'Long Term Asset & Liab'!H122 -> 772.2294 | I121: =Financials!I55*'Long Term Asset & Liab'!I122 -> 830.79955 | J121: =Financials!J55*'Long Term Asset & Liab'!J122 -> 893.84252 | K121: =Financials!K55*'Long Term Asset & Liab'!K122 -> 961.70201 | L121: =Financials!L55*'Long Term Asset & Liab'!L122 -> 1034.7483
A122: Percentage of Revenue | B122: =B121/Financials!B55 -> 0.0073213881 | C122: =C121/Financials!C55 -> 0.0052910453 | D122: =D121/Financials!D55 -> 0.0046441779 | E122: =E121/Financials!E55 -> 0.0040342306 | F122: =F121/Financials!F55 -> 0.0042968776 | G122: =G121/Financials!G55 -> 0.0042880249 | H122: 0.0045 | I122: 0.0045 | J122: 0.0045 | K122: 0.0045 | L122: 0.0045
A123: 5 year average | G123: =AVERAGE(C122:G122) -> 0.0045108713
A126: Other long-term obligations | B126: =Financials!B35 -> 1535 | C126: =Financials!C35 -> 1807 | D126: =Financials!D35 -> 2013 | E126: =Financials!E35 -> 2566 | F126: =Financials!F35 -> 2783 | G126: =Financials!G35 -> 2738 | H126: =Financials!H55*'Long Term Asset & Liab'!H127 -> 2694.2226 | I126: =Financials!I55*'Long Term Asset & Liab'!I127 -> 2898.5673 | J126: =Financials!J55*'Long Term Asset & Liab'!J127 -> 3118.5173 | K126: =Financials!K55*'Long Term Asset & Liab'!K127 -> 3355.2715 | L126: =Financials!L55*'Long Term Asset & Liab'!L127 -> 3610.1218
A127: Percentage of Revenue | B127: =B126/Financials!B55 -> 0.01392606 | C127: =C126/Financials!C55 -> 0.013677996 | D127: =D126/Financials!D55 -> 0.013317279 | E127: =E126/Financials!E55 -> 0.016302104 | F127: =F126/Financials!F55 -> 0.018228979 | G127: =G126/Financials!G55 -> 0.017164638 | H127: 0.0157 | I127: 0.0157 | J127: 0.0157 | K127: 0.0157 | L127: 0.0157
A128: 5 year average | G128: =AVERAGE(C127:G127) -> 0.015738199
A131: Deferred tax liability | B131: =Financials!B34 -> 706 | C131: =Financials!C34 -> 1131 | D131: =Financials!D34 -> 909 | E131: =Financials!E34 -> 1019 | F131: =Financials!F34 -> 863 | G131: =Financials!G34 -> 1962 | H131: =H137*H139 -> 1575.8957 | I131: =I137*I139 -> 1576.3042 | J131: =J137*J139 -> 1579.2067 | K131: =K137*K139 -> 1585.0523 | L131: =L137*L139 -> 1594.7645
A133: Underlying Assets/Liabilities
A134: PP&E | B134: =Financials!B12 -> 22770 | C134: =Financials!C12 -> 24705 | D134: =Financials!D12 -> 25199 | E134: =Financials!E12 -> 25631 | F134: =Financials!F12 -> 26154 | G134: =Financials!G12 -> 26702 | H134: =Financials!H12 -> 27196.248 | I134: =Financials!I12 -> 27763.533 | ... L134: =Financials!L12 -> 29967.996
A135: Goodwill | B135: =Financials!B14 -> 2254 | C135: =Financials!C14 -> 7126 | D135: =Financials!D14 -> 7449 | E135: =Financials!E14 -> 7444 | F135: =Financials!F14 -> 8455 | G135: =Financials!G14 -> 19475 | H135: =Financials!H14 -> 19475 | I135: =Financials!I14 -> 19475 | ... L135: =Financials!L14 -> 19475
A136: Intangible Assets | B136: =Financials!B15 -> 0 | C136: =Financials!C15 -> 3612 | D136: =Financials!D15 -> 3503 | E136: =Financials!E15 -> 3323 | F136: =Financials!F15 -> 3606 | G136: =Financials!G15 -> 8983 | H136: =Financials!H15 -> 8430 | I136: =Financials!I15 -> 7877 | ... L136: =Financials!L15 -> 6318
A137: Total | B137: =SUM(B134:B136) -> 25024 | C137: =SUM(C134:C136) -> 35443 | D137: =SUM(D134:D136) -> 36151 | E137: =SUM(E134:E136) -> 36398 | F137: =SUM(F134:F136) -> 38215 | G137: =SUM(G134:G136) -> 55160 | H137: =SUM(H134:H136) -> 55101.248 | I137: =SUM(I134:I136) -> 55115.533 | ... L137: =SUM(L134:L136) -> 55760.996
A139: Percentage of underlying | B139: =B131/B137 -> 0.028212916 | C139: =C131/C137 -> 0.031910391 | D139: =D131/D137 -> 0.025144533 | E139: =E131/E137 -> 0.027996044 | F139: =F131/F137 -> 0.022582755 | G139: =G131/G137 -> 0.035569253 | H139: 0.0286 | I139: 0.0286 | J139: 0.0286 | K139: 0.0286 | L139: 0.0286
A140: 5 year average | G140: =AVERAGE(C139:G139) -> 0.028640595

Sheet Financing
A1: The Home Depot, Inc. | B1: ACTUAL | H1: FORECAST
A2: (in millions) | B2: 43863 | C2: 44227 | D2: 44591 | E2: 44955 | F2: 45319 | G2: 45690 | H2: 46053 | I2: 46418 | J2: 46783 | K2: 47149 | L2: 47514
A4: Current maturities long-term debt--actual | B4: =Financials!B27 -> 1839 | C4: =Financials!C27 -> 1416 | D4: =Financials!D27 -> 2447 | E4: =Financials!E27 -> 1231 | F4: =Financials!F27 -> 1368 | G4: =Financials!G27 -> 4582
A6: Beginning Balance | C6: =B9 -> 1839 | D6: =C9 -> 1416 | E6: =D9 -> 2447 | F6: =E9 -> 1231 | G6: =F9 -> 1368 | H6: =G9 -> 4582 | I6: =H9 -> 4845 | J6: =I9 -> 3769 | ... L6: =K9 -> 3946
A7: Payments | C7: =-C6 -> -1839 | D7: =-D6 -> -1416 | E7: =-E6 -> -2447 | F7: =-F6 -> -1231 | G7: =-G6 -> -1368 | H7: =-H6 -> -4582 | I7: =-I6 -> -4845 | J7: =-J6 -> -3769 | ... L7: =-L6 -> -3946
A8: Transfer from Long-term | C8: =C4 -> 1416 | D8: =D4 -> 2447 | E8: =E4 -> 1231 | F8: =F4 -> 1368 | G8: =G4 -> 4582 | H8: =-I24 -> 4845 | I8: =-J24 -> 3769 | J8: =-K24 -> 2727 | K8: =-L24 -> 3946 | L8: =-M24 -> 3946
A9: Ending Balance | B9: =B4 -> 1839 | C9: =SUM(C6:C8) -> 1416 | D9: =SUM(D6:D8) -> 2447 | E9: =SUM(E6:E8) -> 1231 | F9: =SUM(F6:F8) -> 1368 | G9: =SUM(G6:G8) -> 4582 | H9: =SUM(H6:H8) -> 4845 | I9: =SUM(I6:I8) -> 3769 | J9: =SUM(J6:J8) -> 2727 | ... L9: =SUM(L6:L8) -> 3946
A12: Long-term debt--balance sheet--actual | B12: =Financials!B32 -> 28670 | C12: =Financials!C32 -> 35822 | D12: =Financials!D32 -> 36604 | E12: =Financials!E32 -> 41962 | F12: =Financials!F32 -> 42743 | G12: =Financials!G32 -> 48485
A14: Beginning Balance | C14: =B21 -> 28670 | D14: =C21 -> 35822 | E14: =D21 -> 36604 | F14: =E21 -> 41962 | G14: =F21 -> 42743 | H14: =G21 -> 48485 | I14: =H21 -> 43640 | J14: =I21 -> 39871 | ... L14: =K21 -> 33198
A15: Payments | C15: =C25 -> -1033 | D15: =D25 -> -116 | E15: =E25 -> -44 | F15: =F25 -> -40 | G15: =G25 -> -168
A16: Transfer to short-term | C16: =-C8 -> -1416 | D16: =-D8 -> -2447 | E16: =-E8 -> -1231 | F16: =-F8 -> -1368 | G16: =-G8 -> -4582 | H16: =-H8 -> -4845 | I16: =-I8 -> -3769 | J16: =-J8 -> -2727 | ... L16: =-L8 -> -3946
A17: Additions--new debt | C17: =Financials!C120 -> 7933 | D17: =Financials!D120 -> 2979 | E17: =Financials!E120 -> 6942 | F17: =Financials!F120 -> 1995 | G17: =Financials!G120 -> 10010
A18: Debt incurred in acquisitions
A19: New finance leases | C19: ='Long Term Asset & Liab'!C21 -> 1730 | D19: ='Long Term Asset & Liab'!D21 -> 672 | E19: ='Long Term Asset & Liab'!E21 -> 322 | F19: ='Long Term Asset & Liab'!F21 -> 336 | G19: ='Long Term Asset & Liab'!G21 -> 153
A20: Unknown | C20: -62 | D20: -306 | E20: -631 | F20: -142 | G20: 329
A21: Ending Balance | B21: =B12 -> 28670 | C21: =SUM(C14:C20) -> 35822 | D21: =SUM(D14:D20) -> 36604 | E21: =SUM(E14:E20) -> 41962 | F21: =SUM(F14:F20) -> 42743 | G21: =SUM(G14:G20) -> 48485 | H21: =SUM(H14:H20) -> 43640 | I21: =SUM(I14:I20) -> 39871 | J21: =SUM(J14:J20) -> 37144 | ... L21: =SUM(L14:L20) -> 29252
A24: Minimum Debt Payments | C24: =C7 -> -1839 | D24: =D7 -> -1416 | E24: =E7 -> -2447 | F24: =F7 -> -1231 | G24: =G7 -> -1368 | H24: -4582 | I24: =-4608-237 -> -4845 | J24: =-3559-210 -> -3769 | K24: =-2554-173 -> -2727 | L24: =-3799-147 -> -3946 | M24: =L24 -> -3946
A25: Additional Payments--if have extra cash | C25: =C26-C24 -> -1033 | D25: =D26-D24 -> -116 | E25: =E26-E24 -> -44 | F25: =F26-F24 -> -40 | G25: =G26-G24 -> -168
A26: Total Debt Payments | C26: =Financials!C121 -> -2872 | D26: =Financials!D121 -> -1532 | E26: =Financials!E121 -> -2491 | F26: =Financials!F121 -> -1271 | G26: =Financials!G121 -> -1536 | H26: =H24+H25 -> -4582 | I26: =I24+I25 -> -4845 | J26: =J24+J25 -> -3769 | K26: =K24+K25 -> -2727 | L26: =L24+L25 -> -3946
A29: Interest Expense | C29: =Financials!C71 -> 1347 | D29: =Financials!D71 -> 1347 | E29: =Financials!E71 -> 1617 | F29: =Financials!F71 -> 1943 | G29: =Financials!G71 -> 2321 | H29: =(G9+G21)*H31 -> 2191.6671 | I29: =(H9+H21)*I31 -> 2002.4305 | J29: =(I9+I21)*J31 -> 1802.332 | K29: =(J9+J21)*K31 -> 1646.6723 | L29: =(K9+K21)*L31 -> 1534.0472
A31: Interest Rate (interest expense/average debt) | C31: =C29/((B9+C9+B21+C21)/2) -> 0.039765598 | D31: =D29/((C9+D9+C21+D21)/2) -> 0.035313086 | E31: =E29/((D9+E9+D21+E21)/2) -> 0.039322017 | F31: =F29/((E9+F9+E21+F21)/2) -> 0.044511134 | G31: =G29/((F9+G9+F21+G21)/2) -> 0.047768013 | H31: 0.0413 | I31: 0.0413 | J31: 0.0413 | K31: 0.0413 | L31: 0.0413
A47: Owners Equity
A49: Common stock | B49: =Financials!B39 -> 89 | C49: =Financials!C39 -> 89 | D49: =Financials!D39 -> 90 | E49: =Financials!E39 -> 90 | F49: =Financials!F39 -> 90 | G49: =Financials!G39 -> 90 | H49: =G49 -> 90 | I49: =H49 -> 90 | J49: =I49 -> 90 | K49: =J49 -> 90 | L49: =K49 -> 90
A50: Additional paid in capital | B50: =Financials!B40 -> 11001 | C50: =Financials!C40 -> 11540 | D50: =Financials!D40 -> 12132 | E50: =Financials!E40 -> 12592 | F50: =Financials!F40 -> 13147 | G50: =Financials!G40 -> 14117 | H50: =H51-H49 -> 14811.189 | I50: =I51-I49 -> 15560.124 | J50: =J51-J49 -> 16368.218 | K50: =K51-K49 -> 17240.231 | L50: =L51-L49 -> 18181.727
A51: Total common equity | B51: =B49+B50 -> 11090 | C51: =C49+C50 -> 11629 | D51: =D49+D50 -> 12222 | E51: =E49+E50 -> 12682 | F51: =F49+F50 -> 13237 | G51: =G49+G50 -> 14207 | H51: =H57 -> 14901.189 | I51: =I57 -> 15650.124 | J51: =J57 -> 16458.218 | K51: =K57 -> 17330.231 | L51: =L57 -> 18271.727
A53: Beginning balance | C53: =B51 -> 11090 | D53: =C57 -> 11629 | E53: =D57 -> 12222 | F53: =E57 -> 12682 | G53: =F57 -> 13237 | H53: =G57 -> 14207 | I53: =H57 -> 14901.189 | J53: =I57 -> 15650.124 | K53: =J57 -> 16458.218 | L53: =K57 -> 17330.231
A54: Issue new stock
A55: Share-based compensation--issue stock | C55: 229 | D55: =1+194 -> 195 | E55: 94 | F55: 175 | G55: 528 | H55: =H64*H56 -> 268.33214 | I55: =I64*I56 -> 289.49404 | J55: =J64*J56 -> 312.36118 | K55: =K64*K56 -> 337.06864 | L55: =L64*L56 -> 363.92644
A56: Share-based compensation--expense | C56: 310 | D56: 398 | E56: 366 | F56: 380 | G56: 442 | H56: =Financials!H67*H61 -> 425.85643 | I56: =Financials!I67*I61 -> 459.44143 | J56: =Financials!J67*J61 -> 495.73271 | K56: =Financials!K67*K61 -> 534.94467 | L56: =Financials!L67*L61 -> 577.56935
A57: Ending balance | C57: =SUM(C53:C56) -> 11629 | D57: =SUM(D53:D56) -> 12222 | E57: =SUM(E53:E56) -> 12682 | F57: =SUM(F53:F56) -> 13237 | G57: =SUM(G53:G56) -> 14207 | H57: =SUM(H53:H56) -> 14901.189 | I57: =SUM(I53:I56) -> 15650.124 | J57: =SUM(J53:J56) -> 16458.218 | ... L57: =SUM(L53:L56) -> 18271.727
A60: Stock compensation
A61: Compensation Expense as a % operating income | C61: =C56/Financials!E67 -> 0.012895711 | D61: =D56/Financials!F67 -> 0.018350316 | E61: =E56/Financials!G67 -> 0.017002694 | F61: =F56/Financials!H67 -> 0.015615591 | G61: =G56/Financials!I67 -> 0.016835661 | H61: 0.0175 | I61: 0.0175 | J61: 0.0175 | K61: 0.0175 | L61: 0.0175
A62: average | G62: =AVERAGE(C61:G61) -> 0.016139995
A64: Stock issuance as a % compensation expense | C64: =C55/C56 -> 0.73870968 | D64: =D55/D56 -> 0.48994975 | E64: =E55/E56 -> 0.2568306 | F64: =F55/F56 -> 0.46052632 | G64: =G55/G56 -> 1.1945701 | H64: 0.6301 | I64: 0.6301 | J64: 0.6301 | K64: 0.6301 | L64: 0.6301
A65: average | G65: =AVERAGE(C64:G64) -> 0.6281173
A68: Shares issued | C68: =C89 -> 3 | D68: =D89 -> 3 | E68: =E89 -> 2 | F68: =F89 -> 2 | G68: =G89 -> 4 | H68: =G73*H75 -> 2.4001644 | I68: =H73*I75 -> 2.74984 | J68: =I73*J75 -> 2.74984 | K68: =J73*K75 -> 2.74984 | L68: =K73*L75 -> 2.74984
A70: Shares Available
A71: Stock options outstanding | B71: 5.212 | C71: 4.35 | D71: 3.641 | E71: 3.626 | F71: 3.085 | G71: 2.201 | H71: 3.6 | I71: 3.6 | J71: 3.6 | K71: 3.6 | L71: 3.6
A72: Nonvested restricted & performance stock | B72: 3.975 | C72: 4.098 | D72: 3.709 | E72: 3.359 | F72: 3.386 | G72: =3.05+1.208 -> 4.258 | H72: 3.8 | I72: 3.8 | J72: 3.8 | K72: 3.8 | L72: 3.8
B73: =SUM(B71:B72) -> 9.187 | C73: =SUM(C71:C72) -> 8.448 | D73: =SUM(D71:D72) -> 7.35 | E73: =SUM(E71:E72) -> 6.985 | F73: =SUM(F71:F72) -> 6.471 | G73: =SUM(G71:G72) -> 6.459 | H73: =SUM(H71:H72) -> 7.4 | I73: =SUM(I71:I72) -> 7.4 | ... L73: =SUM(L71:L72) -> 7.4
A75: Percentage of previous year available issued in current year | C75: =C68/B73 -> 0.32654838 | D75: =D68/C73 -> 0.35511364 | E75: =E68/D73 -> 0.27210884 | F75: =F68/E73 -> 0.28632785 | G75: =G68/F73 -> 0.61814248 | H75: 0.3716 | I75: 0.3716 | J75: 0.3716 | K75: 0.3716 | L75: 0.3716
A76: Average | G76: =AVERAGE(C75:G75) -> 0.37164824
A79: Treasury Stock
A80: Beginning balance | C80: =B82 -> -65196 | D80: =C82 -> -65793 | E80: =D82 -> -80794 | F80: =E82 -> -87298 | G80: =F82 -> -95372 | H80: =G82 -> -95971 | I80: =H82 -> -102171 | J80: =I82 -> -108371 | ... L80: =K82 -> -120771
A81: Share repurchases | C81: -597 | D81: -15001 | E81: -6504 | F81: -8074 | G81: -599 | H81: =-H133 -> -6200 | I81: =-I133 -> -6200 | J81: =-J133 -> -6200 | K81: =-K133 -> -6200 | L81: =-L133 -> -6200
A82: Ending balance | B82: =Financials!B43 -> -65196 | C82: =C80+C81 -> -65793 | D82: =D80+D81 -> -80794 | E82: =E80+E81 -> -87298 | F82: =F80+F81 -> -95372 | G82: =G80+G81 -> -95971 | H82: =H80+H81 -> -102171 | I82: =I80+I81 -> -108371 | J82: =J80+J81 -> -114571 | ... L82: =L80+L81 -> -126971
A86: Shares Issued
A87: Beginning balance | B87: 1782 | C87: =B90 -> 1786 | D87: =C90 -> 1789 | E87: =D90 -> 1792 | F87: =E90 -> 1794 | G87: =F90 -> 1796 | H87: =G90 -> 1800 | I87: =H90 -> 1802.4002 | J87: =I90 -> 1805.15 | ... L87: =K90 -> 1810.6497
A88: New stock issuance | H88: =H54/H99 -> 0 | I88: =I54/I99 -> 0 | J88: =J54/J99 -> 0 | K88: =K54/K99 -> 0 | L88: =L54/L99 -> 0
A89: Issued to employees | B89: 4 | C89: 3 | D89: 3 | E89: 2 | F89: 2 | G89: 4 | H89: =H68 -> 2.4001644 | I89: =I68 -> 2.74984 | J89: =J68 -> 2.74984 | K89: =K68 -> 2.74984 | L89: =L68 -> 2.74984
A90: Ending balance | B90: =SUM(B87:B89) -> 1786 | C90: =SUM(C87:C89) -> 1789 | D90: =SUM(D87:D89) -> 1792 | E90: =SUM(E87:E89) -> 1794 | F90: =SUM(F87:F89) -> 1796 | G90: =SUM(G87:G89) -> 1800 | H90: =SUM(H87:H89) -> 1802.4002 | I90: =SUM(I87:I89) -> 1805.15 | ... L90: =SUM(L87:L89) -> 1813.3995
A92: Treasury Shares
A93: Beginning balance | B93: -677 | C93: =B95 -> -709 | D93: =C95 -> -712 | E93: =D95 -> -757 | F93: =E95 -> -778 | G93: =F95 -> -804 | H93: =G95 -> -806 | I93: =H95 -> -821.16782 | J93: =I95 -> -836.33565 | ... L93: =K95 -> -866.6713
A94: Repurchases | B94: -32 | C94: -3 | D94: -45 | E94: -21 | F94: -26 | G94: -2 | H94: =H81/H99 -> -15.167825 | I94: =I81/I99 -> -15.167825 | J94: =J81/J99 -> -15.167825 | K94: =K81/K99 -> -15.167825 | L94: =L81/L99 -> -15.167825
A95: Ending balance | B95: =B93+B94 -> -709 | C95: =C93+C94 -> -712 | D95: =D93+D94 -> -757 | E95: =E93+E94 -> -778 | F95: =F93+F94 -> -804 | G95: =G93+G94 -> -806 | H95: =H93+H94 -> -821.16782 | I95: =I93+I94 -> -836.33565 | ... L95: =L93+L94 -> -881.83912
A97: Net shares outstanding | B97: =B90+B95 -> 1077 | C97: =C90+C95 -> 1077 | D97: =D90+D95 -> 1035 | E97: =E90+E95 -> 1016 | F97: =F90+F95 -> 992 | G97: =G90+G95 -> 994 | H97: =H90+H95 -> 981.23234 | I97: =I90+I95 -> 968.81436 | ... L97: =L90+L95 -> 931.5604
A99: Stock price | D99: 366.54 | E99: 316.69 | F99: 355.3 | G99: 408.76 | H99: 408.76 | I99: 408.76 | J99: 408.76 | K99: 408.76 | L99: 408.76
A102: Dividends Declared
A103: Dividends paid | C103: =Financials!C124 -> -6451 | D103: =Financials!D124 -> -6985 | E103: =Financials!E124 -> -7789 | F103: =Financials!F124 -> -8383 | G103: =Financials!G124 -> -8929 | H103: =-G97*H105 -> -7524.58 | I103: =-H97*I105 -> -7427.9288 | J103: =-I97*J105 -> -7333.9247 | K103: =-J97*K105 -> -7239.9205 | L103: =-K97*L105 -> -7145.9164
A105: Dividends per share | C105: =-C103/C97 -> 5.9897864 | D105: =-D103/D97 -> 6.7487923 | E105: =-E103/E97 -> 7.6663386 | F105: =-F103/F97 -> 8.4506048 | G105: =-G103/G97 -> 8.9828974 | H105: 7.57 | I105: 7.57 | J105: 7.57 | K105: 7.57 | L105: 7.57
A110: Cash Requirements / Cash to Invest
A112: All changes to cash except for new debt, share repurchases and investments
A113: Cash from Operations | H113: =Financials!H107 -> 23537.63 | I113: =Financials!I107 -> 22515.838 | J113: =Financials!J107 -> 24452.046 | K113: =Financials!K107 -> 26336.327 | L113: =Financials!L107 -> 28187.079
A114: Cash For PP&E and Acquisitions | H114: =Financials!H110+Financials!H111+Financials!H112 -> -3593.3031 | I114: =Financials!I110+Financials!I111+Financials!I112 -> -3865.9685 | J114: =Financials!J110+Financials!J111+Financials!J112 -> -4159.9455 | K114: =Financials!K110+Financials!K111+Financials!K112 -> -4476.9583 | L114: =Financials!L110+Financials!L111+Financials!L112 -> -4818.8747
A115: Cash from stock options & other financing | H115: =H55 -> 268.33214 | I115: =I55 -> 289.49404 | J115: =J55 -> 312.36118 | K115: =K55 -> 337.06864 | L115: =L55 -> 363.92644
A116: Cash Paid for Dividends | H116: =H103 -> -7524.58 | I116: =I103 -> -7427.9288 | J116: =J103 -> -7333.9247 | K116: =K103 -> -7239.9205 | L116: =L103 -> -7145.9164
A117: Minimum Debt Payments | H117: =H24 -> -4582 | I117: =I24 -> -4845 | J117: =J24 -> -3769 | K117: =K24 -> -2727 | L117: =L24 -> -3946
A118: Net Cash Inflow / Outflow | H118: =SUM(H113:H117) -> 8106.0788 | I118: =SUM(I113:I117) -> 6666.4346 | J118: =SUM(J113:J117) -> 9501.5368 | K118: =SUM(K113:K117) -> 12229.516 | L118: =SUM(L113:L117) -> 12640.215
A119: Cash at Beginning of Year | H119: =Financials!G5 -> 1659 | I119: =Financials!H5 -> 2600 | J119: =Financials!I5 -> 2600 | K119: =Financials!J5 -> 2600 | L119: =Financials!K5 -> 2600
A120: Total Cash on Hand | H120: =H118+H119 -> 9765.0788 | I120: =I118+I119 -> 9266.4346 | J120: =J118+J119 -> 12101.537 | K120: =K118+K119 -> 14829.516 | L120: =L118+L119 -> 15240.215
A122: Minimum Cash Balance | H122: 2600 | I122: 2600 | J122: 2600 | K122: 2600 | L122: 2600
A123: average over past few years
A125: Financing Needed
A126: Total needed | H126: =IF(H120<H122,H122-H120,0) -> 0 | I126: =IF(I120<I122,I122-I120,0) -> 0 | J126: =IF(J120<J122,J122-J120,0) -> 0 | K126: =IF(K120<K122,K122-K120,0) -> 0 | L126: =IF(L120<L122,L122-L120,0) -> 0
A127: Desired Debt Ratio | H127: 1 | I127: 1 | J127: 1 | K127: 1 | L127: 1
A128: Financed by Debt | H128: =H126*H127 -> 0 | I128: =I126*I127 -> 0 | J128: =J126*J127 -> 0 | K128: =K126*K127 -> 0 | L128: =L126*L127 -> 0
A129: Financed by Equity | H129: =H126*(1-H127) -> 0 | I129: =I126*(1-I127) -> 0 | J129: =J126*(1-J127) -> 0 | K129: =K126*(1-K127) -> 0 | L129: =L126*(1-L127) -> 0
A131: Excess Cash
A132: Total excess | H132: =IF(H120>H122,H120-H122,0) -> 7165.0788 | I132: =IF(I120>I122,I120-I122,0) -> 6666.4346 | J132: =IF(J120>J122,J120-J122,0) -> 9501.5368 | K132: =IF(K120>K122,K120-K122,0) -> 12229.516 | L132: =IF(L120>L122,L120-L122,0) -> 12640.215
A133: Repurchase Stock | H133: 6200 | I133: 6200 | J133: 6200 | K133: 6200 | L133: 6200
A134: Pay Down Debt
A135: Purchase Investments | H135: =H132-H133-H134 -> 965.07883 | I135: =I132-I133-I134 -> 466.43461 | J135: =J132-J133-J134 -> 3301.5368 | K135: =K132-K133-K134 -> 6029.5164 | L135: =L132-L133-L134 -> 6440.2145
A137: Short-term Investments
A138: Beginning | H138: 0 | I138: =H141 -> 965.07883 | J138: =I141 -> 1431.5134 | K138: =J141 -> 4733.0502 | L138: =K141 -> 10762.567
A139: Additions | H139: =H135 -> 965.07883 | I139: =I135 -> 466.43461 | J139: =J135 -> 3301.5368 | K139: =K135 -> 6029.5164 | L139: =L135 -> 6440.2145
A140: Sell-off
A141: Ending | B141: 0 | C141: 0 | D141: 0 | E141: 0 | F141: 0 | G141: 0 | H141: =SUM(H138:H140) -> 965.07883 | I141: =SUM(I138:I140) -> 1431.5134 | J141: =SUM(J138:J140) -> 4733.0502 | K141: =SUM(K138:K140) -> 10762.567 | L141: =SUM(L138:L140) -> 17202.781
A143: Interest and investment income | B143: =-Financials!B70 -> 73 | C143: =-Financials!C70 -> 47 | D143: =-Financials!D70 -> 44 | E143: =-Financials!E70 -> 55 | F143: =-Financials!F70 -> 178 | G143: =-Financials!G70 -> 201 | H143: =G141*H145 -> 0 | I143: =H141*I145 -> 67.555518 | J143: =I141*J145 -> 100.20594 | K143: =J141*K145 -> 331.31351 | L143: =K141*L145 -> 753.37966
A145: % Investments | H145: 0.07 | I145: 0.07 | J145: 0.07 | K145: 0.07 | L145: 0.07

Sheet Free Cash Flows
A1: The Home Depot, Inc. | B1: ACTUAL | H1: FORECAST
A2: (in millions) | B2: 43863 | C2: 44227 | D2: 44591 | E2: 44955 | F2: 45319 | G2: 45690 | H2: 46053 | I2: 46418 | J2: 46783 | K2: 47149 | L2: 47514
A4: Earnings before Interest and Taxes | H4: =Financials!H75-Financials!H73 -> 19951.319 | I4: =Financials!I75-Financials!I73 -> 22113.824 | J4: =Financials!J75-Financials!J73 -> 24522.507 | K4: =Financials!K75-Financials!K73 -> 26612.295 | L4: =Financials!L75-Financials!L73 -> 28429.109
A5: Tax Rate | H5: =Expenses!H22 -> 0.2397 | I5: =Expenses!I22 -> 0.2397 | J5: =Expenses!J22 -> 0.2397 | K5: =Expenses!K22 -> 0.2397 | L5: =Expenses!L22 -> 0.2397
A6: Less Taxes | H6: =H4*H5 -> 4782.3311 | I6: =I4*I5 -> 5300.6835 | J6: =J4*J5 -> 5878.045 | K6: =K4*K5 -> 6378.9672 | L6: =L4*L5 -> 6814.4574
A7: Earnings After Tax | H7: =H4-H6 -> 15168.988 | I7: =I4-I6 -> 16813.14 | J7: =J4-J6 -> 18644.462 | K7: =K4-K6 -> 20233.328 | L7: =L4-L6 -> 21614.651
A9: Less Capital Expenditures (Net) | H9: =Financials!H110+Financials!H112 -> -3593.3031 | I9: =Financials!I110+Financials!I112 -> -3865.9685 | J9: =Financials!J110+Financials!J112 -> -4159.9455 | K9: =Financials!K110+Financials!K112 -> -4476.9583 | L9: =Financials!L110+Financials!L112 -> -4818.8747
A11: Add Depreciation and amortization | H11: =Financials!H89+Financials!H90 -> 3652.0556 | I11: =Financials!I89+Financials!I90 -> 3851.6835 | J11: =Financials!J89+Financials!J90 -> 4058.4595 | K11: =Financials!K89+Financials!K90 -> 4272.5676 | L11: =Financials!L89+Financials!L90 -> 4479.2875
A13: Add Other Non-cash Items | H13: ='Long Term Asset & Liab'!H32 -> 0 | I13: ='Long Term Asset & Liab'!I32 -> 0 | J13: ='Long Term Asset & Liab'!J32 -> 0 | K13: ='Long Term Asset & Liab'!K32 -> 0 | L13: ='Long Term Asset & Liab'!L32 -> 0
A15: Change in Working Capital Requirements | H15: =SUM(Financials!H94:H105) -> 2624.4056 | I15: =SUM(Financials!I94:I105) -> -182.23753 | J15: =SUM(Financials!J94:J105) -> -193.10849 | K15: =SUM(Financials!K94:K105) -> -208.37644 | L15: =SUM(Financials!L94:L105) -> -223.55984
A17: Free Cash Flows | H17: =SUM(H7:H15) -> 17852.146 | I17: =SUM(I7:I15) -> 16616.618 | J17: =SUM(J7:J15) -> 18349.868 | K17: =SUM(K7:K15) -> 19820.561 | L17: =SUM(L7:L15) -> 21051.504

Sheet Ratios
A1: The Home Depot, Inc. | B1: ACTUAL | H1: FORECAST
A2: (in millions) | B2: 43863 | C2: 44227 | D2: 44591 | E2: 44955 | F2: 45319 | G2: 45690 | H2: 46053 | I2: 46418 | J2: 46783 | K2: 47149 | L2: 47514
A4: LIQUIDITY RATIOS
A6: Current Ratio
A7: Current Assets | B7: =Financials!B10 -> 19810 | C7: =Financials!C10 -> 28477 | D7: =Financials!D10 -> 29055 | E7: =Financials!E10 -> 32471 | F7: =Financials!F10 -> 29775 | G7: =Financials!G10 -> 31683 | H7: =Financials!H10 -> 32194.983 | I7: =Financials!I10 -> 34832.868 | ... L7: =Financials!L10 -> 58165.403
A8: Current Liabilities | B8: =Financials!B30 -> 18375 | C8: =Financials!C30 -> 23166 | D8: =Financials!D30 -> 28693 | E8: =Financials!E30 -> 23110 | F8: =Financials!F30 -> 22015 | G8: =Financials!G30 -> 28661 | H8: =Financials!H30 -> 30672.421 | I8: =Financials!I30 -> 31439.451 | ... L8: =Financials!L30 -> 38026.607
A10: Current ratio | B10: =B7/B8 -> 1.0780952 | C10: =C7/C8 -> 1.2292584 | D10: =D7/D8 -> 1.0126163 | E10: =E7/E8 -> 1.4050627 | F10: =F7/F8 -> 1.3524869 | G10: =G7/G8 -> 1.1054394 | H10: =H7/H8 -> 1.0496394 | I10: =I7/I8 -> 1.107935 | ... L10: =L7/L8 -> 1.5295975
A13: Quick Ratio (acid test)
A14: Cash + ST Investments + Acct. Rec. | B14: =Financials!B5+Financials!B6+Financials!B7 -> 4239 | C14: =Financials!C5+Financials!C6+Financials!C7 -> 10887 | D14: =Financials!D5+Financials!D6+Financials!D7 -> 5769 | E14: =Financials!E5+Financials!E6+Financials!E7 -> 6074 | F14: =Financials!F5+Financials!F6+Financials!F7 -> 7088 | G14: =Financials!G5+Financials!G6+Financials!G7 -> 6562 | H14: =Financials!H5+Financials!H6+Financials!H7 -> 7321.6164 | I14: =Financials!I5+Financials!I6+Financials!I7 -> 8072.9676 | ... L14: =Financials!L5+Financials!L6+Financials!L7 -> 24836.351
A15: Total Current Liabilities | B15: =Financials!B30 -> 18375 | C15: =Financials!C30 -> 23166 | D15: =Financials!D30 -> 28693 | E15: =Financials!E30 -> 23110 | F15: =Financials!F30 -> 22015 | G15: =Financials!G30 -> 28661 | H15: =Financials!H30 -> 30672.421 | I15: =Financials!I30 -> 31439.451 | ... L15: =Financials!L30 -> 38026.607
A17: Quick ratio | B17: =B14/B15 -> 0.23069388 | C17: =C14/C15 -> 0.46995597 | D17: =D14/D15 -> 0.20105949 | E17: =E14/E15 -> 0.26282994 | F17: =F14/F15 -> 0.3219623 | G17: =G14/G15 -> 0.22895223 | H17: =H14/H15 -> 0.23870357 | I17: =I14/I15 -> 0.25677826 | ... L17: =L14/L15 -> 0.65313087
A21: DEBT (LEVERAGE) RATIOS
A23: Total Liabilities to Total Assets
A24: Total Liabilities | B24: =Financials!B36 -> 54352 | C24: =Financials!C36 -> 67282 | D24: =Financials!D36 -> 73572 | E24: =Financials!E36 -> 74883 | F24: =Financials!F36 -> 75486 | G24: =Financials!G36 -> 89479 | H24: =Financials!H36 -> 86215.539 | I24: =Financials!I36 -> 83418.323 | ... L24: =Financials!L36 -> 80116.493
A25: Total Assets | B25: =Financials!B17 -> 51236 | C25: =Financials!C17 -> 70581 | D25: =Financials!D17 -> 71876 | E25: =Financials!E17 -> 76445 | F25: =Financials!F17 -> 76530 | G25: =Financials!G17 -> 96119 | H25: =Financials!H17 -> 96660.46 | I25: =Financials!I17 -> 99371.2 | ... L25: =Financials!L17 -> 123553.15
A27: Total Liabilities to Total Assets | B27: =B24/B25 -> 1.0608166 | C27: =C24/C25 -> 0.95325938 | D27: =D24/D25 -> 1.0235962 | E27: =E24/E25 -> 0.97956701 | F27: =F24/F25 -> 0.98635829 | G27: =G24/G25 -> 0.93091897 | H27: =H24/H25 -> 0.89194216 | I27: =I24/I25 -> 0.83946176 | ... L27: =L24/L25 -> 0.64843749
A30: Debt to Debt + Equity
A31: Interest Bearing Debt | B31: =Financials!B21+Financials!B27+Financials!B32 -> 31483 | C31: =Financials!C21+Financials!C27+Financials!C32 -> 37238 | D31: =Financials!D21+Financials!D27+Financials!D32 -> 40086 | E31: =Financials!E21+Financials!E27+Financials!E32 -> 43193 | F31: =Financials!F21+Financials!F27+Financials!F32 -> 44111 | G31: =Financials!G21+Financials!G27+Financials!G32 -> 53383 | H31: =Financials!H21+Financials!H27+Financials!H32 -> 48801 | I31: =Financials!I21+Financials!I27+Financials!I32 -> 43956 | ... L31: =Financials!L21+Financials!L27+Financials!L32 -> 33514
A32: Int. Bearing Debt + Common Equity | B32: =Financials!B21+Financials!B27+Financials!B32+Financials!B44 -> 28367 | C32: =Financials!C21+Financials!C27+Financials!C32+Financials!C44 -> 40537 | D32: =Financials!D21+Financials!D27+Financials!D32+Financials!D44 -> 38390 | E32: =Financials!E21+Financials!E27+Financials!E32+Financials!E44 -> 44755 | F32: =Financials!F21+Financials!F27+Financials!F32+Financials!F44 -> 45155 | G32: =Financials!G21+Financials!G27+Financials!G32+Financials!G44 -> 60023 | H32: =Financials!H21+Financials!H27+Financials!H32+Financials!H44 -> 59245.921 | I32: =Financials!I21+Financials!I27+Financials!I32+Financials!I44 -> 59908.878 | ... L32: =Financials!L21+Financials!L27+Financials!L32+Financials!L44 -> 76950.654
A34: Debt to Debt + Equity | B34: =B31/B32 -> 1.1098459 | C34: =C31/C32 -> 0.91861756 | D34: =D31/D32 -> 1.0441782 | E34: =E31/E32 -> 0.96509887 | F34: =F31/F32 -> 0.97687964 | G34: =G31/G32 -> 0.88937574 | H34: =H31/H32 -> 0.82370228 | I34: =I31/I32 -> 0.73371429 | ... L34: =L31/L32 -> 0.43552586
A37: Times Interest Earned (interest coverage)
A38: Operating Income | B38: =Financials!B67 -> 15843 | C38: =Financials!C67 -> 18278 | D38: =Financials!D67 -> 23040 | E38: =Financials!E67 -> 24039 | F38: =Financials!F67 -> 21689 | G38: =Financials!G67 -> 21526 | H38: =Financials!H67 -> 24334.653 | I38: =Financials!I67 -> 26253.796 | ... L38: =Financials!L67 -> 33003.963
A39: Interest Expense | B39: =Financials!B71 -> 1201 | C39: =Financials!C71 -> 1347 | D39: =Financials!D71 -> 1347 | E39: =Financials!E71 -> 1617 | F39: =Financials!F71 -> 1943 | G39: =Financials!G71 -> 2321 | H39: =Financials!H71 -> 2191.6671 | I39: =Financials!I71 -> 2002.4305 | ... L39: =Financials!L71 -> 1534.0472
A41: Times Interest Earned | B41: =B38/B39 -> 13.191507 | C41: =C38/C39 -> 13.569414 | D41: =D38/D39 -> 17.104677 | E41: =E38/E39 -> 14.866419 | F41: =F38/F39 -> 11.162635 | G41: =G38/G39 -> 9.2744507 | H41: =H38/H39 -> 11.103262 | I41: =I38/I39 -> 13.110965 | ... L41: =L38/L39 -> 21.514307
A44: Debt to EBITDA
A45: Interest Bearing Debt | B45: =Financials!B21+Financials!B27+Financials!B32 -> 31483 | C45: =Financials!C21+Financials!C27+Financials!C32 -> 37238 | D45: =Financials!D21+Financials!D27+Financials!D32 -> 40086 | E45: =Financials!E21+Financials!E27+Financials!E32 -> 43193 | F45: =Financials!F21+Financials!F27+Financials!F32 -> 44111 | G45: =Financials!G21+Financials!G27+Financials!G32 -> 53383 | H45: =Financials!H21+Financials!H27+Financials!H32 -> 48801 | I45: =Financials!I21+Financials!I27+Financials!I32 -> 43956 | ... L45: =Financials!L21+Financials!L27+Financials!L32 -> 33514
A46: Earnings before Int. Tax. Depr. & Amort. | B46: =Financials!B75+Financials!B71+Financials!B89+Financials!B90 -> 18212 | C46: =Financials!C75+Financials!C71+Financials!C89+Financials!C90 -> 20844 | D46: =Financials!D75+Financials!D71+Financials!D89+Financials!D90 -> 25946 | E46: =Financials!E75+Financials!E71+Financials!E89+Financials!E90 -> 27069 | F46: =Financials!F75+Financials!F71+Financials!F89+Financials!F90 -> 25114 | G46: =Financials!G75+Financials!G71+Financials!G89+Financials!G90 -> 25488 | H46: =Financials!H75+Financials!H71+Financials!H89+Financials!H90 -> 27986.709 | I46: =Financials!I75+Financials!I71+Financials!I89+Financials!I90 -> 30037.924 | ... L46: =Financials!L75+Financials!L71+Financials!L89+Financials!L90 -> 36729.87
A48: Debt to EBITDA | B48: =B45/B46 -> 1.7286954 | C48: =C45/C46 -> 1.7865093 | D48: =D45/D46 -> 1.544978 | E48: =E45/E46 -> 1.5956629 | F48: =F45/F46 -> 1.7564307 | G48: =G45/G46 -> 2.0944366 | H48: =H45/H46 -> 1.7437206 | I48: =I45/I46 -> 1.4633501 | ... L48: =L45/L46 -> 0.91244536
A52: ASSET MANAGEMENT RATIOS
A54: Days Sales in A/R
A55: Average Accounts Receivable | C55: =(Financials!B7+Financials!C7)/2 -> 2549 | D55: =(Financials!C7+Financials!D7)/2 -> 3209 | E55: =(Financials!D7+Financials!E7)/2 -> 3371.5 | F55: =(Financials!E7+Financials!F7)/2 -> 3322.5 | G55: =(Financials!F7+Financials!G7)/2 -> 4115.5 | H55: =(Financials!G7+Financials!H7)/2 -> 4329.7688 | I55: =(Financials!H7+Financials!I7)/2 -> 3898.9958 | J55: =(Financials!I7+Financials!J7)/2 -> 4194.7915 | ... L55: =(Financials!K7+Financials!L7)/2 -> 4855.9019
A56: Sales | C56: =Financials!C55 -> 132110 | D56: =Financials!D55 -> 151157 | E56: =Financials!E55 -> 157403 | F56: =Financials!F55 -> 152669 | G56: =Financials!G55 -> 159514 | H56: =Financials!H55 -> 171606.53 | I56: =Financials!I55 -> 184622.12 | J56: =Financials!J55 -> 198631.67 | ... L56: =Financials!L55 -> 229944.06
A57: 365 days | C57: 365 | D57: 365 | E57: 365 | F57: 365 | G57: 365 | H57: 365 | I57: 365 | J57: 365 | K57: 365 | L57: 365
A59: Days Sales in A/R | C59: =C55/(C56/C57) -> 7.0425025 | D59: =D55/(D56/D57) -> 7.7487976 | E59: =E55/(E56/E57) -> 7.8181324 | F59: =F55/(F56/F57) -> 7.9434103 | G59: =G55/(G56/G57) -> 9.4170888 | H59: =H55/(H56/H57) -> 9.2092391 | I59: =I55/(I56/I57) -> 7.7083583 | J59: =J55/(J56/J57) -> 7.7082315 | ... L59: =L55/(L56/L57) -> 7.7079799
A62: Inventory Turnover
A63: Cost of Goods Sold | C63: =Financials!C57 -> 87257 | D63: =Financials!D57 -> 100325 | E63: =Financials!E57 -> 104625 | F63: =Financials!F57 -> 101709 | G63: =Financials!G57 -> 106206 | H63: =Financials!H57 -> 113826.61 | I63: =Financials!I57 -> 122459.85 | J63: =Financials!J57 -> 131752.39 | ... L63: =Financials!L57 -> 152521.9
A64: Average Inventory | C64: =(Financials!B8+Financials!C8)/2 -> 15579 | D64: =(Financials!C8+Financials!D8)/2 -> 19347.5 | E64: =(Financials!D8+Financials!E8)/2 -> 23477 | F64: =(Financials!E8+Financials!F8)/2 -> 22931 | G64: =(Financials!F8+Financials!G8)/2 -> 22213.5 | H64: =(Financials!G8+Financials!H8)/2 -> 23364.213 | I64: =(Financials!H8+Financials!I8)/2 -> 24160.171 | J64: =(Financials!I8+Financials!J8)/2 -> 25993.072 | ... L64: =(Financials!K8+Financials!L8)/2 -> 30089.65
A66: Inventory Turnover | C66: =C63/C64 -> 5.6009372 | D66: =D63/D64 -> 5.1854245 | E66: =E63/E64 -> 4.4564893 | F66: =F63/F64 -> 4.4354367 | G66: =G63/G64 -> 4.7811466 | H66: =H63/H64 -> 4.871836 | I66: =I63/I64 -> 5.0686668 | J66: =J63/J64 -> 5.0687502 | ... L66: =L63/L64 -> 5.0689157
A69: Age of Inventory
A70: 365 | C70: 365 | D70: 365 | E70: 365 | F70: 365 | G70: 365 | H70: 365 | I70: 365 | J70: 365 | K70: 365 | L70: 365
A71: Inventory Turnover | C71: =C66 -> 5.6009372 | D71: =D66 -> 5.1854245 | E71: =E66 -> 4.4564893 | F71: =F66 -> 4.4354367 | G71: =G66 -> 4.7811466 | H71: =H66 -> 4.871836 | I71: =I66 -> 5.0686668 | J71: =J66 -> 5.0687502 | ... L71: =L66 -> 5.0689157
A73: Age of Inventory | C73: =C70/C71 -> 65.167666 | D73: =D70/D71 -> 70.389609 | E73: =E70/E71 -> 81.903035 | F73: =F70/F71 -> 82.291783 | G73: =G70/G71 -> 76.34152 | H73: =H70/H71 -> 74.920421 | I73: =I70/I71 -> 72.011046 | J73: =J70/J71 -> 72.009861 | ... L73: =L70/L71 -> 72.007511
A76: Days Payables Outstanding
A77: Average Accounts Payable | C77: =(Financials!B22+Financials!C22)/2 -> 9696.5 | D77: =(Financials!C22+Financials!D22)/2 -> 12534 | E77: =(Financials!D22+Financials!E22)/2 -> 12452.5 | F77: =(Financials!E22+Financials!F22)/2 -> 10740 | G77: =(Financials!F22+Financials!G22)/2 -> 10987.5 | H77: =(Financials!G22+Financials!H22)/2 -> 12399.903 | I77: =(Financials!H22+Financials!I22)/2 -> 13349.561 | J77: =(Financials!I22+Financials!J22)/2 -> 14362.32 | ... L77: =(Financials!K22+Financials!L22)/2 -> 16625.86
A78: Expenses in A/P | C78: =Financials!C57+Financials!C62 -> 111704 | D78: =Financials!D57+Financials!D62 -> 125731 | E78: =Financials!E57+Financials!E62 -> 130909 | F78: =Financials!F57+Financials!F62 -> 128307 | G78: =Financials!G57+Financials!G62 -> 134954 | H78: =Financials!H57+Financials!H62 -> 143960.72 | I78: =Financials!I57+Financials!I62 -> 154879.5 | J78: =Financials!J57+Financials!J62 -> 166632.11 | ... L78: =Financials!L57+Financials!L62 -> 192900.07
A79: 365 days | C79: 365 | D79: 365 | E79: 365 | F79: 365 | G79: 365 | H79: 365 | I79: 365 | J79: 365 | K79: 365 | L79: 365
A81: Days Payables Outstanding | C81: =C77/(C78/C79) -> 31.683937 | D81: =D77/(D78/D79) -> 36.386492 | E81: =E77/(E78/E79) -> 34.720015 | F81: =F77/(F78/F79) -> 30.552503 | G81: =G77/(G78/G79) -> 29.71707 | H81: =H77/(H78/H79) -> 31.438885 | I81: =I77/(I78/I79) -> 31.460521 | J81: =J77/(J78/J79) -> 31.460004 | ... L81: =L77/(L78/L79) -> 31.458977
A84: Total Asset Turnover
A85: Sales | C85: =Financials!C55 -> 132110 | D85: =Financials!D55 -> 151157 | E85: =Financials!E55 -> 157403 | F85: =Financials!F55 -> 152669 | G85: =Financials!G55 -> 159514 | H85: =Financials!H55 -> 171606.53 | I85: =Financials!I55 -> 184622.12 | J85: =Financials!J55 -> 198631.67 | ... L85: =Financials!L55 -> 229944.06
A86: Average Total Assets | C86: =(Financials!B17+Financials!C17)/2 -> 60908.5 | D86: =(Financials!C17+Financials!D17)/2 -> 71228.5 | E86: =(Financials!D17+Financials!E17)/2 -> 74160.5 | F86: =(Financials!E17+Financials!F17)/2 -> 76487.5 | G86: =(Financials!F17+Financials!G17)/2 -> 86324.5 | H86: =(Financials!G17+Financials!H17)/2 -> 96389.73 | I86: =(Financials!H17+Financials!I17)/2 -> 98015.83 | J86: =(Financials!I17+Financials!J17)/2 -> 102272.87 | ... L86: =(Financials!K17+Financials!L17)/2 -> 118772.65
A88: Total Asset Turnover | C88: =C85/C86 -> 2.1689912 | D88: =D85/D86 -> 2.1221421 | E88: =E85/E86 -> 2.1224641 | F88: =F85/F86 -> 1.9959993 | G88: =G85/G86 -> 1.8478416 | H88: =H85/H86 -> 1.7803404 | I88: =I85/I86 -> 1.883595 | J88: =J85/J86 -> 1.9421736 | ... L88: =L85/L86 -> 1.9360018
A92: PROFITABILITY RATIOS
A94: Gross Profit
A95: Gross Profit | B95: =Financials!B59 -> 37572 | C95: =Financials!C59 -> 44853 | D95: =Financials!D59 -> 50832 | E95: =Financials!E59 -> 52778 | F95: =Financials!F59 -> 50960 | G95: =Financials!G59 -> 53308 | H95: =Financials!H59 -> 57779.92 | I95: =Financials!I59 -> 62162.269 | ... L95: =Financials!L59 -> 77422.166
A96: Sales | B96: =Financials!B55 -> 110225 | C96: =Financials!C55 -> 132110 | D96: =Financials!D55 -> 151157 | E96: =Financials!E55 -> 157403 | F96: =Financials!F55 -> 152669 | G96: =Financials!G55 -> 159514 | H96: =Financials!H55 -> 171606.53 | I96: =Financials!I55 -> 184622.12 | ... L96: =Financials!L55 -> 229944.06
A98: Gross Profit | B98: =B95/B96 -> 0.34086641 | C98: =C95/C96 -> 0.33951253 | D98: =D95/D96 -> 0.33628611 | E98: =E95/E96 -> 0.33530492 | F98: =F95/F96 -> 0.33379402 | G98: =G95/G96 -> 0.3341901 | H98: =H95/H96 -> 0.3367 | I98: =I95/I96 -> 0.3367 | ... L98: =L95/L96 -> 0.3367
A101: Operating Profit
A102: Operating Income | B102: =Financials!B67 -> 15843 | C102: =Financials!C67 -> 18278 | D102: =Financials!D67 -> 23040 | E102: =Financials!E67 -> 24039 | F102: =Financials!F67 -> 21689 | G102: =Financials!G67 -> 21526 | H102: =Financials!H67 -> 24334.653 | I102: =Financials!I67 -> 26253.796 | ... L102: =Financials!L67 -> 33003.963
A103: Sales | B103: =Financials!B55 -> 110225 | C103: =Financials!C55 -> 132110 | D103: =Financials!D55 -> 151157 | E103: =Financials!E55 -> 157403 | F103: =Financials!F55 -> 152669 | G103: =Financials!G55 -> 159514 | H103: =Financials!H55 -> 171606.53 | I103: =Financials!I55 -> 184622.12 | ... L103: =Financials!L55 -> 229944.06
A105: Operating Profit | B105: =B102/B103 -> 0.14373327 | C105: =C102/C103 -> 0.1383544 | D105: =D102/D103 -> 0.1524243 | E105: =E102/E103 -> 0.15272263 | F105: =F102/F103 -> 0.14206551 | G105: =G102/G103 -> 0.1349474 | H105: =H102/H103 -> 0.14180493 | I105: =I102/I103 -> 0.14220287 | ... L105: =L102/L103 -> 0.1435304
A108: Return on Sales
A109: Net Income | B109: =Financials!B79 -> 11242 | C109: =Financials!C79 -> 12866 | D109: =Financials!D79 -> 16433 | E109: =Financials!E79 -> 17105 | F109: =Financials!F79 -> 15143 | G109: =Financials!G79 -> 14806 | H109: =Financials!H79 -> 16835.312 | I109: =Financials!I79 -> 18386.951 | ... L109: =Financials!L79 -> 23353.782
A110: Sales | B110: =Financials!B55 -> 110225 | C110: =Financials!C55 -> 132110 | D110: =Financials!D55 -> 151157 | E110: =Financials!E55 -> 157403 | F110: =Financials!F55 -> 152669 | G110: =Financials!G55 -> 159514 | H110: =Financials!H55 -> 171606.53 | I110: =Financials!I55 -> 184622.12 | ... L110: =Financials!L55 -> 229944.06
A112: Return on Sales | B112: =B109/B110 -> 0.10199138 | C112: =C109/C110 -> 0.09738854 | D112: =D109/D110 -> 0.10871478 | E112: =E109/E110 -> 0.1086701 | F112: =F109/F110 -> 0.09918844 | G112: =G109/G110 -> 0.092819439 | H112: =H109/H110 -> 0.098104145 | I112: =I109/I110 -> 0.099592347 | ... L112: =L109/L110 -> 0.10156288
A115: Effective Tax Rate
A116: Tax Expense | B116: =Financials!B77 -> 3473 | C116: =Financials!C77 -> 4112 | D116: =Financials!D77 -> 5304 | E116: =Financials!E77 -> 5372 | F116: =Financials!F77 -> 4781 | G116: =Financials!G77 -> 4600 | H116: =Financials!H77 -> 5307.6737 | I116: =Financials!I77 -> 5796.8592 | ... L116: =Financials!L77 -> 7362.7536
A117: Pre-tax Income | B117: =Financials!B75 -> 14715 | C117: =Financials!C75 -> 16978 | D117: =Financials!D75 -> 21737 | E117: =Financials!E75 -> 22477 | F117: =Financials!F75 -> 19924 | G117: =Financials!G75 -> 19406 | H117: =Financials!H75 -> 22142.986 | I117: =Financials!I75 -> 24183.81 | ... L117: =Financials!L75 -> 30716.536
A119: Effective Tax Rate | B119: =B116/B117 -> 0.23601767 | C119: =C116/C117 -> 0.24219578 | D119: =D116/D117 -> 0.24400791 | E119: =E116/E117 -> 0.23899987 | F119: =F116/F117 -> 0.23996186 | G119: =G116/G117 -> 0.23704009 | H119: =H116/H117 -> 0.2397 | I119: =I116/I117 -> 0.2397 | ... L119: =L116/L117 -> 0.2397
A122: Return on Assets (ROA)
A123: Net Income + (Interest Expense * (1-ETR)) | C123: =Financials!C79+(Financials!C71 * (1-C119)) -> 13886.762 | D123: =Financials!D79+(Financials!D71 * (1-D119)) -> 17451.321 | E123: =Financials!E79+(Financials!E71 * (1-E119)) -> 18335.537 | F123: =Financials!F79+(Financials!F71 * (1-F119)) -> 16619.754 | G123: =Financials!G79+(Financials!G71 * (1-G119)) -> 16576.83 | H123: =Financials!H79+(Financials!H71 * (1-H119)) -> 18501.637 | I123: =Financials!I79+(Financials!I71 * (1-I119)) -> 19909.398 | J123: =Financials!J79+(Financials!J71 * (1-J119)) -> 21461.275 | ... L123: =Financials!L79+(Financials!L71 * (1-L119)) -> 24520.118
A124: Average Total Assets | C124: =(Financials!B17+Financials!C17)/2 -> 60908.5 | D124: =(Financials!C17+Financials!D17)/2 -> 71228.5 | E124: =(Financials!D17+Financials!E17)/2 -> 74160.5 | F124: =(Financials!E17+Financials!F17)/2 -> 76487.5 | G124: =(Financials!F17+Financials!G17)/2 -> 86324.5 | H124: =(Financials!G17+Financials!H17)/2 -> 96389.73 | I124: =(Financials!H17+Financials!I17)/2 -> 98015.83 | J124: =(Financials!I17+Financials!J17)/2 -> 102272.87 | ... L124: =(Financials!K17+Financials!L17)/2 -> 118772.65
A126: Return on Assets | C126: =C123/C124 -> 0.22799383 | D126: =D123/D124 -> 0.24500476 | E126: =E123/E124 -> 0.24724128 | F126: =F123/F124 -> 0.21728719 | G126: =G123/G124 -> 0.19202926 | H126: =H123/H124 -> 0.19194614 | I126: =I123/I124 -> 0.20312432 | J126: =J123/J124 -> 0.20984328 | ... L126: =L123/L124 -> 0.20644583
A129: Return on Invested Capital (ROIC)
A130: NOPAT (Operating Profit*(1-ETR)) | C130: =Financials!C67*(1-(C119)) -> 13851.145 | D130: =Financials!D67*(1-(D119)) -> 17418.058 | E130: =Financials!E67*(1-(E119)) -> 18293.682 | F130: =Financials!F67*(1-(F119)) -> 16484.467 | G130: =Financials!G67*(1-(G119)) -> 16423.475 | H130: =Financials!H67*(1-(H119)) -> 18501.637 | I130: =Financials!I67*(1-(I119)) -> 19960.761 | J130: =Financials!J67*(1-(J119)) -> 21537.462 | ... L130: =Financials!L67*(1-(L119)) -> 25092.913
A131: Average Total Assets | C131: =(Financials!B17+Financials!C17)/2 -> 60908.5 | D131: =(Financials!C17+Financials!D17)/2 -> 71228.5 | E131: =(Financials!D17+Financials!E17)/2 -> 74160.5 | F131: =(Financials!E17+Financials!F17)/2 -> 76487.5 | G131: =(Financials!F17+Financials!G17)/2 -> 86324.5 | H131: =(Financials!G17+Financials!H17)/2 -> 96389.73 | I131: =(Financials!H17+Financials!I17)/2 -> 98015.83 | J131: =(Financials!I17+Financials!J17)/2 -> 102272.87 | ... L131: =(Financials!K17+Financials!L17)/2 -> 118772.65
A133: Return on Invested Capital | C133: =C130/C131 -> 0.22740907 | D133: =D130/D131 -> 0.24453776 | E133: =E130/E131 -> 0.2466769 | F133: =F130/F131 -> 0.21551845 | G133: =G130/G131 -> 0.19025277 | H133: =H130/H131 -> 0.19194614 | I133: =I130/I131 -> 0.20364834 | J133: =J130/J131 -> 0.21058822 | ... L133: =L130/L131 -> 0.21126844
A136: Return on Common Equity (ROCE)
A137: Net Income | C137: =Financials!C79 -> 12866 | D137: =Financials!D79 -> 16433 | E137: =Financials!E79 -> 17105 | F137: =Financials!F79 -> 15143 | G137: =Financials!G79 -> 14806 | H137: =Financials!H79 -> 16835.312 | I137: =Financials!I79 -> 18386.951 | J137: =Financials!J79 -> 20090.962 | ... L137: =Financials!L79 -> 23353.782
A138: Average Common Equity | C138: =(Financials!B44+Financials!C44)/2 -> 91.5 | D138: =(Financials!C44+Financials!D44)/2 -> 801.5 | E138: =(Financials!D44+Financials!E44)/2 -> -67 | F138: =(Financials!E44+Financials!F44)/2 -> 1303 | G138: =(Financials!F44+Financials!G44)/2 -> 3842 | H138: =(Financials!G44+Financials!H44)/2 -> 8542.4604 | I138: =(Financials!H44+Financials!I44)/2 -> 13198.899 | J138: =(Financials!I44+Financials!J44)/2 -> 19635.444 | ... L138: =(Financials!K44+Financials!L44)/2 -> 37961.973
A140: Return on Common Equity | C140: =C137/C138 -> 140.61202 | D140: =D137/D138 -> 20.502807 | E140: =E137/E138 -> -255.29851 | F140: =F137/F138 -> 11.621642 | G140: =G137/G138 -> 3.853722 | H140: =H137/H138 -> 1.9707802 | I140: =I137/I138 -> 1.393067 | J140: =J137/J138 -> 1.0231988 | ... L140: =L137/L138 -> 0.61518883

Sheet Year-over-Year
A1: The Home Depot, Inc. | B1: ACTUAL | H1: FORECAST
A2: Year-over-Year Balance Sheet | B2: 43863 | C2: 44227 | D2: 44591 | E2: 44955 | F2: 45319 | G2: 45690 | H2: 46053 | I2: 46418 | J2: 46783 | K2: 47149 | L2: 47514
A4: ASSETS
A5: Cash and cash equivalents | C5: =(Financials!C5-Financials!B5)/Financials!B5 -> 2.7013596 | D5: =(Financials!D5-Financials!C5)/Financials!C5 -> -0.70322989 | E5: =(Financials!E5-Financials!D5)/Financials!D5 -> 0.17669654 | F5: =(Financials!F5-Financials!E5)/Financials!E5 -> 0.36380123 | G5: =(Financials!G5-Financials!F5)/Financials!F5 -> -0.5587766 | H5: =(Financials!H5-Financials!G5)/Financials!G5 -> 0.56720916 | I5: =(Financials!I5-Financials!H5)/Financials!H5 -> 0 | J5: =(Financials!J5-Financials!I5)/Financials!I5 -> 0 | ... L5: =(Financials!L5-Financials!K5)/Financials!K5 -> 0
A6: Short-term investments
A7: Receivables, net | C7: =(Financials!C7-Financials!B7)/Financials!B7 -> 0.42070275 | D7: =(Financials!D7-Financials!C7)/Financials!C7 -> 0.14505348 | E7: =(Financials!E7-Financials!D7)/Financials!D7 -> -0.031815528 | F7: =(Financials!F7-Financials!E7)/Financials!E7 -> 0.0033162496 | G7: =(Financials!G7-Financials!F7)/Financials!F7 -> 0.47325721 | H7: =(Financials!H7-Financials!G7)/Financials!G7 -> -0.23382877 | I7: =(Financials!I7-Financials!H7)/Financials!H7 -> 0.075845539 | J7: =(Financials!J7-Financials!I7)/Financials!I7 -> 0.075882286 | ... L7: =(Financials!L7-Financials!K7)/Financials!K7 -> 0.075955201
A8: Merchandise inventories | C8: =(Financials!C8-Financials!B8)/Financials!B8 -> 0.14424334 | D8: =(Financials!D8-Financials!C8)/Financials!C8 -> 0.32723883 | E8: =(Financials!E8-Financials!D8)/Financials!D8 -> 0.12769621 | F8: =(Financials!F8-Financials!E8)/Financials!E8 -> -0.15711645 | G8: =(Financials!G8-Financials!F8)/Financials!F8 -> 0.11799199 | H8: =(Financials!H8-Financials!G8)/Financials!G8 -> -0.007401558 | I8: =(Financials!I8-Financials!H8)/Financials!H8 -> 0.075845539 | J8: =(Financials!J8-Financials!I8)/Financials!I8 -> 0.075882286 | ... L8: =(Financials!L8-Financials!K8)/Financials!K8 -> 0.075955201
A9: Other current assets | C9: =(Financials!C9-Financials!B9)/Financials!B9 -> -0.074038462 | D9: =(Financials!D9-Financials!C9)/Financials!C9 -> 0.26479751 | E9: =(Financials!E9-Financials!D9)/Financials!D9 -> 0.24055829 | F9: =(Financials!F9-Financials!E9)/Financials!E9 -> 0.13236267 | G9: =(Financials!G9-Financials!F9)/Financials!F9 -> -0.023962595 | H9: =(Financials!H9-Financials!G9)/Financials!G9 -> -0.044346851 | I9: =(Financials!I9-Financials!H9)/Financials!H9 -> 0.075845539 | J9: =(Financials!J9-Financials!I9)/Financials!I9 -> 0.075882286 | ... L9: =(Financials!L9-Financials!K9)/Financials!K9 -> 0.075955201
A10: Total current assets | C10: =(Financials!C10-Financials!B10)/Financials!B10 -> 0.43750631 | D10: =(Financials!D10-Financials!C10)/Financials!C10 -> 0.020297082 | E10: =(Financials!E10-Financials!D10)/Financials!D10 -> 0.11757013 | F10: =(Financials!F10-Financials!E10)/Financials!E10 -> -0.083027933 | G10: =(Financials!G10-Financials!F10)/Financials!F10 -> 0.064080605 | H10: =(Financials!H10-Financials!G10)/Financials!G10 -> 0.016159555 | I10: =(Financials!I10-Financials!H10)/Financials!H10 -> 0.081934664 | J10: =(Financials!J10-Financials!I10)/Financials!I10 -> 0.16188199 | ... L10: =(Financials!L10-Financials!K10)/Financials!K10 -> 0.18663625
A12: Net property and equipment | C12: =(Financials!C12-Financials!B12)/Financials!B12 -> 0.084980237 | D12: =(Financials!D12-Financials!C12)/Financials!C12 -> 0.019995952 | E12: =(Financials!E12-Financials!D12)/Financials!D12 -> 0.017143537 | F12: =(Financials!F12-Financials!E12)/Financials!E12 -> 0.020404978 | G12: =(Financials!G12-Financials!F12)/Financials!F12 -> 0.020952818 | H12: =(Financials!H12-Financials!G12)/Financials!G12 -> 0.018509758 | I12: =(Financials!I12-Financials!H12)/Financials!H12 -> 0.020858945 | J12: =(Financials!J12-Financials!I12)/Financials!I12 -> 0.023285438 | ... L12: =(Financials!L12-Financials!K12)/Financials!K12 -> 0.028329406
A13: Operating lease right-of-use assets | D13: =(Financials!D13-Financials!C13)/Financials!C13 -> 0.0010063737 | E13: =(Financials!E13-Financials!D13)/Financials!D13 -> 0.16303619 | F13: =(Financials!F13-Financials!E13)/Financials!E13 -> 0.13585939 | G13: =(Financials!G13-Financials!F13)/Financials!F13 -> 0.089802131 | H13: =(Financials!H13-Financials!G13)/Financials!G13 -> 0 | I13: =(Financials!I13-Financials!H13)/Financials!H13 -> 0 | J13: =(Financials!J13-Financials!I13)/Financials!I13 -> 0 | K13: =(Financials!K13-Financials!J13)/Financials!J13 -> 0 | L13: =(Financials!L13-Financials!K13)/Financials!K13 -> 0
A14: Goodwill | C14: =(Financials!C14-Financials!B14)/Financials!B14 -> 2.1614907 | D14: =(Financials!D14-Financials!C14)/Financials!C14 -> 0.045326972 | E14: =(Financials!E14-Financials!D14)/Financials!D14 -> -0.00067123104 | F14: =(Financials!F14-Financials!E14)/Financials!E14 -> 0.13581408 | G14: =(Financials!G14-Financials!F14)/Financials!F14 -> 1.3033708 | H14: =(Financials!H14-Financials!G14)/Financials!G14 -> 0 | I14: =(Financials!I14-Financials!H14)/Financials!H14 -> 0 | J14: =(Financials!J14-Financials!I14)/Financials!I14 -> 0 | ... L14: =(Financials!L14-Financials!K14)/Financials!K14 -> 0
A15: Intangible assets | E15: =(Financials!E15-Financials!D15)/Financials!D15 -> -0.051384528 | F15: =(Financials!F15-Financials!E15)/Financials!E15 -> 0.085164008 | G15: =(Financials!G15-Financials!F15)/Financials!F15 -> 1.4911259 | H15: =(Financials!H15-Financials!G15)/Financials!G15 -> -0.061560726 | I15: =(Financials!I15-Financials!H15)/Financials!H15 -> -0.065599051 | J15: =(Financials!J15-Financials!I15)/Financials!I15 -> -0.069188777 | K15: =(Financials!K15-Financials!J15)/Financials!J15 -> -0.072013093 | L15: =(Financials!L15-Financials!K15)/Financials!K15 -> -0.071428571
A16: Other assets | C16: =(Financials!C16-Financials!B16)/Financials!B16 -> -0.133829 | D16: =(Financials!D16-Financials!C16)/Financials!C16 -> 0.0042918455 | E16: =(Financials!E16-Financials!D16)/Financials!D16 -> -0.095441595 | F16: =(Financials!F16-Financials!E16)/Financials!E16 -> 0.033070866 | G16: =(Financials!G16-Financials!F16)/Financials!F16 -> 0.042682927 | H16: =(Financials!H16-Financials!G16)/Financials!G16 -> 0.12899035 | I16: =(Financials!I16-Financials!H16)/Financials!H16 -> 0.075845539 | J16: =(Financials!J16-Financials!I16)/Financials!I16 -> 0.075882286 | ... L16: =(Financials!L16-Financials!K16)/Financials!K16 -> 0.075955201
A17: Total assets | C17: =(Financials!C17-Financials!B17)/Financials!B17 -> 0.37756655 | D17: =(Financials!D17-Financials!C17)/Financials!C17 -> 0.018347714 | E17: =(Financials!E17-Financials!D17)/Financials!D17 -> 0.063567811 | F17: =(Financials!F17-Financials!E17)/Financials!E17 -> 0.0011119105 | G17: =(Financials!G17-Financials!F17)/Financials!F17 -> 0.25596498 | H17: =(Financials!H17-Financials!G17)/Financials!G17 -> 0.0056332269 | I17: =(Financials!I17-Financials!H17)/Financials!H17 -> 0.028043942 | J17: =(Financials!J17-Financials!I17)/Financials!I17 -> 0.058400653 | ... L17: =(Financials!L17-Financials!K17)/Financials!K17 -> 0.083874113
A19: LIABILITIES
A21: Short-term debt
A22: Accounts payable | C22: =(Financials!C22-Financials!B22)/Financials!B22 -> 0.49043277 | D22: =(Financials!D22-Financials!C22)/Financials!C22 -> 0.15991728 | E22: =(Financials!E22-Financials!D22)/Financials!D22 -> -0.14997772 | F22: =(Financials!F22-Financials!E22)/Financials!E22 -> -0.12286988 | G22: =(Financials!G22-Financials!F22)/Financials!F22 -> 0.18939922 | H22: =(Financials!H22-Financials!G22)/Financials!G22 -> 0.077383629 | I22: =(Financials!I22-Financials!H22)/Financials!H22 -> 0.075845539 | J22: =(Financials!J22-Financials!I22)/Financials!I22 -> 0.075882286 | ... L22: =(Financials!L22-Financials!K22)/Financials!K22 -> 0.075955201
A23: Accrued salaries and related expenses | C23: =(Financials!C23-Financials!B23)/Financials!B23 -> 0.64859438 | D23: =(Financials!D23-Financials!C23)/Financials!C23 -> -0.01502233 | E23: =(Financials!E23-Financials!D23)/Financials!D23 -> -0.1793075 | F23: =(Financials!F23-Financials!E23)/Financials!E23 -> 0.052737318 | G23: =(Financials!G23-Financials!F23)/Financials!F23 -> 0.10448473 | H23: =(Financials!H23-Financials!G23)/Financials!G23 -> 0.11934902 | I23: =(Financials!I23-Financials!H23)/Financials!H23 -> 0.075845539 | J23: =(Financials!J23-Financials!I23)/Financials!I23 -> 0.075882286 | ... L23: =(Financials!L23-Financials!K23)/Financials!K23 -> 0.075955201
A24: Sales taxes payable | C24: =(Financials!C24-Financials!B24)/Financials!B24 -> 0.27933884 | D24: =(Financials!D24-Financials!C24)/Financials!C24 -> 0.095607235 | E24: =(Financials!E24-Financials!D24)/Financials!D24 -> -0.37735849 | F24: =(Financials!F24-Financials!E24)/Financials!E24 -> -0.14962121 | G24: =(Financials!G24-Financials!F24)/Financials!F24 -> 0.3986637 | H24: =(Financials!H24-Financials!G24)/Financials!G24 -> 0.17501289 | I24: =(Financials!I24-Financials!H24)/Financials!H24 -> 0.075845539 | J24: =(Financials!J24-Financials!I24)/Financials!I24 -> 0.075882286 | ... L24: =(Financials!L24-Financials!K24)/Financials!K24 -> 0.075955201
A25: Deferred revenue | C25: =(Financials!C25-Financials!B25)/Financials!B25 -> 0.33412098 | D25: =(Financials!D25-Financials!C25)/Financials!C25 -> 0.27382217 | E25: =(Financials!E25-Financials!D25)/Financials!D25 -> -0.14794216 | F25: =(Financials!F25-Financials!E25)/Financials!E25 -> -0.098563969 | G25: =(Financials!G25-Financials!F25)/Financials!F25 -> -0.055032585 | H25: =(Financials!H25-Financials!G25)/Financials!G25 -> 0.30184267 | I25: =(Financials!I25-Financials!H25)/Financials!H25 -> 0.075845539 | J25: =(Financials!J25-Financials!I25)/Financials!I25 -> 0.075882286 | ... L25: =(Financials!L25-Financials!K25)/Financials!K25 -> 0.075955201
A26: Income taxes payable | C26: =(Financials!C26-Financials!B26)/Financials!B26 -> 2.5090909 | D26: =(Financials!D26-Financials!C26)/Financials!C26 -> -0.18134715 | E26: =(Financials!E26-Financials!D26)/Financials!D26 -> -0.6835443 | F26: =(Financials!F26-Financials!E26)/Financials!E26 -> -0.44 | G26: =(Financials!G26-Financials!F26)/Financials!F26 -> 28.714286 | H26: =(Financials!H26-Financials!G26)/Financials!G26 -> -0.65168391 | I26: =(Financials!I26-Financials!H26)/Financials!H26 -> 0.092165698 | J26: =(Financials!J26-Financials!I26)/Financials!I26 -> 0.092675048 | ... L26: =(Financials!L26-Financials!K26)/Financials!K26 -> 0.074369842
A27: Current installments of long-term debt | C27: =(Financials!C27-Financials!B27)/Financials!B27 -> -0.23001631 | D27: =(Financials!D27-Financials!C27)/Financials!C27 -> 0.72810734 | E27: =(Financials!E27-Financials!D27)/Financials!D27 -> -0.49693502 | F27: =(Financials!F27-Financials!E27)/Financials!E27 -> 0.11129163 | G27: =(Financials!G27-Financials!F27)/Financials!F27 -> 2.3494152 | H27: =(Financials!H27-Financials!G27)/Financials!G27 -> 0.057398516 | I27: =(Financials!I27-Financials!H27)/Financials!H27 -> -0.22208462 | J27: =(Financials!J27-Financials!I27)/Financials!I27 -> -0.27646591 | ... L27: =(Financials!L27-Financials!K27)/Financials!K27 -> 0
A28: Current operating lease liabilities | E28: =(Financials!E28-Financials!D28)/Financials!D28 -> 0.13855422 | F28: =(Financials!F28-Financials!E28)/Financials!E28 -> 0.11111111 | G28: =(Financials!G28-Financials!F28)/Financials!F28 -> 0.21333333 | H28: =(Financials!H28-Financials!G28)/Financials!G28 -> 0 | I28: =(Financials!I28-Financials!H28)/Financials!H28 -> 0 | J28: =(Financials!J28-Financials!I28)/Financials!I28 -> 0 | K28: =(Financials!K28-Financials!J28)/Financials!J28 -> 0 | L28: =(Financials!L28-Financials!K28)/Financials!K28 -> 0
A29: Other accrued expenses | C29: =(Financials!C29-Financials!B29)/Financials!B29 -> 0.14419126 | D29: =(Financials!D29-Financials!C29)/Financials!C29 -> 0.27032321 | E29: =(Financials!E29-Financials!D29)/Financials!D29 -> -0.0084811103 | F29: =(Financials!F29-Financials!E29)/Financials!E29 -> 0.095127009 | G29: =(Financials!G29-Financials!F29)/Financials!F29 -> -0.013964497 | H29: =(Financials!H29-Financials!G29)/Financials!G29 -> 0.046280831 | I29: =(Financials!I29-Financials!H29)/Financials!H29 -> 0.075845539 | J29: =(Financials!J29-Financials!I29)/Financials!I29 -> 0.075882286 | ... L29: =(Financials!L29-Financials!K29)/Financials!K29 -> 0.075955201
A30: Total current liabilities | C30: =(Financials!C30-Financials!B30)/Financials!B30 -> 0.26073469 | D30: =(Financials!D30-Financials!C30)/Financials!C30 -> 0.23858241 | E30: =(Financials!E30-Financials!D30)/Financials!D30 -> -0.19457707 | F30: =(Financials!F30-Financials!E30)/Financials!E30 -> -0.047382086 | G30: =(Financials!G30-Financials!F30)/Financials!F30 -> 0.30188508 | H30: =(Financials!H30-Financials!G30)/Financials!G30 -> 0.070179725 | I30: =(Financials!I30-Financials!H30)/Financials!H30 -> 0.02500715 | J30: =(Financials!J30-Financials!I30)/Financials!I30 -> 0.029973783 | ... L30: =(Financials!L30-Financials!K30)/Financials!K30 -> 0.06417128
A32: Long-term debt | C32: =(Financials!C32-Financials!B32)/Financials!B32 -> 0.24945937 | D32: =(Financials!D32-Financials!C32)/Financials!C32 -> 0.02183016 | E32: =(Financials!E32-Financials!D32)/Financials!D32 -> 0.14637745 | F32: =(Financials!F32-Financials!E32)/Financials!E32 -> 0.018612078 | G32: =(Financials!G32-Financials!F32)/Financials!F32 -> 0.13433779 | H32: =(Financials!H32-Financials!G32)/Financials!G32 -> -0.099927813 | I32: =(Financials!I32-Financials!H32)/Financials!H32 -> -0.08636572 | J32: =(Financials!J32-Financials!I32)/Financials!I32 -> -0.068395576 | ... L32: =(Financials!L32-Financials!K32)/Financials!K32 -> -0.11886258
A33: Long-term operating lease liabilities | D33: =(Financials!D33-Financials!C33)/Financials!C33 -> -0.00056011949 | E33: =(Financials!E33-Financials!D33)/Financials!D33 -> 0.16308612 | F33: =(Financials!F33-Financials!E33)/Financials!E33 -> 0.13748795 | G33: =(Financials!G33-Financials!F33)/Financials!F33 -> 0.077802881 | H33: =(Financials!H33-Financials!G33)/Financials!G33 -> 0 | I33: =(Financials!I33-Financials!H33)/Financials!H33 -> 0 | J33: =(Financials!J33-Financials!I33)/Financials!I33 -> 0 | K33: =(Financials!K33-Financials!J33)/Financials!J33 -> 0 | L33: =(Financials!L33-Financials!K33)/Financials!K33 -> 0
A34: Deferred income taxes | C34: =(Financials!C34-Financials!B34)/Financials!B34 -> 0.601983 | D34: =(Financials!D34-Financials!C34)/Financials!C34 -> -0.19628647 | E34: =(Financials!E34-Financials!D34)/Financials!D34 -> 0.1210121 | F34: =(Financials!F34-Financials!E34)/Financials!E34 -> -0.15309127 | G34: =(Financials!G34-Financials!F34)/Financials!F34 -> 1.2734647 | H34: =(Financials!H34-Financials!G34)/Financials!G34 -> -0.19679119 | I34: =(Financials!I34-Financials!H34)/Financials!H34 -> 0.00025925074 | J34: =(Financials!J34-Financials!I34)/Financials!I34 -> 0.0018413322 | ... L34: =(Financials!L34-Financials!K34)/Financials!K34 -> 0.0061273639
A35: Other long-term liabilities | C35: =(Financials!C35-Financials!B35)/Financials!B35 -> 0.1771987 | D35: =(Financials!D35-Financials!C35)/Financials!C35 -> 0.11400111 | E35: =(Financials!E35-Financials!D35)/Financials!D35 -> 0.27471436 | F35: =(Financials!F35-Financials!E35)/Financials!E35 -> 0.08456742 | G35: =(Financials!G35-Financials!F35)/Financials!F35 -> -0.016169601 | H35: =(Financials!H35-Financials!G35)/Financials!G35 -> -0.015988835 | I35: =(Financials!I35-Financials!H35)/Financials!H35 -> 0.075845539 | J35: =(Financials!J35-Financials!I35)/Financials!I35 -> 0.075882286 | ... L35: =(Financials!L35-Financials!K35)/Financials!K35 -> 0.075955201
A36: Total liabilities | C36: =(Financials!C36-Financials!B36)/Financials!B36 -> 0.23789373 | D36: =(Financials!D36-Financials!C36)/Financials!C36 -> 0.093487114 | E36: =(Financials!E36-Financials!D36)/Financials!D36 -> 0.017819279 | F36: =(Financials!F36-Financials!E36)/Financials!E36 -> 0.008052562 | G36: =(Financials!G36-Financials!F36)/Financials!F36 -> 0.18537212 | H36: =(Financials!H36-Financials!G36)/Financials!G36 -> -0.036471805 | I36: =(Financials!I36-Financials!H36)/Financials!H36 -> -0.032444463 | J36: =(Financials!J36-Financials!I36)/Financials!I36 -> -0.018722365 | ... L36: =(Financials!L36-Financials!K36)/Financials!K36 -> -0.017034204
A38: SHAREHOLDERS' EQUITY
A39: Common stock | C39: =(Financials!C39-Financials!B39)/Financials!B39 -> 0 | D39: =(Financials!D39-Financials!C39)/Financials!C39 -> 0.011235955 | E39: =(Financials!E39-Financials!D39)/Financials!D39 -> 0 | F39: =(Financials!F39-Financials!E39)/Financials!E39 -> 0 | G39: =(Financials!G39-Financials!F39)/Financials!F39 -> 0 | H39: =(Financials!H39-Financials!G39)/Financials!G39 -> 0 | I39: =(Financials!I39-Financials!H39)/Financials!H39 -> 0 | J39: =(Financials!J39-Financials!I39)/Financials!I39 -> 0 | ... L39: =(Financials!L39-Financials!K39)/Financials!K39 -> 0
A40: Paid-in capital | C40: =(Financials!C40-Financials!B40)/Financials!B40 -> 0.048995546 | D40: =(Financials!D40-Financials!C40)/Financials!C40 -> 0.051299827 | E40: =(Financials!E40-Financials!D40)/Financials!D40 -> 0.037916255 | F40: =(Financials!F40-Financials!E40)/Financials!E40 -> 0.044075604 | G40: =(Financials!G40-Financials!F40)/Financials!F40 -> 0.073781091 | H40: =(Financials!H40-Financials!G40)/Financials!G40 -> 0.049173944 | I40: =(Financials!I40-Financials!H40)/Financials!H40 -> 0.050565521 | J40: =(Financials!J40-Financials!I40)/Financials!I40 -> 0.051933641 | ... L40: =(Financials!L40-Financials!K40)/Financials!K40 -> 0.054610392
A41: Retained earnings | C41: =(Financials!C41-Financials!B41)/Financials!B41 -> 0.12381836 | D41: =(Financials!D41-Financials!C41)/Financials!C41 -> 0.16248667 | E41: =(Financials!E41-Financials!D41)/Financials!D41 -> 0.13785144 | F41: =(Financials!F41-Financials!E41)/Financials!E41 -> 0.087910945 | G41: =(Financials!G41-Financials!F41)/Financials!F41 -> 0.070251984 | H41: =(Financials!H41-Financials!G41)/Financials!G41 -> 0.10399218 | I41: =(Financials!I41-Financials!H41)/Financials!H41 -> 0.1108722 | J41: =(Financials!J41-Financials!I41)/Financials!I41 -> 0.1161814 | ... L41: =(Financials!L41-Financials!K41)/Financials!K41 -> 0.11825633
A42: Accumulated other comp. income (loss) | C42: =(Financials!C42-Financials!B42)/Financials!B42 -> -0.092016238 | D42: =(Financials!D42-Financials!C42)/Financials!C42 -> 0.049180328 | E42: =(Financials!E42-Financials!D42)/Financials!D42 -> 0.019886364 | F42: =(Financials!F42-Financials!E42)/Financials!E42 -> -0.3356546 | G42: =(Financials!G42-Financials!F42)/Financials!F42 -> 1.3668763 | H42: =(Financials!H42-Financials!G42)/Financials!G42 -> 0 | I42: =(Financials!I42-Financials!H42)/Financials!H42 -> 0 | J42: =(Financials!J42-Financials!I42)/Financials!I42 -> 0 | ... L42: =(Financials!L42-Financials!K42)/Financials!K42 -> 0
A43: Treasury stock | C43: =(Financials!C43-Financials!B43)/Financials!B43 -> 0.0091570035 | D43: =(Financials!D43-Financials!C43)/Financials!C43 -> 0.22800298 | E43: =(Financials!E43-Financials!D43)/Financials!D43 -> 0.080501027 | F43: =(Financials!F43-Financials!E43)/Financials!E43 -> 0.0924878 | G43: =(Financials!G43-Financials!F43)/Financials!F43 -> 0.0062806694 | H43: =(Financials!H43-Financials!G43)/Financials!G43 -> 0.064602849 | I43: =(Financials!I43-Financials!H43)/Financials!H43 -> 0.060682581 | J43: =(Financials!J43-Financials!I43)/Financials!I43 -> 0.057210877 | ... L43: =(Financials!L43-Financials!K43)/Financials!K43 -> 0.051336828
A44: Total shareholders equity | C44: =(Financials!C44-Financials!B44)/Financials!B44 -> -2.0587291 | D44: =(Financials!D44-Financials!C44)/Financials!C44 -> -1.5140952 | E44: =(Financials!E44-Financials!D44)/Financials!D44 -> -1.9209906 | F44: =(Financials!F44-Financials!E44)/Financials!E44 -> -0.33162612 | G44: =(Financials!G44-Financials!F44)/Financials!F44 -> 5.3601533 | H44: =(Financials!H44-Financials!G44)/Financials!G44 -> 0.57303024 | I44: =(Financials!I44-Financials!H44)/Financials!H44 -> 0.52733355 | J44: =(Financials!J44-Financials!I44)/Financials!I44 -> 0.46168041 | ... L44: =(Financials!L44-Financials!K44)/Financials!K44 -> 0.33703521
A46: Total liabilities & equity | C46: =(Financials!C46-Financials!B46)/Financials!B46 -> 0.37756655 | D46: =(Financials!D46-Financials!C46)/Financials!C46 -> 0.018347714 | E46: =(Financials!E46-Financials!D46)/Financials!D46 -> 0.063567811 | F46: =(Financials!F46-Financials!E46)/Financials!E46 -> 0.0011119105 | G46: =(Financials!G46-Financials!F46)/Financials!F46 -> 0.25596498 | H46: =(Financials!H46-Financials!G46)/Financials!G46 -> 0.0056332269 | I46: =(Financials!I46-Financials!H46)/Financials!H46 -> 0.028043942 | J46: =(Financials!J46-Financials!I46)/Financials!I46 -> 0.058400653 | ... L46: =(Financials!L46-Financials!K46)/Financials!K46 -> 0.083874113
A52: The Home Depot, Inc. | B52: ACTUAL | H52: FORECAST
A53: Year-over-Year Statement of Earnings | B53: 43499 | C53: 43863 | D53: 44227 | E53: 44591 | F53: 44955 | G53: 45319 | H53: 45688 | I53: 46053 | J53: 46418 | K53: 46783 | L53: 47149
A55: Net sales | C55: =(Financials!C55-Financials!B55)/Financials!B55 -> 0.19854842 | D55: =(Financials!D55-Financials!C55)/Financials!C55 -> 0.14417531 | E55: =(Financials!E55-Financials!D55)/Financials!D55 -> 0.041321275 | F55: =(Financials!F55-Financials!E55)/Financials!E55 -> -0.030075666 | G55: =(Financials!G55-Financials!F55)/Financials!F55 -> 0.044835559 | H55: =(Financials!H55-Financials!G55)/Financials!G55 -> 0.075808601 | I55: =(Financials!I55-Financials!H55)/Financials!H55 -> 0.075845539 | J55: =(Financials!J55-Financials!I55)/Financials!I55 -> 0.075882286 | ... L55: =(Financials!L55-Financials!K55)/Financials!K55 -> 0.075955201
A57: Cost of sales | C57: =(Financials!C57-Financials!B57)/Financials!B57 -> 0.20101028 | D57: =(Financials!D57-Financials!C57)/Financials!C57 -> 0.14976449 | E57: =(Financials!E57-Financials!D57)/Financials!D57 -> 0.042860703 | F57: =(Financials!F57-Financials!E57)/Financials!E57 -> -0.027870968 | G57: =(Financials!G57-Financials!F57)/Financials!F57 -> 0.044214376 | H57: =(Financials!H57-Financials!G57)/Financials!G57 -> 0.071753135 | I57: =(Financials!I57-Financials!H57)/Financials!H57 -> 0.075845539 | J57: =(Financials!J57-Financials!I57)/Financials!I57 -> 0.075882286 | ... L57: =(Financials!L57-Financials!K57)/Financials!K57 -> 0.075955201
A59: Gross profit | C59: =(Financials!C59-Financials!B59)/Financials!B59 -> 0.19378793 | D59: =(Financials!D59-Financials!C59)/Financials!C59 -> 0.13330212 | E59: =(Financials!E59-Financials!D59)/Financials!D59 -> 0.038282971 | F59: =(Financials!F59-Financials!E59)/Financials!E59 -> -0.034446171 | G59: =(Financials!G59-Financials!F59)/Financials!F59 -> 0.046075353 | H59: =(Financials!H59-Financials!G59)/Financials!G59 -> 0.083888342 | I59: =(Financials!I59-Financials!H59)/Financials!H59 -> 0.075845539 | J59: =(Financials!J59-Financials!I59)/Financials!I59 -> 0.075882286 | ... L59: =(Financials!L59-Financials!K59)/Financials!K59 -> 0.075955201
A61: Operating expenses:
A62: Selling, general and administrative | C62: =(Financials!C62-Financials!B62)/Financials!B62 -> 0.23844985 | D62: =(Financials!D62-Financials!C62)/Financials!C62 -> 0.039227717 | E62: =(Financials!E62-Financials!D62)/Financials!D62 -> 0.034558766 | F62: =(Financials!F62-Financials!E62)/Financials!E62 -> 0.011946431 | G62: =(Financials!G62-Financials!F62)/Financials!F62 -> 0.080833145 | H62: =(Financials!H62-Financials!G62)/Financials!G62 -> 0.048215779 | I62: =(Financials!I62-Financials!H62)/Financials!H62 -> 0.075845539 | J62: =(Financials!J62-Financials!I62)/Financials!I62 -> 0.075882286 | ... L62: =(Financials!L62-Financials!K62)/Financials!K62 -> 0.075955201
A63: Depreciation and amortization | C63: =(Financials!C63-Financials!B63)/Financials!B63 -> 0.069884364 | D63: =(Financials!D63-Financials!C63)/Financials!C63 -> 0.1212406 | E63: =(Financials!E63-Financials!D63)/Financials!D63 -> 0.028918692 | F63: =(Financials!F63-Financials!E63)/Financials!E63 -> 0.088798371 | G63: =(Financials!G63-Financials!F63)/Financials!F63 -> 0.13505425 | H63: =(Financials!H63-Financials!G63)/Financials!G63 -> 0.091351168 | I63: =(Financials!I63-Financials!H63)/Financials!H63 -> 0.053657602 | J63: =(Financials!J63-Financials!I63)/Financials!I63 -> 0.052496325 | ... L63: =(Financials!L63-Financials!K63)/Financials!K63 -> 0.0464585
A64: Tradename impairment loss
A65: Total operating expenses | C65: =(Financials!C65-Financials!B65)/Financials!B65 -> 0.22301993 | D65: =(Financials!D65-Financials!C65)/Financials!C65 -> 0.04579492 | E65: =(Financials!E65-Financials!D65)/Financials!D65 -> 0.034074554 | F65: =(Financials!F65-Financials!E65)/Financials!E65 -> 0.01851143 | G65: =(Financials!G65-Financials!F65)/Financials!F65 -> 0.085784565 | H65: =(Financials!H65-Financials!G65)/Financials!G65 -> 0.052333606 | I65: =(Financials!I65-Financials!H65)/Financials!H65 -> 0.073648882 | J65: =(Financials!J65-Financials!I65)/Financials!I65 -> 0.073610131 | ... L65: =(Financials!L65-Financials!K65)/Financials!K65 -> 0.073203782
A67: Operating income (loss) | C67: =(Financials!C67-Financials!B67)/Financials!B67 -> 0.15369564 | D67: =(Financials!D67-Financials!C67)/Financials!C67 -> 0.26053179 | E67: =(Financials!E67-Financials!D67)/Financials!D67 -> 0.043359375 | F67: =(Financials!F67-Financials!E67)/Financials!E67 -> -0.09775781 | G67: =(Financials!G67-Financials!F67)/Financials!F67 -> -0.0075153304 | H67: =(Financials!H67-Financials!G67)/Financials!G67 -> 0.13047724 | I67: =(Financials!I67-Financials!H67)/Financials!H67 -> 0.0788646 | J67: =(Financials!J67-Financials!I67)/Financials!I67 -> 0.078990012 | ... L67: =(Financials!L67-Financials!K67)/Financials!K67 -> 0.079680531
A69: Interest and other (income) expense:
A70: Interest and investment income | C70: =(Financials!C70-Financials!B70)/Financials!B70 -> -0.35616438 | D70: =(Financials!D70-Financials!C70)/Financials!C70 -> -0.063829787 | E70: =(Financials!E70-Financials!D70)/Financials!D70 -> 0.25 | F70: =(Financials!F70-Financials!E70)/Financials!E70 -> 2.2363636 | G70: =(Financials!G70-Financials!F70)/Financials!F70 -> 0.12921348 | H70: =(Financials!H70-Financials!G70)/Financials!G70 -> -1 | J70: =(Financials!J70-Financials!I70)/Financials!I70 -> 0.48331244 | K70: =(Financials!K70-Financials!J70)/Financials!J70 -> 2.3063261 | L70: =(Financials!L70-Financials!K70)/Financials!K70 -> 1.2739177
A71: Interest expense | C71: =(Financials!C71-Financials!B71)/Financials!B71 -> 0.12156536 | D71: =(Financials!D71-Financials!C71)/Financials!C71 -> 0 | E71: =(Financials!E71-Financials!D71)/Financials!D71 -> 0.20044543 | F71: =(Financials!F71-Financials!E71)/Financials!E71 -> 0.20160792 | G71: =(Financials!G71-Financials!F71)/Financials!F71 -> 0.19454452 | H71: =(Financials!H71-Financials!G71)/Financials!G71 -> -0.055722921 | I71: =(Financials!I71-Financials!H71)/Financials!H71 -> -0.086343679 | J71: =(Financials!J71-Financials!I71)/Financials!I71 -> -0.099927813 | ... L71: =(Financials!L71-Financials!K71)/Financials!K71 -> -0.068395576
A72: Other
A73: Interest and other,net | C73: =(Financials!C73-Financials!B73)/Financials!B73 -> 0.15248227 | D73: =(Financials!D73-Financials!C73)/Financials!C73 -> 0.0023076923 | E73: =(Financials!E73-Financials!D73)/Financials!D73 -> 0.19877206 | F73: =(Financials!F73-Financials!E73)/Financials!E73 -> 0.12996159 | G73: =(Financials!G73-Financials!F73)/Financials!F73 -> 0.20113314 | H73: =(Financials!H73-Financials!G73)/Financials!G73 -> 0.033805236 | I73: =(Financials!I73-Financials!H73)/Financials!H73 -> -0.055519874 | J73: =(Financials!J73-Financials!I73)/Financials!I73 -> -0.080893338 | ... L73: =(Financials!L73-Financials!K73)/Financials!K73 -> 0.1564425
A75: Earnings before income taxes | C75: =(Financials!C75-Financials!B75)/Financials!B75 -> 0.15378865 | D75: =(Financials!D75-Financials!C75)/Financials!C75 -> 0.28030392 | E75: =(Financials!E75-Financials!D75)/Financials!D75 -> 0.034043336 | F75: =(Financials!F75-Financials!E75)/Financials!E75 -> -0.11358277 | G75: =(Financials!G75-Financials!F75)/Financials!F75 -> -0.025998795 | H75: =(Financials!H75-Financials!G75)/Financials!G75 -> 0.14103813 | I75: =(Financials!I75-Financials!H75)/Financials!H75 -> 0.092165698 | J75: =(Financials!J75-Financials!I75)/Financials!I75 -> 0.092675048 | ... L75: =(Financials!L75-Financials!K75)/Financials!K75 -> 0.074369842
A77: Provision for income taxes | C77: =(Financials!C77-Financials!B77)/Financials!B77 -> 0.18399079 | D77: =(Financials!D77-Financials!C77)/Financials!C77 -> 0.28988327 | E77: =(Financials!E77-Financials!D77)/Financials!D77 -> 0.012820513 | F77: =(Financials!F77-Financials!E77)/Financials!E77 -> -0.11001489 | G77: =(Financials!G77-Financials!F77)/Financials!F77 -> -0.037858189 | H77: =(Financials!H77-Financials!G77)/Financials!G77 -> 0.15384212 | I77: =(Financials!I77-Financials!H77)/Financials!H77 -> 0.092165698 | J77: =(Financials!J77-Financials!I77)/Financials!I77 -> 0.092675048 | ... L77: =(Financials!L77-Financials!K77)/Financials!K77 -> 0.074369842
A79: Net earnings | C79: =(Financials!C79-Financials!B79)/Financials!B79 -> 0.14445828 | D79: =(Financials!D79-Financials!C79)/Financials!C79 -> 0.27724234 | E79: =(Financials!E79-Financials!D79)/Financials!D79 -> 0.040893324 | F79: =(Financials!F79-Financials!E79)/Financials!E79 -> -0.1147033 | G79: =(Financials!G79-Financials!F79)/Financials!F79 -> -0.022254507 | H79: =(Financials!H79-Financials!G79)/Financials!G79 -> 0.13706013 | I79: =(Financials!I79-Financials!H79)/Financials!H79 -> 0.092165698 | J79: =(Financials!J79-Financials!I79)/Financials!I79 -> 0.092675048 | ... L79: =(Financials!L79-Financials!K79)/Financials!K79 -> 0.074369842

Sheet Common Size
A1: The Home Depot, Inc. | B1: ACTUAL | H1: FORECAST
A2: Common Size Balance Sheet | B2: 43863 | C2: 44227 | D2: 44591 | E2: 44955 | F2: 45319 | G2: 45690 | H2: 46053 | I2: 46418 | J2: 46783 | K2: 47149 | L2: 47514
A4: ASSETS
A5: Cash and cash equivalents | B5: =Financials!B5/Financials!B$17 -> 0.041630885 | C5: =Financials!C5/Financials!C$17 -> 0.1118573 | D5: =Financials!D5/Financials!D$17 -> 0.032597807 | E5: =Financials!E5/Financials!E$17 -> 0.036065145 | F5: =Financials!F5/Financials!F$17 -> 0.04913106 | G5: =Financials!G5/Financials!G$17 -> 0.017259855 | H5: =Financials!H5/Financials!H$17 -> 0.026898279 | I5: =Financials!I5/Financials!I$17 -> 0.026164522 | ... L5: =Financials!L5/Financials!L$17 -> 0.021043576
A6: Short-term investments | B6: =Financials!B6/Financials!B$17 -> 0 | C6: =Financials!C6/Financials!C$17 -> 0 | D6: =Financials!D6/Financials!D$17 -> 0 | E6: =Financials!E6/Financials!E$17 -> 0 | F6: =Financials!F6/Financials!F$17 -> 0 | G6: =Financials!G6/Financials!G$17 -> 0 | H6: =Financials!H6/Financials!H$17 -> 0.0099842151 | I6: =Financials!I6/Financials!I$17 -> 0.014405717 | ... L6: =Financials!L6/Financials!L$17 -> 0.13923386
A7: Receivables, net | B7: =Financials!B7/Financials!B$17 -> 0.041103911 | C7: =Financials!C7/Financials!C$17 -> 0.042391012 | D7: =Financials!D7/Financials!D$17 -> 0.047665424 | E7: =Financials!E7/Financials!E$17 -> 0.043390673 | F7: =Financials!F7/Financials!F$17 -> 0.043486215 | G7: =Financials!G7/Financials!G$17 -> 0.051009686 | H7: =Financials!H7/Financials!H$17 -> 0.038863228 | I7: =Financials!I7/Financials!I$17 -> 0.040670276 | ... L7: =Financials!L7/Financials!L$17 -> 0.04074012
A8: Merchandise inventories | B8: =Financials!B8/Financials!B$17 -> 0.28360918 | C8: =Financials!C8/Financials!C$17 -> 0.23557331 | D8: =Financials!D8/Financials!D$17 -> 0.30702877 | E8: =Financials!E8/Financials!E$17 -> 0.32554124 | F8: =Financials!F8/Financials!F$17 -> 0.27408859 | G8: =Financials!G8/Financials!G$17 -> 0.24397882 | H8: =Financials!H8/Financials!H$17 -> 0.24081642 | I8: =Financials!I8/Financials!I$17 -> 0.25201381 | ... L8: =Financials!L8/Financials!L$17 -> 0.2524466
A9: Other current assets | B9: =Financials!B9/Financials!B$17 -> 0.020298228 | C9: =Financials!C9/Financials!C$17 -> 0.013643898 | D9: =Financials!D9/Financials!D$17 -> 0.016945851 | E9: =Financials!E9/Financials!E$17 -> 0.019765845 | F9: =Financials!F9/Financials!F$17 -> 0.022357246 | G9: =Financials!G9/Financials!G$17 -> 0.017374296 | H9: =Financials!H9/Financials!H$17 -> 0.016510792 | I9: =Financials!I9/Financials!I$17 -> 0.017278505 | ... L9: =Financials!L9/Financials!L$17 -> 0.017308177
A10: Total current assets | B10: =Financials!B10/Financials!B$17 -> 0.3866422 | C10: =Financials!C10/Financials!C$17 -> 0.40346552 | D10: =Financials!D10/Financials!D$17 -> 0.40423785 | E10: =Financials!E10/Financials!E$17 -> 0.4247629 | F10: =Financials!F10/Financials!F$17 -> 0.38906311 | G10: =Financials!G10/Financials!G$17 -> 0.32962266 | H10: =Financials!H10/Financials!H$17 -> 0.33307294 | I10: =Financials!I10/Financials!I$17 -> 0.35053283 | ... L10: =Financials!L10/Financials!L$17 -> 0.47077233
A12: Net property and equipment | B12: =Financials!B12/Financials!B$17 -> 0.44441408 | C12: =Financials!C12/Financials!C$17 -> 0.35002338 | D12: =Financials!D12/Financials!D$17 -> 0.3505899 | E12: =Financials!E12/Financials!E$17 -> 0.33528681 | F12: =Financials!F12/Financials!F$17 -> 0.34174833 | G12: =Financials!G12/Financials!G$17 -> 0.27780148 | H12: =Financials!H12/Financials!H$17 -> 0.28135856 | I12: =Financials!I12/Financials!I$17 -> 0.27939214 | ... L12: =Financials!L12/Financials!L$17 -> 0.24255146
A13: Operating lease right-of-use assets | B13: =Financials!B13/Financials!B$17 -> 0.10920056 | C13: =Financials!C13/Financials!C$17 -> 0.084470325 | D13: =Financials!D13/Financials!D$17 -> 0.083031888 | E13: =Financials!E13/Financials!E$17 -> 0.090797305 | F13: =Financials!F13/Financials!F$17 -> 0.10301842 | G13: =Financials!G13/Financials!G$17 -> 0.089389195 | H13: =Financials!H13/Financials!H$17 -> 0.088888466 | I13: =Financials!I13/Financials!I$17 -> 0.086463683 | ... L13: =Financials!L13/Financials!L$17 -> 0.069540924
A14: Goodwill | B14: =Financials!B14/Financials!B$17 -> 0.043992505 | C14: =Financials!C14/Financials!C$17 -> 0.10096202 | D14: =Financials!D14/Financials!D$17 -> 0.10363682 | E14: =Financials!E14/Financials!E$17 -> 0.097377199 | F14: =Financials!F14/Financials!F$17 -> 0.11047955 | G14: =Financials!G14/Financials!G$17 -> 0.20261343 | H14: =Financials!H14/Financials!H$17 -> 0.20147845 | I14: =Financials!I14/Financials!I$17 -> 0.19598234 | ... L14: =Financials!L14/Financials!L$17 -> 0.15762447
A15: Intangible assets | B15: =Financials!B15/Financials!B$17 -> 0 | C15: =Financials!C15/Financials!C$17 -> 0.051175245 | D15: =Financials!D15/Financials!D$17 -> 0.048736713 | E15: =Financials!E15/Financials!E$17 -> 0.043469161 | F15: =Financials!F15/Financials!F$17 -> 0.047118777 | G15: =Financials!G15/Financials!G$17 -> 0.093457069 | H15: =Financials!H15/Financials!H$17 -> 0.087212496 | I15: =Financials!I15/Financials!I$17 -> 0.07926844 | ... L15: =Financials!L15/Financials!L$17 -> 0.051135889
A16: Other assets | B16: =Financials!B16/Financials!B$17 -> 0.015750644 | C16: =Financials!C16/Financials!C$17 -> 0.0099035151 | D16: =Financials!D16/Financials!D$17 -> 0.0097668206 | E16: =Financials!E16/Financials!E$17 -> 0.0083066257 | F16: =Financials!F16/Financials!F$17 -> 0.0085718019 | G16: =Financials!G16/Financials!G$17 -> 0.0071161789 | H16: =Financials!H16/Financials!H$17 -> 0.0079890929 | I16: =Financials!I16/Financials!I$17 -> 0.0083605667 | ... L16: =Financials!L16/Financials!L$17 -> 0.0083749245
A17: Total assets | B17: =Financials!B17/Financials!B$17 -> 1 | C17: =Financials!C17/Financials!C$17 -> 1 | D17: =Financials!D17/Financials!D$17 -> 1 | E17: =Financials!E17/Financials!E$17 -> 1 | F17: =Financials!F17/Financials!F$17 -> 1 | G17: =Financials!G17/Financials!G$17 -> 1 | H17: =Financials!H17/Financials!H$17 -> 1 | I17: =Financials!I17/Financials!I$17 -> 1 | ... L17: =Financials!L17/Financials!L$17 -> 1
A19: LIABILITIES
A21: Short-term debt | B21: =Financials!B21/Financials!B$17 -> 0.019010071 | C21: =Financials!C21/Financials!C$17 -> 0 | D21: =Financials!D21/Financials!D$17 -> 0.0143998 | E21: =Financials!E21/Financials!E$17 -> 0 | F21: =Financials!F21/Financials!F$17 -> 0 | G21: =Financials!G21/Financials!G$17 -> 0.0032875914 | H21: =Financials!H21/Financials!H$17 -> 0.0032691754 | I21: =Financials!I21/Financials!I$17 -> 0.0031799958 | ... L21: =Financials!L21/Financials!L$17 -> 0.0025576038
A22: Accounts payable | B22: =Financials!B22/Financials!B$17 -> 0.15198298 | C22: =Financials!C22/Financials!C$17 -> 0.16443519 | D22: =Financials!D22/Financials!D$17 -> 0.18729479 | E22: =Financials!E22/Financials!E$17 -> 0.14968932 | F22: =Financials!F22/Financials!F$17 -> 0.13115118 | G22: =Financials!G22/Financials!G$17 -> 0.12420021 | H22: =Financials!H22/Financials!H$17 -> 0.13306171 | I22: =Financials!I22/Financials!I$17 -> 0.13924876 | ... L22: =Financials!L22/Financials!L$17 -> 0.13948789
A23: Accrued salaries and related expenses | B23: =Financials!B23/Financials!B$17 -> 0.029159185 | C23: =Financials!C23/Financials!C$17 -> 0.034896077 | D23: =Financials!D23/Financials!D$17 -> 0.033752574 | E23: =Financials!E23/Financials!E$17 -> 0.026044869 | F23: =Financials!F23/Financials!F$17 -> 0.027387952 | G23: =Financials!G23/Financials!G$17 -> 0.024084728 | H23: =Financials!H23/Financials!H$17 -> 0.0268082 | I23: =Financials!I23/Financials!I$17 -> 0.028054718 | ... L23: =Financials!L23/Financials!L$17 -> 0.028102897
A24: Sales taxes payable | B24: =Financials!B24/Financials!B$17 -> 0.011808104 | C24: =Financials!C24/Financials!C$17 -> 0.010966124 | D24: =Financials!D24/Financials!D$17 -> 0.011798097 | E24: =Financials!E24/Financials!E$17 -> 0.0069069265 | F24: =Financials!F24/Financials!F$17 -> 0.0058669803 | G24: =Financials!G24/Financials!G$17 -> 0.0065335678 | H24: =Financials!H24/Financials!H$17 -> 0.0076340221 | I24: =Financials!I24/Financials!I$17 -> 0.007988986 | ... L24: =Financials!L24/Financials!L$17 -> 0.0080027056
A25: Deferred revenue | B25: =Financials!B25/Financials!B$17 -> 0.041299087 | C25: =Financials!C25/Financials!C$17 -> 0.0399966 | D25: =Financials!D25/Financials!D$17 -> 0.050030608 | E25: =Financials!E25/Financials!E$17 -> 0.040081104 | F25: =Financials!F25/Financials!F$17 -> 0.036090422 | G25: =Financials!G25/Financials!G$17 -> 0.027153841 | H25: =Financials!H25/Financials!H$17 -> 0.035152009 | I25: =Financials!I25/Financials!I$17 -> 0.036786494 | ... L25: =Financials!L25/Financials!L$17 -> 0.036849668
A26: Income taxes payable | B26: =Financials!B26/Financials!B$17 -> 0.001073464 | C26: =Financials!C26/Financials!C$17 -> 0.0027344469 | D26: =Financials!D26/Financials!D$17 -> 0.0021982303 | E26: =Financials!E26/Financials!E$17 -> 0.00065406501 | F26: =Financials!F26/Financials!F$17 -> 0.00036586959 | G26: =Financials!G26/Financials!G$17 -> 0.0086559369 | H26: =Financials!H26/Financials!H$17 -> 0.002998113 | I26: =Financials!I26/Financials!I$17 -> 0.0031851131 | ... L26: =Financials!L26/Financials!L$17 -> 0.0032537119
A27: Current installments of long-term debt | B27: =Financials!B27/Financials!B$17 -> 0.035892732 | C27: =Financials!C27/Financials!C$17 -> 0.020062056 | D27: =Financials!D27/Financials!D$17 -> 0.034044744 | E27: =Financials!E27/Financials!E$17 -> 0.016103081 | F27: =Financials!F27/Financials!F$17 -> 0.017875343 | G27: =Financials!G27/Financials!G$17 -> 0.047670076 | H27: =Financials!H27/Financials!H$17 -> 0.050123908 | I27: =Financials!I27/Financials!I$17 -> 0.037928494 | ... L27: =Financials!L27/Financials!L$17 -> 0.031937673
A28: Current operating lease liabilities | B28: =Financials!B28/Financials!B$17 -> 0.016160512 | C28: =Financials!C28/Financials!C$17 -> 0.011731202 | D28: =Financials!D28/Financials!D$17 -> 0.011547665 | E28: =Financials!E28/Financials!E$17 -> 0.012361829 | F28: =Financials!F28/Financials!F$17 -> 0.01372011 | G28: =Financials!G28/Financials!G$17 -> 0.013254403 | H28: =Financials!H28/Financials!H$17 -> 0.013180157 | I28: =Financials!I28/Financials!I$17 -> 0.012820616 | ... L28: =Financials!L28/Financials!L$17 -> 0.010311352
A29: Other accrued expenses | B29: =Financials!B29/Financials!B$17 -> 0.052248419 | C29: =Financials!C29/Financials!C$17 -> 0.043396948 | D29: =Financials!D29/Financials!D$17 -> 0.054134899 | E29: =Financials!E29/Financials!E$17 -> 0.050467656 | F29: =Financials!F29/Financials!F$17 -> 0.055207108 | G29: =Financials!G29/Financials!G$17 -> 0.043342107 | H29: =Financials!H29/Financials!H$17 -> 0.045093991 | I29: =Financials!I29/Financials!I$17 -> 0.047190755 | ... L29: =Financials!L29/Financials!L$17 -> 0.047271796
A30: Total current liabilities | B30: =Financials!B30/Financials!B$17 -> 0.35863455 | C30: =Financials!C30/Financials!C$17 -> 0.32821864 | D30: =Financials!D30/Financials!D$17 -> 0.3992014 | E30: =Financials!E30/Financials!E$17 -> 0.30230885 | F30: =Financials!F30/Financials!F$17 -> 0.28766497 | G30: =Financials!G30/Financials!G$17 -> 0.29818246 | H30: =Financials!H30/Financials!H$17 -> 0.31732128 | I30: =Financials!I30/Financials!I$17 -> 0.31638393 | ... L30: =Financials!L30/Financials!L$17 -> 0.3077753
A32: Long-term debt | B32: =Financials!B32/Financials!B$17 -> 0.55956749 | C32: =Financials!C32/Financials!C$17 -> 0.50753036 | D32: =Financials!D32/Financials!D$17 -> 0.50926596 | E32: =Financials!E32/Financials!E$17 -> 0.54891752 | F32: =Financials!F32/Financials!F$17 -> 0.558513 | G32: =Financials!G32/Financials!G$17 -> 0.5044268 | H32: =Financials!H32/Financials!H$17 -> 0.45147726 | I32: =Financials!I32/Financials!I$17 -> 0.40123295 | ... L32: =Financials!L32/Financials!L$17 -> 0.23675641
A33: Long-term operating lease liabilities | B33: =Financials!B33/Financials!B$17 -> 0.09887579 | C33: =Financials!C33/Financials!C$17 -> 0.075884445 | D33: =Financials!D33/Financials!D$17 -> 0.074475486 | E33: =Financials!E33/Financials!E$17 -> 0.081444176 | F33: =Financials!F33/Financials!F$17 -> 0.092538874 | G33: =Financials!G33/Financials!G$17 -> 0.079411979 | H33: =Financials!H33/Financials!H$17 -> 0.078967139 | I33: =Financials!I33/Financials!I$17 -> 0.076813 | ... L33: =Financials!L33/Financials!L$17 -> 0.061779082
... A36: Total liabilities | B36: =Financials!B36/Financials!B$17 -> 1.0608166 | C36: =Financials!C36/Financials!C$17 -> 0.95325938 | D36: =Financials!D36/Financials!D$17 -> 1.0235962 | E36: =Financials!E36/Financials!E$17 -> 0.97956701 | F36: =Financials!F36/Financials!F$17 -> 0.98635829 | G36: =Financials!G36/Financials!G$17 -> 0.93091897 | H36: =Financials!H36/Financials!H$17 -> 0.89194216 | I36: =Financials!I36/Financials!I$17 -> 0.83946176 | ... L36: =Financials!L36/Financials!L$17 -> 0.64843749
A38: SHAREHOLDERS' EQUITY
A39: Common stock | B39: =Financials!B39/Financials!B$17 -> 0.0017370599 | C39: =Financials!C39/Financials!C$17 -> 0.0012609626 | D39: =Financials!D39/Financials!D$17 -> 0.0012521565 | E39: =Financials!E39/Financials!E$17 -> 0.001177317 | F39: =Financials!F39/Financials!F$17 -> 0.0011760094 | G39: =Financials!G39/Financials!G$17 -> 0.00093633933 | H39: =Financials!H39/Financials!H$17 -> 0.00093109426 | I39: =Financials!I39/Financials!I$17 -> 0.00090569501 | ... L39: =Financials!L39/Financials!L$17 -> 0.00072843146
A40: Paid-in capital | B40: =Financials!B40/Financials!B$17 -> 0.21471231 | C40: =Financials!C40/Financials!C$17 -> 0.16350009 | D40: =Financials!D40/Financials!D$17 -> 0.1687907 | E40: =Financials!E40/Financials!E$17 -> 0.16471973 | F40: =Financials!F40/Financials!F$17 -> 0.17178884 | G40: =Financials!G40/Financials!G$17 -> 0.14687003 | H40: =Financials!H40/Financials!H$17 -> 0.15322903 | I40: =Financials!I40/Financials!I$17 -> 0.15658585 | ... L40: =Financials!L40/Financials!L$17 -> 0.14715713
A41: Retained earnings | B41: =Financials!B41/Financials!B$17 -> 1.0096221 | C41: =Financials!C41/Financials!C$17 -> 0.82364942 | D41: =Financials!D41/Financials!D$17 -> 0.9402304 | E41: =Financials!E41/Financials!E$17 -> 1.0058997 | F41: =Financials!F41/Financials!F$17 -> 1.0931138 | G41: =Financials!G41/Financials!G$17 -> 0.93148077 | H41: =Financials!H41/Financials!H$17 -> 1.022587 | I41: =Financials!I41/Financials!I$17 -> 1.1049756 | ... L41: =Financials!L41/Financials!L$17 -> 1.2404777
A42: Accumulated other comp. income (loss) | B42: =Financials!B42/Financials!B$17 -> -0.014423452 | C42: =Financials!C42/Financials!C$17 -> -0.0095068078 | D42: =Financials!D42/Financials!D$17 -> -0.0097946463 | E42: =Financials!E42/Financials!E$17 -> -0.0093923736 | F42: =Financials!F42/Financials!F$17 -> -0.0062328499 | G42: =Financials!G42/Financials!G$17 -> -0.011745857 | H42: =Financials!H42/Financials!H$17 -> -0.01168006 | I42: =Financials!I42/Financials!I$17 -> -0.011361441 | ... L42: =Financials!L42/Financials!L$17 -> -0.009137768
A43: Treasury stock | B43: =Financials!B43/Financials!B$17 -> -1.2724647 | C43: =Financials!C43/Financials!C$17 -> -0.93216305 | D43: =Financials!D43/Financials!D$17 -> -1.1240748 | E43: =Financials!E43/Financials!E$17 -> -1.1419714 | F43: =Financials!F43/Financials!F$17 -> -1.2462041 | G43: =Financials!G43/Financials!G$17 -> -0.99846024 | H43: =Financials!H43/Financials!H$17 -> -1.0570092 | I43: =Financials!I43/Financials!I$17 -> -1.0905675 | ... L43: =Financials!L43/Financials!L$17 -> -1.027663
A44: Total shareholders equity | B44: =Financials!B44/Financials!B$17 -> -0.060816613 | C44: =Financials!C44/Financials!C$17 -> 0.046740624 | D44: =Financials!D44/Financials!D$17 -> -0.023596193 | E44: =Financials!E44/Financials!E$17 -> 0.020432991 | F44: =Financials!F44/Financials!F$17 -> 0.013641709 | G44: =Financials!G44/Financials!G$17 -> 0.069081035 | H44: =Financials!H44/Financials!H$17 -> 0.10805784 | I44: =Financials!I44/Financials!I$17 -> 0.16053824 | ... L44: =Financials!L44/Financials!L$17 -> 0.35156251
A46: Total liabilities & equity | B46: =Financials!B46/Financials!B$17 -> 1 | C46: =Financials!C46/Financials!C$17 -> 1 | D46: =Financials!D46/Financials!D$17 -> 1 | E46: =Financials!E46/Financials!E$17 -> 1 | F46: =Financials!F46/Financials!F$17 -> 1 | G46: =Financials!G46/Financials!G$17 -> 1 | H46: =Financials!H46/Financials!H$17 -> 1 | I46: =Financials!I46/Financials!I$17 -> 1 | ... L46: =Financials!L46/Financials!L$17 -> 1
A52: The Home Depot, Inc. | B52: ACTUAL | H52: FORECAST
A53: Common Size Statement of Earnings | B53: 42764 | C53: 43128 | D53: 43499 | E53: 43863 | F53: 44227 | G53: 44591 | H53: 44957 | I53: 45322 | J53: 45688 | K53: 46053 | L53: 46418
A55: Net sales | B55: =Financials!B55/Financials!B$55 -> 1 | C55: =Financials!C55/Financials!C$55 -> 1 | D55: =Financials!D55/Financials!D$55 -> 1 | E55: =Financials!E55/Financials!E$55 -> 1 | F55: =Financials!F55/Financials!F$55 -> 1 | G55: =Financials!G55/Financials!G$55 -> 1 | H55: =Financials!H55/Financials!H$55 -> 1 | I55: =Financials!I55/Financials!I$55 -> 1 | ... L55: =Financials!L55/Financials!L$55 -> 1
A57: Cost of sales | B57: =Financials!B57/Financials!B$55 -> 0.65913359 | C57: =Financials!C57/Financials!C$55 -> 0.66048747 | D57: =Financials!D57/Financials!D$55 -> 0.66371389 | E57: =Financials!E57/Financials!E$55 -> 0.66469508 | F57: =Financials!F57/Financials!F$55 -> 0.66620598 | G57: =Financials!G57/Financials!G$55 -> 0.6658099 | H57: =Financials!H57/Financials!H$55 -> 0.6633 | I57: =Financials!I57/Financials!I$55 -> 0.6633 | ... L57: =Financials!L57/Financials!L$55 -> 0.6633
A59: Gross profit | B59: =Financials!B59/Financials!B$55 -> 0.34086641 | C59: =Financials!C59/Financials!C$55 -> 0.33951253 | D59: =Financials!D59/Financials!D$55 -> 0.33628611 | E59: =Financials!E59/Financials!E$55 -> 0.33530492 | F59: =Financials!F59/Financials!F$55 -> 0.33379402 | G59: =Financials!G59/Financials!G$55 -> 0.3341901 | H59: =Financials!H59/Financials!H$55 -> 0.3367 | I59: =Financials!I59/Financials!I$55 -> 0.3367 | ... L59: =Financials!L59/Financials!L$55 -> 0.3367
A61: Operating expenses:
A62: Selling, general and administrative | B62: =Financials!B62/Financials!B$55 -> 0.17908823 | C62: =Financials!C62/Financials!C$55 -> 0.18505034 | D62: =Financials!D62/Financials!D$55 -> 0.1680769 | E62: =Financials!E62/Financials!E$55 -> 0.16698538 | F62: =Financials!F62/Financials!F$55 -> 0.17422004 | G62: =Financials!G62/Financials!G$55 -> 0.18022243 | H62: =Financials!H62/Financials!H$55 -> 0.1756 | I62: =Financials!I62/Financials!I$55 -> 0.1756 | ... L62: =Financials!L62/Financials!L$55 -> 0.1756
A63: Depreciation and amortization | B63: =Financials!B63/Financials!B$55 -> 0.018044908 | C63: =Financials!C63/Financials!C$55 -> 0.016107789 | D63: =Financials!D63/Financials!D$55 -> 0.015784912 | E63: =Financials!E63/Financials!E$55 -> 0.015596907 | F63: =Financials!F63/Financials!F$55 -> 0.017508466 | G63: =Financials!G63/Financials!G$55 -> 0.019020274 | H63: =Financials!H63/Financials!H$55 -> 0.019295066 | I63: =Financials!I63/Financials!I$55 -> 0.01889713 | ... L63: =Financials!L63/Financials!L$55 -> 0.017569603
A64: Tradename impairment loss | B64: =Financials!B64/Financials!B$55 -> 0 | C64: =Financials!C64/Financials!C$55 -> 0 | D64: =Financials!D64/Financials!D$55 -> 0 | E64: =Financials!E64/Financials!E$55 -> 0 | F64: =Financials!F64/Financials!F$55 -> 0 | G64: =Financials!G64/Financials!G$55 -> 0 | H64: =Financials!H64/Financials!H$55 -> 0 | I64: =Financials!I64/Financials!I$55 -> 0 | ... L64: =Financials!L64/Financials!L$55 -> 0
A65: Total operating expenses | B65: =Financials!B65/Financials!B$55 -> 0.19713314 | C65: =Financials!C65/Financials!C$55 -> 0.20115813 | D65: =Financials!D65/Financials!D$55 -> 0.18386181 | E65: =Financials!E65/Financials!E$55 -> 0.18258229 | F65: =Financials!F65/Financials!F$55 -> 0.19172851 | G65: =Financials!G65/Financials!G$55 -> 0.1992427 | H65: =Financials!H65/Financials!H$55 -> 0.19489507 | I65: =Financials!I65/Financials!I$55 -> 0.19449713 | ... L65: =Financials!L65/Financials!L$55 -> 0.1931696
A67: Operating income (loss) | B67: =Financials!B67/Financials!B$55 -> 0.14373327 | C67: =Financials!C67/Financials!C$55 -> 0.1383544 | D67: =Financials!D67/Financials!D$55 -> 0.1524243 | E67: =Financials!E67/Financials!E$55 -> 0.15272263 | F67: =Financials!F67/Financials!F$55 -> 0.14206551 | G67: =Financials!G67/Financials!G$55 -> 0.1349474 | H67: =Financials!H67/Financials!H$55 -> 0.14180493 | I67: =Financials!I67/Financials!I$55 -> 0.14220287 | ... L67: =Financials!L67/Financials!L$55 -> 0.1435304
A69: Interest and other (income) expense:
A70: Interest and investment income | B70: =Financials!B70/Financials!B$55 -> -0.0006622817 | C70: =Financials!C70/Financials!C$55 -> -0.00035576414 | D70: =Financials!D70/Financials!D$55 -> -0.00029108807 | E70: =Financials!E70/Financials!E$55 -> -0.00034942155 | F70: =Financials!F70/Financials!F$55 -> -0.001165921 | G70: =Financials!G70/Financials!G$55 -> -0.0012600775 | H70: =Financials!H70/Financials!H$55 -> 0 | I70: =Financials!I70/Financials!I$55 -> 0.00036591237 | ... L70: =Financials!L70/Financials!L$55 -> 0.0032763606
A71: Interest expense | B71: =Financials!B71/Financials!B$55 -> 0.010895895 | C71: =Financials!C71/Financials!C$55 -> 0.010196049 | D71: =Financials!D71/Financials!D$55 -> 0.0089112644 | E71: =Financials!E71/Financials!E$55 -> 0.010272994 | F71: =Financials!F71/Financials!F$55 -> 0.01272688 | G71: =Financials!G71/Financials!G$55 -> 0.014550447 | H71: =Financials!H71/Financials!H$55 -> 0.012771467 | I71: =Financials!I71/Financials!I$55 -> 0.010846103 | ... L71: =Financials!L71/Financials!L$55 -> 0.006671393
A72: Other | B72: =Financials!B72/Financials!B$55 -> 0 | C72: =Financials!C72/Financials!C$55 -> 0 | D72: =Financials!D72/Financials!D$55 -> 0 | E72: =Financials!E72/Financials!E$55 -> 0 | F72: =Financials!F72/Financials!F$55 -> 0 | G72: =Financials!G72/Financials!G$55 -> 0 | H72: =Financials!H72/Financials!H$55 -> 0 | I72: =Financials!I72/Financials!I$55 -> 0 | ... L72: =Financials!L72/Financials!L$55 -> 0
A73: Interest and other,net | B73: =Financials!B73/Financials!B$55 -> 0.010233613 | C73: =Financials!C73/Financials!C$55 -> 0.0098402846 | D73: =Financials!D73/Financials!D$55 -> 0.0086201764 | E73: =Financials!E73/Financials!E$55 -> 0.009923572 | F73: =Financials!F73/Financials!F$55 -> 0.011560959 | G73: =Financials!G73/Financials!G$55 -> 0.013290369 | H73: =Financials!H73/Financials!H$55 -> 0.012771467 | I73: =Financials!I73/Financials!I$55 -> 0.011212015 | ... L73: =Financials!L73/Financials!L$55 -> 0.0099477535
A75: Earnings before income taxes | B75: =Financials!B75/Financials!B$55 -> 0.13349966 | C75: =Financials!C75/Financials!C$55 -> 0.12851412 | D75: =Financials!D75/Financials!D$55 -> 0.14380412 | E75: =Financials!E75/Financials!E$55 -> 0.14279906 | F75: =Financials!F75/Financials!F$55 -> 0.13050456 | G75: =Financials!G75/Financials!G$55 -> 0.12165703 | H75: =Financials!H75/Financials!H$55 -> 0.12903347 | I75: =Financials!I75/Financials!I$55 -> 0.13099085 | ... L75: =Financials!L75/Financials!L$55 -> 0.13358264
A77: Provision for income taxes | B77: =Financials!B77/Financials!B$55 -> 0.031508279 | C77: =Financials!C77/Financials!C$55 -> 0.031125577 | D77: =Financials!D77/Financials!D$55 -> 0.035089344 | E77: =Financials!E77/Financials!E$55 -> 0.034128956 | F77: =Financials!F77/Financials!F$55 -> 0.031316115 | G77: =Financials!G77/Financials!G$55 -> 0.028837594 | H77: =Financials!H77/Financials!H$55 -> 0.030929322 | I77: =Financials!I77/Financials!I$55 -> 0.031398508 | ... L77: =Financials!L77/Financials!L$55 -> 0.03201976
A79: Net earnings | B79: =Financials!B79/Financials!B$55 -> 0.10199138 | C79: =Financials!C79/Financials!C$55 -> 0.09738854 | D79: =Financials!D79/Financials!D$55 -> 0.10871478 | E79: =Financials!E79/Financials!E$55 -> 0.1086701 | F79: =Financials!F79/Financials!F$55 -> 0.09918844 | G79: =Financials!G79/Financials!G$55 -> 0.092819439 | H79: =Financials!H79/Financials!H$55 -> 0.098104145 | I79: =Financials!I79/Financials!I$55 -> 0.099592347 | ... L79: =Financials!L79/Financials!L$55 -> 0.10156288
